Workbook

Sheet readme
A1: Implied Rates of Depreciation for Private Nonresidential Fixed Assets
A3: Worksheets in this file contain implied rates of depreciation calculated from unpublished fixed-cost investment and net capital
A4: stock of nonresidential fixed assets. The unpublished data that underlie these estimates are of significantly less quality than that
A5: of the higher level aggregates in which they are included. Compared to these aggregates, the detailed estimates are more likely
A6: to be either based on judgmental trends, on trends in the higher level aggregate, or on less reliable source data. Estimates are
A7: presented for detailed industries by selected major asset-types. The industries are identified by the NAICS-based BEA codes
A8: listed below.
A10: INDUSTRY TITLE | B10: BEA CODE | D10: 2017 NAICS Codes
A12: Agriculture, forestry, fishing, and hunting | B12: -------- | D12: 11
A13: Farms | B13: 110C | D13: 111112
A14: Forestry, fishing, and related activities | B14: 113F | D14: 113114115
A16: Mining | B16: -------- | D16: 21
A17: Oil and gas extraction | B17: 2110 | D17: 211
A18: Mining, except oil and gas | B18: 2120 | D18: 212
A19: Support activities for mining | B19: 2130 | D19: 213
A21: Utilities | B21: -------- | D21: 22
A22: Electric power | B22: 2211 | D22: 221
A23: Natural gas distribution | B23: 2212 | D23: 222
A24: Water, Sewage, and other systems | B24: 2213 | D24: 223
A26: Construction | B26: 2300 | D26: 23
A28: Manufacturing | B28: -------- | D28: 31-33
A29: Durable goods | B29: -------- | D29: --------
A30: Wood products | B30: 3210 | D30: 321
A31: Nonmetallic mineral products | B31: 3270 | D31: 327
A32: Primary metals | B32: 3310 | D32: 331
A33: Fabricated metal products | B33: 3320 | D33: 332
A34: Machinery | B34: 3330 | D34: 333
A35: Computer and electronic products | B35: 3340 | D35: 334
A36: Electrical equipment, appliances, and components | B36: 3350 | D36: 335
A37: Motor vehicles, bodies and trailers, and parts | B37: 336M | D37: 3361-3
A38: Other transportation equipment | B38: 336O | D38: 3364-9
A39: Furniture and related products | B39: 3370 | D39: 337
A40: Medical equipment and supplies | B40: 3380 | D40: 338
A41: Other manufacturing | B41: 3390 | D41: 339
A42: Nondurable goods | B42: -------- | D42: --------
A43: Food manufacturing | B43: 3110 | D43: 311
A44: Beverage, and tobacco product manufacturing | B44: 3120 | D44: 312
A45: Textile mills and textile product mills | B45: 313T | D45: 313, 314
A46: Apparel and leather and allied products | B46: 315A | D46: 315, 316
A47: Paper products | B47: 3220 | D47: 322
A48: Printing and related support activities | B48: 3230 | D48: 323
A49: Petroleum and coal products | B49: 3240 | D49: 324
A50: Chemical products | B50: 3250 | D50: 325
A51: Plastics and rubber products | B51: 3260 | D51: 326
A53: Wholesale trade | B53: -------- | D53: 42
A54: Durable goods | B54: 4210 | D54: 423, pt. 425
A55: Nondurable goods | B55: 4220 | D55: 424, pt. 425
A57: Retail trade | B57: -------- | D57: 44-45
A58: Motor vehicle and parts dealers | B58: 4410 | D58: 441
A59: Food and beverage stores | B59: 4450 | D59: 445
A60: General merchandise stores | B60: 4520 | D60: 452
A61: Other retail | B61: 442R | D61: 442-4, 446-8, 45 ex. 452
A63: Transportation and warehousing | B63: -------- | D63: 48-49
A64: Air transportation | B64: 4810 | D64: 481
A65: Railroad transportation | B65: 4820 | D65: 482
A66: Water transportation | B66: 4830 | D66: 483
A67: Truck transportation | B67: 4840 | D67: 484
A68: Transit and ground passenger transportation | B68: 4850 | D68: 485
A69: Pipeline transportation | B69: 4860 | D69: 486
A70: Other transportation and support activities | B70: 487S | D70: 487488492
A71: Warehousing and storage | B71: 4930 | D71: 493
A73: Information | B73: -------- | D73: 51
A74: Publishing industries (including software) | B74: 5110 | D74: 511
A75: Motion picture and sound recording industries | B75: 5120 | D75: 512
A76: Broadcasting and telecommunications | B76: 5130 | D76: 515, 517
A77: Information and data processing services | B77: 5140 | D77: 518, 519
A79: Finance and insurance | B79: -------- | D79: 52
A80: Federal Reserve banks | B80: 5210 | D80: 521
A81: Depository credit intermediation | B81: 5221 | D81: 5221
A82: Other intermediation | B82: 5223 | D82: 5223
A83: Nondepository credit intermediation | B83: 5229 | D83: 5222
A84: Securities, commodity contracts, and investments | B84: 5230 | D84: 523
A85: Insurance carriers | B85: 524A | D85: 5241
A86: Insurance agencies and brokers and related services | B86: 5243 | D86: 5242
A87: Funds, trusts, and other financial vehicles | B87: 5250 | D87: 525
A89: Real estate and rental and leasing | B89: -------- | D89: 53
A90: Real estate | B90: 5310 | D90: 531
A91: Rental and leasing services and lessors of intangible assets | B91: 5320 | D91: 532533
A93: Professional, scientific, and technical services | B93: -------- | D93: 54
A94: Legal services | B94: 5411 | D94: 5411
A95: Computer systems design and related services | B95: 5415 | D95: 5415
A96: Miscellaneous professional, scientific, and technical services | B96: 5412 | D96: 541 ex. 5411,5415
A98: Management of companies and enterprises | B98: 5500 | D98: 55
A100: Administrative and waste management services | B100: --------
A101: Administrative and support services | B101: 5610 | D101: 561
A102: Waste management and remediation services | B102: 5620 | D102: 562
A104: Educational services | B104: 6100 | D104: 61
A106: Health care and social assistance | B106: -------- | D106: 62
A107: Ambulatory health care services | B107: 6210 | D107: 621
A108: Hospitals | B108: 622H | D108: 622
A109: Nursing and residential care facilities | B109: 6230 | D109: 623
A110: Social assistance | B110: 6240 | D110: 624
A112: Arts, entertainment, and recreation | B112: -------- | D112: 71
A113: Performing arts, spectator sports, museums, and related activities | B113: 711A | D113: 711712
A114: Amusements, gambling, and recreation industries | B114: 7130 | D114: 713
A116: Accommodation and food services | B116: -------- | D116: 72
A117: Accommodation | B117: 7210 | D117: 721
A118: Food services and drinking places | B118: 7220 | D118: 722
A120: Other services, except government | B120: 8100 | D120: 81

Sheet 110C
A1: 110C - Farms
A2: Implied Depreciation Rates for Private Nonresidential Fixed Assets
A3: Updated September 26, 2025
A5: Asset Codes | B5: NIPA Asset Types | C5: 1925 | D5: 1926 | E5: 1927 | F5: 1928 | G5: 1929 | H5: 1930 | I5: 1931 | J5: 1932 | K5: 1933 | L5: 1934 | M5: 1935 | N5: 1936 | O5: 1937 | P5: 1938 | Q5: 1939 | R5: 1940 | S5: 1941 | T5: 1942 | U5: 1943 | V5: 1944 | W5: 1945 | X5: 1946 | Y5: 1947 | Z5: 1948 | AA5: 1949 | AB5: 1950 | AC5: 1951 | AD5: 1952 | AE5: 1953 | AF5: 1954 | AG5: 1955 | AH5: 1956 | AI5: 1957 | AJ5: 1958 | AK5: 1959 | AL5: 1960 | AM5: 1961 | AN5: 1962 | AO5: 1963 | AP5: 1964 | AQ5: 1965 | AR5: 1966 | AS5: 1967 | AT5: 1968 | AU5: 1969 | AV5: 1970 | AW5: 1971 | AX5: 1972 | AY5: 1973 | AZ5: 1974 | BA5: 1975 | BB5: 1976 | BC5: 1977 | BD5: 1978 | BE5: 1979 | BF5: 1980 | BG5: 1981 | BH5: 1982 | BI5: 1983 | BJ5: 1984 | BK5: 1985 | BL5: 1986 | BM5: 1987 | BN5: 1988 | BO5: 1989 | BP5: 1990 | BQ5: 1991 | BR5: 1992 | BS5: 1993 | BT5: 1994 | BU5: 1995 | BV5: 1996 | BW5: 1997 | BX5: 1998 | BY5: 1999 | BZ5: 2000 | CA5: 2001 | CB5: 2002 | CC5: 2003 | CD5: 2004 | CE5: 2005 | CF5: 2006 | CG5: 2007 | CH5: 2008 | CI5: 2009 | CJ5: 2010 | CK5: 2011 | CL5: 2012 | CM5: 2013 | CN5: 2014 | CO5: 2015 | CP5: 2016 | CQ5: 2017 | CR5: 2018 | CS5: 2019 | CT5: 2020 | CU5: 2021 | CV5: 2022 | CW5: 2023 | CX5: 2024
A7: ES00 | B7: Equipment, structures, and intellectual property products | C7: =Datasets!B2 -> 0.0419 | D7: =Datasets!C2 -> 0.0434 | E7: =Datasets!D2 -> 0.0442 | F7: =Datasets!E2 -> 0.0451 | G7: =Datasets!F2 -> 0.0459 | H7: =Datasets!G2 -> 0.0466 | I7: =Datasets!H2 -> 0.0466 | J7: =Datasets!I2 -> 0.0456 | ... CX7: =Datasets!CW2 -> 0.0755
A8: EQ00 | B8: Equipment | C8: =Datasets!B3 -> 0.1349 | D8: =Datasets!C3 -> 0.1381 | E8: =Datasets!D3 -> 0.1384 | F8: =Datasets!E3 -> 0.1391 | G8: =Datasets!F3 -> 0.1395 | H8: =Datasets!G3 -> 0.1392 | I8: =Datasets!H3 -> 0.1389 | J8: =Datasets!I3 -> 0.1385 | ... CX8: =Datasets!CW3 -> 0.1331
A9: EP00 | B9: Information | C9: =Datasets!B4 -> 0 | D9: =Datasets!C4 -> 0 | E9: =Datasets!D4 -> 0 | F9: =Datasets!E4 -> 0 | G9: =Datasets!F4 -> 0 | H9: =Datasets!G4 -> 0 | I9: =Datasets!H4 -> 0 | J9: =Datasets!I4 -> 0 | ... CX9: =Datasets!CW4 -> 0.135
A10: EP11 | B10: Computers | C10: =Datasets!B5 -> 0 | D10: =Datasets!C5 -> 0 | E10: =Datasets!D5 -> 0 | F10: =Datasets!E5 -> 0 | G10: =Datasets!F5 -> 0 | H10: =Datasets!G5 -> 0 | I10: =Datasets!H5 -> 0 | J10: =Datasets!I5 -> 0 | ... CX10: =Datasets!CW5 -> 0.34
A11: EI00 | B11: Industrial | C11: =Datasets!B6 -> 0.1225 | D11: =Datasets!C6 -> 0.1225 | E11: =Datasets!D6 -> 0.1225 | F11: =Datasets!E6 -> 0.1225 | G11: =Datasets!F6 -> 0.1225 | H11: =Datasets!G6 -> 0.1225 | I11: =Datasets!H6 -> 0.1225 | J11: =Datasets!I6 -> 0.1225 | ... CX11: =Datasets!CW6 -> 0.0912
A12: ET00 | B12: Transportation | C12: =Datasets!B7 -> 0.2157 | D12: =Datasets!C7 -> 0.2254 | E12: =Datasets!D7 -> 0.2249 | F12: =Datasets!E7 -> 0.2277 | G12: =Datasets!F7 -> 0.2305 | H12: =Datasets!G7 -> 0.2326 | I12: =Datasets!H7 -> 0.2333 | J12: =Datasets!I7 -> 0.2307 | ... CX12: =Datasets!CW7 -> 0.1923
A13: EO00 | B13: Other equipment | C13: =Datasets!B8 -> 0.1245 | D13: =Datasets!C8 -> 0.1248 | E13: =Datasets!D8 -> 0.125 | F13: =Datasets!E8 -> 0.125 | G13: =Datasets!F8 -> 0.125 | H13: =Datasets!G8 -> 0.125 | I13: =Datasets!H8 -> 0.125 | J13: =Datasets!I8 -> 0.125 | ... CX13: =Datasets!CW8 -> 0.1254
A14: ST00 | B14: Structures | C14: =Datasets!B9 -> 0.0239 | D14: =Datasets!C9 -> 0.0239 | E14: =Datasets!D9 -> 0.0239 | F14: =Datasets!E9 -> 0.0239 | G14: =Datasets!F9 -> 0.0239 | H14: =Datasets!G9 -> 0.0239 | I14: =Datasets!H9 -> 0.0239 | J14: =Datasets!I9 -> 0.0239 | ... CX14: =Datasets!CW9 -> 0.0248
A15: SCHC | B15: Commercial and healthcare | C15: =Datasets!B10 -> 0 | D15: =Datasets!C10 -> 0 | E15: =Datasets!D10 -> 0 | F15: =Datasets!E10 -> 0 | G15: =Datasets!F10 -> 0 | H15: =Datasets!G10 -> 0 | I15: =Datasets!H10 -> 0 | J15: =Datasets!I10 -> 0 | ... CX15: =Datasets!CW10 -> 0
A16: IP00 | B16: Intellectual property products | C16: =Datasets!B11 -> 0 | D16: =Datasets!C11 -> 0 | E16: =Datasets!D11 -> 0 | F16: =Datasets!E11 -> 0 | G16: =Datasets!F11 -> 0 | H16: =Datasets!G11 -> 0 | I16: =Datasets!H11 -> 0 | J16: =Datasets!I11 -> 0 | ... CX16: =Datasets!CW11 -> 0.5191

Sheet 113F
A1: 113F - Forestry, Fishing, and Related Activities
A2: Implied Depreciation Rates for Private Nonresidential Fixed Assets
A3: Updated September 26, 2025
A5: Asset Codes | B5: NIPA Asset Types | C5: 1925 | D5: 1926 | E5: 1927 | F5: 1928 | G5: 1929 | H5: 1930 | I5: 1931 | J5: 1932 | K5: 1933 | L5: 1934 | M5: 1935 | N5: 1936 | O5: 1937 | P5: 1938 | Q5: 1939 | R5: 1940 | S5: 1941 | T5: 1942 | U5: 1943 | V5: 1944 | W5: 1945 | X5: 1946 | Y5: 1947 | Z5: 1948 | AA5: 1949 | AB5: 1950 | AC5: 1951 | AD5: 1952 | AE5: 1953 | AF5: 1954 | AG5: 1955 | AH5: 1956 | AI5: 1957 | AJ5: 1958 | AK5: 1959 | AL5: 1960 | AM5: 1961 | AN5: 1962 | AO5: 1963 | AP5: 1964 | AQ5: 1965 | AR5: 1966 | AS5: 1967 | AT5: 1968 | AU5: 1969 | AV5: 1970 | AW5: 1971 | AX5: 1972 | AY5: 1973 | AZ5: 1974 | BA5: 1975 | BB5: 1976 | BC5: 1977 | BD5: 1978 | BE5: 1979 | BF5: 1980 | BG5: 1981 | BH5: 1982 | BI5: 1983 | BJ5: 1984 | BK5: 1985 | BL5: 1986 | BM5: 1987 | BN5: 1988 | BO5: 1989 | BP5: 1990 | BQ5: 1991 | BR5: 1992 | BS5: 1993 | BT5: 1994 | BU5: 1995 | BV5: 1996 | BW5: 1997 | BX5: 1998 | BY5: 1999 | BZ5: 2000 | CA5: 2001 | CB5: 2002 | CC5: 2003 | CD5: 2004 | CE5: 2005 | CF5: 2006 | CG5: 2007 | CH5: 2008 | CI5: 2009 | CJ5: 2010 | CK5: 2011 | CL5: 2012 | CM5: 2013 | CN5: 2014 | CO5: 2015 | CP5: 2016 | CQ5: 2017 | CR5: 2018 | CS5: 2019 | CT5: 2020 | CU5: 2021 | CV5: 2022 | CW5: 2023 | CX5: 2024
A7: ES00 | B7: Equipment, structures, and intellectual property products | C7: =Datasets!B12 -> 0.0292 | D7: =Datasets!C12 -> 0.0328 | E7: =Datasets!D12 -> 0.0344 | F7: =Datasets!E12 -> 0.0359 | G7: =Datasets!F12 -> 0.0375 | H7: =Datasets!G12 -> 0.0385 | I7: =Datasets!H12 -> 0.0384 | J7: =Datasets!I12 -> 0.038 | ... CX7: =Datasets!CW12 -> 0.0947
A8: EQ00 | B8: Equipment | C8: =Datasets!B13 -> 0.1257 | D8: =Datasets!C13 -> 0.1436 | E8: =Datasets!D13 -> 0.1445 | F8: =Datasets!E13 -> 0.1461 | G8: =Datasets!F13 -> 0.1465 | H8: =Datasets!G13 -> 0.1418 | I8: =Datasets!H13 -> 0.1371 | J8: =Datasets!I13 -> 0.135 | ... CX8: =Datasets!CW13 -> 0.1222
A9: EP00 | B9: Information | C9: =Datasets!B14 -> 0 | D9: =Datasets!C14 -> 0 | E9: =Datasets!D14 -> 0 | F9: =Datasets!E14 -> 0 | G9: =Datasets!F14 -> 0 | H9: =Datasets!G14 -> 0 | I9: =Datasets!H14 -> 0 | J9: =Datasets!I14 -> 0 | ... CX9: =Datasets!CW14 -> 0.158
A10: EP11 | B10: Computers | C10: =Datasets!B15 -> 0 | D10: =Datasets!C15 -> 0 | E10: =Datasets!D15 -> 0 | F10: =Datasets!E15 -> 0 | G10: =Datasets!F15 -> 0 | H10: =Datasets!G15 -> 0 | I10: =Datasets!H15 -> 0 | J10: =Datasets!I15 -> 0 | ... CX10: =Datasets!CW15 -> 0.3397
A11: EI00 | B11: Industrial | C11: =Datasets!B16 -> 0.1027 | D11: =Datasets!C16 -> 0.1028 | E11: =Datasets!D16 -> 0.1029 | F11: =Datasets!E16 -> 0.1029 | G11: =Datasets!F16 -> 0.1028 | H11: =Datasets!G16 -> 0.1026 | I11: =Datasets!H16 -> 0.1025 | J11: =Datasets!I16 -> 0.1025 | ... CX11: =Datasets!CW16 -> 0.1049
A12: ET00 | B12: Transportation | C12: =Datasets!B17 -> 0.2387 | D12: =Datasets!C17 -> 0.2522 | E12: =Datasets!D17 -> 0.2527 | F12: =Datasets!E17 -> 0.2596 | G12: =Datasets!F17 -> 0.2507 | H12: =Datasets!G17 -> 0.2168 | I12: =Datasets!H17 -> 0.1945 | J12: =Datasets!I17 -> 0.188 | ... CX12: =Datasets!CW17 -> 0.1278
A13: EO00 | B13: Other equipment | C13: =Datasets!B18 -> 0 | D13: =Datasets!C18 -> 0 | E13: =Datasets!D18 -> 0 | F13: =Datasets!E18 -> 0 | G13: =Datasets!F18 -> 0 | H13: =Datasets!G18 -> 0 | I13: =Datasets!H18 -> 0 | J13: =Datasets!I18 -> 0 | ... CX13: =Datasets!CW18 -> 0.1237
A14: ST00 | B14: Structures | C14: =Datasets!B19 -> 0.023 | D14: =Datasets!C19 -> 0.0231 | E14: =Datasets!D19 -> 0.0231 | F14: =Datasets!E19 -> 0.0231 | G14: =Datasets!F19 -> 0.0231 | H14: =Datasets!G19 -> 0.0231 | I14: =Datasets!H19 -> 0.0231 | J14: =Datasets!I19 -> 0.0231 | ... CX14: =Datasets!CW19 -> 0.0251
A15: SCHC | B15: Commercial and healthcare | C15: =Datasets!B20 -> 0.0247 | D15: =Datasets!C20 -> 0.0247 | E15: =Datasets!D20 -> 0.0247 | F15: =Datasets!E20 -> 0.0247 | G15: =Datasets!F20 -> 0.0247 | H15: =Datasets!G20 -> 0.0247 | I15: =Datasets!H20 -> 0.0247 | J15: =Datasets!I20 -> 0.0247 | ... CX15: =Datasets!CW20 -> 0.0243
A16: IP00 | B16: Intellectual property products | C16: =Datasets!B21 -> 0 | D16: =Datasets!C21 -> 0 | E16: =Datasets!D21 -> 0 | F16: =Datasets!E21 -> 0 | G16: =Datasets!F21 -> 0 | H16: =Datasets!G21 -> 0 | I16: =Datasets!H21 -> 0 | J16: =Datasets!I21 -> 0 | ... CX16: =Datasets!CW21 -> 0.4258

Sheet 2110
A1: 2110 - Oil and Gas Extraction
A2: Implied Depreciation Rates for Private Nonresidential Fixed Assets
A3: Updated September 26, 2025
A5: Asset Codes | B5: NIPA Asset Types | C5: 1925 | D5: 1926 | E5: 1927 | F5: 1928 | G5: 1929 | H5: 1930 | I5: 1931 | J5: 1932 | K5: 1933 | L5: 1934 | M5: 1935 | N5: 1936 | O5: 1937 | P5: 1938 | Q5: 1939 | R5: 1940 | S5: 1941 | T5: 1942 | U5: 1943 | V5: 1944 | W5: 1945 | X5: 1946 | Y5: 1947 | Z5: 1948 | AA5: 1949 | AB5: 1950 | AC5: 1951 | AD5: 1952 | AE5: 1953 | AF5: 1954 | AG5: 1955 | AH5: 1956 | AI5: 1957 | AJ5: 1958 | AK5: 1959 | AL5: 1960 | AM5: 1961 | AN5: 1962 | AO5: 1963 | AP5: 1964 | AQ5: 1965 | AR5: 1966 | AS5: 1967 | AT5: 1968 | AU5: 1969 | AV5: 1970 | AW5: 1971 | AX5: 1972 | AY5: 1973 | AZ5: 1974 | BA5: 1975 | BB5: 1976 | BC5: 1977 | BD5: 1978 | BE5: 1979 | BF5: 1980 | BG5: 1981 | BH5: 1982 | BI5: 1983 | BJ5: 1984 | BK5: 1985 | BL5: 1986 | BM5: 1987 | BN5: 1988 | BO5: 1989 | BP5: 1990 | BQ5: 1991 | BR5: 1992 | BS5: 1993 | BT5: 1994 | BU5: 1995 | BV5: 1996 | BW5: 1997 | BX5: 1998 | BY5: 1999 | BZ5: 2000 | CA5: 2001 | CB5: 2002 | CC5: 2003 | CD5: 2004 | CE5: 2005 | CF5: 2006 | CG5: 2007 | CH5: 2008 | CI5: 2009 | CJ5: 2010 | CK5: 2011 | CL5: 2012 | CM5: 2013 | CN5: 2014 | CO5: 2015 | CP5: 2016 | CQ5: 2017 | CR5: 2018 | CS5: 2019 | CT5: 2020 | CU5: 2021 | CV5: 2022 | CW5: 2023 | CX5: 2024
A7: ES00 | B7: Equipment, structures, and intellectual property products | C7: =Datasets!B22 -> 0.0537 | D7: =Datasets!C22 -> 0.0539 | E7: =Datasets!D22 -> 0.0539 | F7: =Datasets!E22 -> 0.0539 | G7: =Datasets!F22 -> 0.054 | H7: =Datasets!G22 -> 0.0541 | I7: =Datasets!H22 -> 0.0542 | J7: =Datasets!I22 -> 0.0542 | ... CX7: =Datasets!CW22 -> 0.0738
A8: EQ00 | B8: Equipment | C8: =Datasets!B23 -> 0.1695 | D8: =Datasets!C23 -> 0.1807 | E8: =Datasets!D23 -> 0.1739 | F8: =Datasets!E23 -> 0.1728 | G8: =Datasets!F23 -> 0.1688 | H8: =Datasets!G23 -> 0.1648 | I8: =Datasets!H23 -> 0.1644 | J8: =Datasets!I23 -> 0.1623 | ... CX8: =Datasets!CW23 -> 0.1283
A9: EP00 | B9: Information | C9: =Datasets!B24 -> 0 | D9: =Datasets!C24 -> 0 | E9: =Datasets!D24 -> 0 | F9: =Datasets!E24 -> 0 | G9: =Datasets!F24 -> 0 | H9: =Datasets!G24 -> 0 | I9: =Datasets!H24 -> 0 | J9: =Datasets!I24 -> 0 | ... CX9: =Datasets!CW24 -> 0.1807
A10: EP11 | B10: Computers | C10: =Datasets!B25 -> 0 | D10: =Datasets!C25 -> 0 | E10: =Datasets!D25 -> 0 | F10: =Datasets!E25 -> 0 | G10: =Datasets!F25 -> 0 | H10: =Datasets!G25 -> 0 | I10: =Datasets!H25 -> 0 | J10: =Datasets!I25 -> 0 | ... CX10: =Datasets!CW25 -> 0.3431
A11: EI00 | B11: Industrial | C11: =Datasets!B26 -> 0.0948 | D11: =Datasets!C26 -> 0.0952 | E11: =Datasets!D26 -> 0.0944 | F11: =Datasets!E26 -> 0.0925 | G11: =Datasets!F26 -> 0.0913 | H11: =Datasets!G26 -> 0.0909 | I11: =Datasets!H26 -> 0.0901 | J11: =Datasets!I26 -> 0.0895 | ... CX11: =Datasets!CW26 -> 0.106
A12: ET00 | B12: Transportation | C12: =Datasets!B27 -> 0.2387 | D12: =Datasets!C27 -> 0.2522 | E12: =Datasets!D27 -> 0.2527 | F12: =Datasets!E27 -> 0.2596 | G12: =Datasets!F27 -> 0.2648 | H12: =Datasets!G27 -> 0.2671 | I12: =Datasets!H27 -> 0.2669 | J12: =Datasets!I27 -> 0.2601 | ... CX12: =Datasets!CW27 -> 0.0754
A13: EO00 | B13: Other equipment | C13: =Datasets!B28 -> 0 | D13: =Datasets!C28 -> 0 | E13: =Datasets!D28 -> 0 | F13: =Datasets!E28 -> 0 | G13: =Datasets!F28 -> 0 | H13: =Datasets!G28 -> 0.15 | I13: =Datasets!H28 -> 0.15 | J13: =Datasets!I28 -> 0.15 | ... CX13: =Datasets!CW28 -> 0.1502
A14: ST00 | B14: Structures | C14: =Datasets!B29 -> 0.0533 | D14: =Datasets!C29 -> 0.0533 | E14: =Datasets!D29 -> 0.0532 | F14: =Datasets!E29 -> 0.0533 | G14: =Datasets!F29 -> 0.0533 | H14: =Datasets!G29 -> 0.0534 | I14: =Datasets!H29 -> 0.0534 | J14: =Datasets!I29 -> 0.0534 | ... CX14: =Datasets!CW29 -> 0.0703
A15: SCHC | B15: Commercial and healthcare | C15: =Datasets!B30 -> 0.0247 | D15: =Datasets!C30 -> 0.0247 | E15: =Datasets!D30 -> 0.0247 | F15: =Datasets!E30 -> 0.0247 | G15: =Datasets!F30 -> 0.0247 | H15: =Datasets!G30 -> 0.0247 | I15: =Datasets!H30 -> 0.0247 | J15: =Datasets!I30 -> 0.0247 | ... CX15: =Datasets!CW30 -> 0.0258
A16: IP00 | B16: Intellectual property products | C16: =Datasets!B31 -> 0.16 | D16: =Datasets!C31 -> 0.16 | E16: =Datasets!D31 -> 0.16 | F16: =Datasets!E31 -> 0.16 | G16: =Datasets!F31 -> 0.16 | H16: =Datasets!G31 -> 0.16 | I16: =Datasets!H31 -> 0.16 | J16: =Datasets!I31 -> 0.16 | ... CX16: =Datasets!CW31 -> 0.1682

Sheet 2120
A1: 2120 - Mining, Except Oil and Gas
A2: Implied Depreciation Rates for Private Nonresidential Fixed Assets
A3: Updated September 26, 2025
A5: Asset Codes | B5: NIPA Asset Types | C5: 1925 | D5: 1926 | E5: 1927 | F5: 1928 | G5: 1929 | H5: 1930 | I5: 1931 | J5: 1932 | K5: 1933 | L5: 1934 | M5: 1935 | N5: 1936 | O5: 1937 | P5: 1938 | Q5: 1939 | R5: 1940 | S5: 1941 | T5: 1942 | U5: 1943 | V5: 1944 | W5: 1945 | X5: 1946 | Y5: 1947 | Z5: 1948 | AA5: 1949 | AB5: 1950 | AC5: 1951 | AD5: 1952 | AE5: 1953 | AF5: 1954 | AG5: 1955 | AH5: 1956 | AI5: 1957 | AJ5: 1958 | AK5: 1959 | AL5: 1960 | AM5: 1961 | AN5: 1962 | AO5: 1963 | AP5: 1964 | AQ5: 1965 | AR5: 1966 | AS5: 1967 | AT5: 1968 | AU5: 1969 | AV5: 1970 | AW5: 1971 | AX5: 1972 | AY5: 1973 | AZ5: 1974 | BA5: 1975 | BB5: 1976 | BC5: 1977 | BD5: 1978 | BE5: 1979 | BF5: 1980 | BG5: 1981 | BH5: 1982 | BI5: 1983 | BJ5: 1984 | BK5: 1985 | BL5: 1986 | BM5: 1987 | BN5: 1988 | BO5: 1989 | BP5: 1990 | BQ5: 1991 | BR5: 1992 | BS5: 1993 | BT5: 1994 | BU5: 1995 | BV5: 1996 | BW5: 1997 | BX5: 1998 | BY5: 1999 | BZ5: 2000 | CA5: 2001 | CB5: 2002 | CC5: 2003 | CD5: 2004 | CE5: 2005 | CF5: 2006 | CG5: 2007 | CH5: 2008 | CI5: 2009 | CJ5: 2010 | CK5: 2011 | CL5: 2012 | CM5: 2013 | CN5: 2014 | CO5: 2015 | CP5: 2016 | CQ5: 2017 | CR5: 2018 | CS5: 2019 | CT5: 2020 | CU5: 2021 | CV5: 2022 | CW5: 2023 | CX5: 2024
A7: ES00 | B7: Equipment, structures, and intellectual property products | C7: =Datasets!B32 -> 0.0359 | D7: =Datasets!C32 -> 0.037 | E7: =Datasets!D32 -> 0.0377 | F7: =Datasets!E32 -> 0.0381 | G7: =Datasets!F32 -> 0.0388 | H7: =Datasets!G32 -> 0.0404 | I7: =Datasets!H32 -> 0.0419 | J7: =Datasets!I32 -> 0.0424 | ... CX7: =Datasets!CW32 -> 0.0654
A8: EQ00 | B8: Equipment | C8: =Datasets!B33 -> 0.1216 | D8: =Datasets!C33 -> 0.1279 | E8: =Datasets!D33 -> 0.1259 | F8: =Datasets!E33 -> 0.1257 | G8: =Datasets!F33 -> 0.1247 | H8: =Datasets!G33 -> 0.1291 | I8: =Datasets!H33 -> 0.1343 | J8: =Datasets!I33 -> 0.136 | ... CX8: =Datasets!CW33 -> 0.1417
A9: EP00 | B9: Information | C9: =Datasets!B34 -> 0 | D9: =Datasets!C34 -> 0 | E9: =Datasets!D34 -> 0 | F9: =Datasets!E34 -> 0 | G9: =Datasets!F34 -> 0 | H9: =Datasets!G34 -> 0 | I9: =Datasets!H34 -> 0 | J9: =Datasets!I34 -> 0 | ... CX9: =Datasets!CW34 -> 0.1517
A10: EP11 | B10: Computers | C10: =Datasets!B35 -> 0 | D10: =Datasets!C35 -> 0 | E10: =Datasets!D35 -> 0 | F10: =Datasets!E35 -> 0 | G10: =Datasets!F35 -> 0 | H10: =Datasets!G35 -> 0 | I10: =Datasets!H35 -> 0 | J10: =Datasets!I35 -> 0 | ... CX10: =Datasets!CW35 -> 0.3383
A11: EI00 | B11: Industrial | C11: =Datasets!B36 -> 0.0996 | D11: =Datasets!C36 -> 0.0997 | E11: =Datasets!D36 -> 0.0997 | F11: =Datasets!E36 -> 0.099 | G11: =Datasets!F36 -> 0.0987 | H11: =Datasets!G36 -> 0.0984 | I11: =Datasets!H36 -> 0.0978 | J11: =Datasets!I36 -> 0.0973 | ... CX11: =Datasets!CW36 -> 0.0994
A12: ET00 | B12: Transportation | C12: =Datasets!B37 -> 0.2387 | D12: =Datasets!C37 -> 0.2522 | E12: =Datasets!D37 -> 0.2527 | F12: =Datasets!E37 -> 0.2596 | G12: =Datasets!F37 -> 0.2659 | H12: =Datasets!G37 -> 0.2693 | I12: =Datasets!H37 -> 0.269 | J12: =Datasets!I37 -> 0.2621 | ... CX12: =Datasets!CW37 -> 0.1496
A13: EO00 | B13: Other equipment | C13: =Datasets!B38 -> 0 | D13: =Datasets!C38 -> 0 | E13: =Datasets!D38 -> 0 | F13: =Datasets!E38 -> 0 | G13: =Datasets!F38 -> 0.1633 | H13: =Datasets!G38 -> 0.1514 | I13: =Datasets!H38 -> 0.1508 | J13: =Datasets!I38 -> 0.1508 | ... CX13: =Datasets!CW38 -> 0.1522
A14: ST00 | B14: Structures | C14: =Datasets!B39 -> 0.0334 | D14: =Datasets!C39 -> 0.0335 | E14: =Datasets!D39 -> 0.0336 | F14: =Datasets!E39 -> 0.0337 | G14: =Datasets!F39 -> 0.0338 | H14: =Datasets!G39 -> 0.0339 | I14: =Datasets!H39 -> 0.034 | J14: =Datasets!I39 -> 0.0341 | ... CX14: =Datasets!CW39 -> 0.0413
A15: SCHC | B15: Commercial and healthcare | C15: =Datasets!B40 -> 0.0247 | D15: =Datasets!C40 -> 0.0247 | E15: =Datasets!D40 -> 0.0247 | F15: =Datasets!E40 -> 0.0247 | G15: =Datasets!F40 -> 0.0247 | H15: =Datasets!G40 -> 0.0247 | I15: =Datasets!H40 -> 0.0247 | J15: =Datasets!I40 -> 0.0247 | ... CX15: =Datasets!CW40 -> 0.0272
A16: IP00 | B16: Intellectual property products | C16: =Datasets!B41 -> 0.16 | D16: =Datasets!C41 -> 0.16 | E16: =Datasets!D41 -> 0.16 | F16: =Datasets!E41 -> 0.16 | G16: =Datasets!F41 -> 0.16 | H16: =Datasets!G41 -> 0.16 | I16: =Datasets!H41 -> 0.16 | J16: =Datasets!I41 -> 0.16 | ... CX16: =Datasets!CW41 -> 0.1838

Sheet 2130
A1: 2130 - Support Activites for Mining
A2: Implied Depreciation Rates for Private Nonresidential Fixed Assets
A3: Updated September 26, 2025
A5: Asset Codes | B5: NIPA Asset Types | C5: 1925 | D5: 1926 | E5: 1927 | F5: 1928 | G5: 1929 | H5: 1930 | I5: 1931 | J5: 1932 | K5: 1933 | L5: 1934 | M5: 1935 | N5: 1936 | O5: 1937 | P5: 1938 | Q5: 1939 | R5: 1940 | S5: 1941 | T5: 1942 | U5: 1943 | V5: 1944 | W5: 1945 | X5: 1946 | Y5: 1947 | Z5: 1948 | AA5: 1949 | AB5: 1950 | AC5: 1951 | AD5: 1952 | AE5: 1953 | AF5: 1954 | AG5: 1955 | AH5: 1956 | AI5: 1957 | AJ5: 1958 | AK5: 1959 | AL5: 1960 | AM5: 1961 | AN5: 1962 | AO5: 1963 | AP5: 1964 | AQ5: 1965 | AR5: 1966 | AS5: 1967 | AT5: 1968 | AU5: 1969 | AV5: 1970 | AW5: 1971 | AX5: 1972 | AY5: 1973 | AZ5: 1974 | BA5: 1975 | BB5: 1976 | BC5: 1977 | BD5: 1978 | BE5: 1979 | BF5: 1980 | BG5: 1981 | BH5: 1982 | BI5: 1983 | BJ5: 1984 | BK5: 1985 | BL5: 1986 | BM5: 1987 | BN5: 1988 | BO5: 1989 | BP5: 1990 | BQ5: 1991 | BR5: 1992 | BS5: 1993 | BT5: 1994 | BU5: 1995 | BV5: 1996 | BW5: 1997 | BX5: 1998 | BY5: 1999 | BZ5: 2000 | CA5: 2001 | CB5: 2002 | CC5: 2003 | CD5: 2004 | CE5: 2005 | CF5: 2006 | CG5: 2007 | CH5: 2008 | CI5: 2009 | CJ5: 2010 | CK5: 2011 | CL5: 2012 | CM5: 2013 | CN5: 2014 | CO5: 2015 | CP5: 2016 | CQ5: 2017 | CR5: 2018 | CS5: 2019 | CT5: 2020 | CU5: 2021 | CV5: 2022 | CW5: 2023 | CX5: 2024
A7: ES00 | B7: Equipment, structures, and intellectual property products | C7: =Datasets!B42 -> 0.0614 | D7: =Datasets!C42 -> 0.063 | E7: =Datasets!D42 -> 0.0633 | F7: =Datasets!E42 -> 0.0635 | G7: =Datasets!F42 -> 0.0639 | H7: =Datasets!G42 -> 0.0647 | I7: =Datasets!H42 -> 0.0653 | J7: =Datasets!I42 -> 0.0652 | ... CX7: =Datasets!CW42 -> 0.088
A8: EQ00 | B8: Equipment | C8: =Datasets!B43 -> 0.1363 | D8: =Datasets!C43 -> 0.1404 | E8: =Datasets!D43 -> 0.1339 | F8: =Datasets!E43 -> 0.131 | G8: =Datasets!F43 -> 0.127 | H8: =Datasets!G43 -> 0.1268 | I8: =Datasets!H43 -> 0.1297 | J8: =Datasets!I43 -> 0.1299 | ... CX8: =Datasets!CW43 -> 0.1244
A9: EP00 | B9: Information | C9: =Datasets!B44 -> 0 | D9: =Datasets!C44 -> 0 | E9: =Datasets!D44 -> 0 | F9: =Datasets!E44 -> 0 | G9: =Datasets!F44 -> 0 | H9: =Datasets!G44 -> 0 | I9: =Datasets!H44 -> 0 | J9: =Datasets!I44 -> 0 | ... CX9: =Datasets!CW44 -> 0.1753
A10: EP11 | B10: Computers | C10: =Datasets!B45 -> 0 | D10: =Datasets!C45 -> 0 | E10: =Datasets!D45 -> 0 | F10: =Datasets!E45 -> 0 | G10: =Datasets!F45 -> 0 | H10: =Datasets!G45 -> 0 | I10: =Datasets!H45 -> 0 | J10: =Datasets!I45 -> 0 | ... CX10: =Datasets!CW45 -> 0.3387
A11: EI00 | B11: Industrial | C11: =Datasets!B46 -> 0.0939 | D11: =Datasets!C46 -> 0.0944 | E11: =Datasets!D46 -> 0.0939 | F11: =Datasets!E46 -> 0.0922 | G11: =Datasets!F46 -> 0.0911 | H11: =Datasets!G46 -> 0.0907 | I11: =Datasets!H46 -> 0.09 | J11: =Datasets!I46 -> 0.0893 | ... CX11: =Datasets!CW46 -> 0.0762
A12: ET00 | B12: Transportation | C12: =Datasets!B47 -> 0.2387 | D12: =Datasets!C47 -> 0.2522 | E12: =Datasets!D47 -> 0.2527 | F12: =Datasets!E47 -> 0.2596 | G12: =Datasets!F47 -> 0.2659 | H12: =Datasets!G47 -> 0.2693 | I12: =Datasets!H47 -> 0.269 | J12: =Datasets!I47 -> 0.2621 | ... CX12: =Datasets!CW47 -> 0.0944
A13: EO00 | B13: Other equipment | C13: =Datasets!B48 -> 0 | D13: =Datasets!C48 -> 0 | E13: =Datasets!D48 -> 0 | F13: =Datasets!E48 -> 0 | G13: =Datasets!F48 -> 0.1633 | H13: =Datasets!G48 -> 0.1507 | I13: =Datasets!H48 -> 0.1504 | J13: =Datasets!I48 -> 0.1504 | ... CX13: =Datasets!CW48 -> 0.1504
A14: ST00 | B14: Structures | C14: =Datasets!B49 -> 0.0556 | D14: =Datasets!C49 -> 0.0556 | E14: =Datasets!D49 -> 0.0556 | F14: =Datasets!E49 -> 0.0556 | G14: =Datasets!F49 -> 0.0556 | H14: =Datasets!G49 -> 0.0556 | I14: =Datasets!H49 -> 0.0556 | J14: =Datasets!I49 -> 0.0555 | ... CX14: =Datasets!CW49 -> 0.0522
A15: SCHC | B15: Commercial and healthcare | C15: =Datasets!B50 -> 0.0247 | D15: =Datasets!C50 -> 0.0247 | E15: =Datasets!D50 -> 0.0247 | F15: =Datasets!E50 -> 0.0247 | G15: =Datasets!F50 -> 0.0247 | H15: =Datasets!G50 -> 0.0247 | I15: =Datasets!H50 -> 0.0247 | J15: =Datasets!I50 -> 0.0247 | ... CX15: =Datasets!CW50 -> 0.0256
A16: IP00 | B16: Intellectual property products | C16: =Datasets!B51 -> 0.16 | D16: =Datasets!C51 -> 0.16 | E16: =Datasets!D51 -> 0.16 | F16: =Datasets!E51 -> 0.16 | G16: =Datasets!F51 -> 0.16 | H16: =Datasets!G51 -> 0.16 | I16: =Datasets!H51 -> 0.16 | J16: =Datasets!I51 -> 0.16 | ... CX16: =Datasets!CW51 -> 0.2394

Sheet 2211
A1: 2211 - Electric Power
A2: Implied Depreciation Rates for Private Nonresidential Fixed Assets
A3: Updated September 26, 2025
A5: Asset Codes | B5: NIPA Asset Types | C5: 1925 | D5: 1926 | E5: 1927 | F5: 1928 | G5: 1929 | H5: 1930 | I5: 1931 | J5: 1932 | K5: 1933 | L5: 1934 | M5: 1935 | N5: 1936 | O5: 1937 | P5: 1938 | Q5: 1939 | R5: 1940 | S5: 1941 | T5: 1942 | U5: 1943 | V5: 1944 | W5: 1945 | X5: 1946 | Y5: 1947 | Z5: 1948 | AA5: 1949 | AB5: 1950 | AC5: 1951 | AD5: 1952 | AE5: 1953 | AF5: 1954 | AG5: 1955 | AH5: 1956 | AI5: 1957 | AJ5: 1958 | AK5: 1959 | AL5: 1960 | AM5: 1961 | AN5: 1962 | AO5: 1963 | AP5: 1964 | AQ5: 1965 | AR5: 1966 | AS5: 1967 | AT5: 1968 | AU5: 1969 | AV5: 1970 | AW5: 1971 | AX5: 1972 | AY5: 1973 | AZ5: 1974 | BA5: 1975 | BB5: 1976 | BC5: 1977 | BD5: 1978 | BE5: 1979 | BF5: 1980 | BG5: 1981 | BH5: 1982 | BI5: 1983 | BJ5: 1984 | BK5: 1985 | BL5: 1986 | BM5: 1987 | BN5: 1988 | BO5: 1989 | BP5: 1990 | BQ5: 1991 | BR5: 1992 | BS5: 1993 | BT5: 1994 | BU5: 1995 | BV5: 1996 | BW5: 1997 | BX5: 1998 | BY5: 1999 | BZ5: 2000 | CA5: 2001 | CB5: 2002 | CC5: 2003 | CD5: 2004 | CE5: 2005 | CF5: 2006 | CG5: 2007 | CH5: 2008 | CI5: 2009 | CJ5: 2010 | CK5: 2011 | CL5: 2012 | CM5: 2013 | CN5: 2014 | CO5: 2015 | CP5: 2016 | CQ5: 2017 | CR5: 2018 | CS5: 2019 | CT5: 2020 | CU5: 2021 | CV5: 2022 | CW5: 2023 | CX5: 2024
A7: ES00 | B7: Equipment, structures, and intellectual property products | C7: =Datasets!B52 -> 0.0256 | D7: =Datasets!C52 -> 0.0259 | E7: =Datasets!D52 -> 0.0258 | F7: =Datasets!E52 -> 0.0258 | G7: =Datasets!F52 -> 0.0258 | H7: =Datasets!G52 -> 0.0257 | I7: =Datasets!H52 -> 0.0256 | J7: =Datasets!I52 -> 0.0256 | ... CX7: =Datasets!CW52 -> 0.0403
A8: EQ00 | B8: Equipment | C8: =Datasets!B53 -> 0.0772 | D8: =Datasets!C53 -> 0.0841 | E8: =Datasets!D53 -> 0.0847 | F8: =Datasets!E53 -> 0.0861 | G8: =Datasets!F53 -> 0.0876 | H8: =Datasets!G53 -> 0.0879 | I8: =Datasets!H53 -> 0.0867 | J8: =Datasets!I53 -> 0.0848 | ... CX8: =Datasets!CW53 -> 0.0645
A9: EP00 | B9: Information | C9: =Datasets!B54 -> 0 | D9: =Datasets!C54 -> 0 | E9: =Datasets!D54 -> 0.11 | F9: =Datasets!E54 -> 0.11 | G9: =Datasets!F54 -> 0.11 | H9: =Datasets!G54 -> 0.11 | I9: =Datasets!H54 -> 0.1195 | J9: =Datasets!I54 -> 0.1288 | ... CX9: =Datasets!CW54 -> 0.1563
A10: EP11 | B10: Computers | C10: =Datasets!B55 -> 0 | D10: =Datasets!C55 -> 0 | E10: =Datasets!D55 -> 0 | F10: =Datasets!E55 -> 0 | G10: =Datasets!F55 -> 0 | H10: =Datasets!G55 -> 0 | I10: =Datasets!H55 -> 0 | J10: =Datasets!I55 -> 0 | ... CX10: =Datasets!CW55 -> 0.3373
A11: EI00 | B11: Industrial | C11: =Datasets!B56 -> 0.0523 | D11: =Datasets!C56 -> 0.0527 | E11: =Datasets!D56 -> 0.0529 | F11: =Datasets!E56 -> 0.0529 | G11: =Datasets!F56 -> 0.0528 | H11: =Datasets!G56 -> 0.053 | I11: =Datasets!H56 -> 0.0533 | J11: =Datasets!I56 -> 0.0534 | ... CX11: =Datasets!CW56 -> 0.0563
A12: ET00 | B12: Transportation | C12: =Datasets!B57 -> 0.2387 | D12: =Datasets!C57 -> 0.2522 | E12: =Datasets!D57 -> 0.2527 | F12: =Datasets!E57 -> 0.2596 | G12: =Datasets!F57 -> 0.2659 | H12: =Datasets!G57 -> 0.2693 | I12: =Datasets!H57 -> 0.269 | J12: =Datasets!I57 -> 0.2621 | ... CX12: =Datasets!CW57 -> 0.1596
A13: EO00 | B13: Other equipment | C13: =Datasets!B58 -> 0 | D13: =Datasets!C58 -> 0 | E13: =Datasets!D58 -> 0 | F13: =Datasets!E58 -> 0 | G13: =Datasets!F58 -> 0 | H13: =Datasets!G58 -> 0 | I13: =Datasets!H58 -> 0 | J13: =Datasets!I58 -> 0 | ... CX13: =Datasets!CW58 -> 0.1695
A14: ST00 | B14: Structures | C14: =Datasets!B59 -> 0.0237 | D14: =Datasets!C59 -> 0.0237 | E14: =Datasets!D59 -> 0.0237 | F14: =Datasets!E59 -> 0.0237 | G14: =Datasets!F59 -> 0.0237 | H14: =Datasets!G59 -> 0.0237 | I14: =Datasets!H59 -> 0.0237 | J14: =Datasets!I59 -> 0.0237 | ... CX14: =Datasets!CW59 -> 0.0236
A15: SCHC | B15: Commercial and healthcare | C15: =Datasets!B60 -> 0 | D15: =Datasets!C60 -> 0 | E15: =Datasets!D60 -> 0 | F15: =Datasets!E60 -> 0 | G15: =Datasets!F60 -> 0 | H15: =Datasets!G60 -> 0 | I15: =Datasets!H60 -> 0 | J15: =Datasets!I60 -> 0 | ... CX15: =Datasets!CW60 -> 0.0252
A16: IP00 | B16: Intellectual property products | C16: =Datasets!B61 -> 0.16 | D16: =Datasets!C61 -> 0.16 | E16: =Datasets!D61 -> 0.16 | F16: =Datasets!E61 -> 0.16 | G16: =Datasets!F61 -> 0.16 | H16: =Datasets!G61 -> 0.16 | I16: =Datasets!H61 -> 0.16 | J16: =Datasets!I61 -> 0.16 | ... CX16: =Datasets!CW61 -> 0.388

Sheet 2212
A1: 2212 - Natural Gas Distribution
A2: Implied Depreciation Rates for Private Nonresidential Fixed Assets
A3: Updated September 26, 2025
A5: Asset Codes | B5: NIPA Asset Types | C5: 1925 | D5: 1926 | E5: 1927 | F5: 1928 | G5: 1929 | H5: 1930 | I5: 1931 | J5: 1932 | K5: 1933 | L5: 1934 | M5: 1935 | N5: 1936 | O5: 1937 | P5: 1938 | Q5: 1939 | R5: 1940 | S5: 1941 | T5: 1942 | U5: 1943 | V5: 1944 | W5: 1945 | X5: 1946 | Y5: 1947 | Z5: 1948 | AA5: 1949 | AB5: 1950 | AC5: 1951 | AD5: 1952 | AE5: 1953 | AF5: 1954 | AG5: 1955 | AH5: 1956 | AI5: 1957 | AJ5: 1958 | AK5: 1959 | AL5: 1960 | AM5: 1961 | AN5: 1962 | AO5: 1963 | AP5: 1964 | AQ5: 1965 | AR5: 1966 | AS5: 1967 | AT5: 1968 | AU5: 1969 | AV5: 1970 | AW5: 1971 | AX5: 1972 | AY5: 1973 | AZ5: 1974 | BA5: 1975 | BB5: 1976 | BC5: 1977 | BD5: 1978 | BE5: 1979 | BF5: 1980 | BG5: 1981 | BH5: 1982 | BI5: 1983 | BJ5: 1984 | BK5: 1985 | BL5: 1986 | BM5: 1987 | BN5: 1988 | BO5: 1989 | BP5: 1990 | BQ5: 1991 | BR5: 1992 | BS5: 1993 | BT5: 1994 | BU5: 1995 | BV5: 1996 | BW5: 1997 | BX5: 1998 | BY5: 1999 | BZ5: 2000 | CA5: 2001 | CB5: 2002 | CC5: 2003 | CD5: 2004 | CE5: 2005 | CF5: 2006 | CG5: 2007 | CH5: 2008 | CI5: 2009 | CJ5: 2010 | CK5: 2011 | CL5: 2012 | CM5: 2013 | CN5: 2014 | CO5: 2015 | CP5: 2016 | CQ5: 2017 | CR5: 2018 | CS5: 2019 | CT5: 2020 | CU5: 2021 | CV5: 2022 | CW5: 2023 | CX5: 2024
A7: ES00 | B7: Equipment, structures, and intellectual property products | C7: =Datasets!B62 -> 0.0259 | D7: =Datasets!C62 -> 0.0263 | E7: =Datasets!D62 -> 0.0267 | F7: =Datasets!E62 -> 0.027 | G7: =Datasets!F62 -> 0.0271 | H7: =Datasets!G62 -> 0.0271 | I7: =Datasets!H62 -> 0.0269 | J7: =Datasets!I62 -> 0.0267 | ... CX7: =Datasets!CW62 -> 0.0481
A8: EQ00 | B8: Equipment | C8: =Datasets!B63 -> 0.1051 | D8: =Datasets!C63 -> 0.1078 | E8: =Datasets!D63 -> 0.1075 | F8: =Datasets!E63 -> 0.1061 | G8: =Datasets!F63 -> 0.1051 | H8: =Datasets!G63 -> 0.1054 | I8: =Datasets!H63 -> 0.1055 | J8: =Datasets!I63 -> 0.1052 | ... CX8: =Datasets!CW63 -> 0.1044
A9: EP00 | B9: Information | C9: =Datasets!B64 -> 0.135 | D9: =Datasets!C64 -> 0.135 | E9: =Datasets!D64 -> 0.135 | F9: =Datasets!E64 -> 0.135 | G9: =Datasets!F64 -> 0.135 | H9: =Datasets!G64 -> 0.135 | I9: =Datasets!H64 -> 0.135 | J9: =Datasets!I64 -> 0.135 | ... CX9: =Datasets!CW64 -> 0.1464
A10: EP11 | B10: Computers | C10: =Datasets!B65 -> 0 | D10: =Datasets!C65 -> 0 | E10: =Datasets!D65 -> 0 | F10: =Datasets!E65 -> 0 | G10: =Datasets!F65 -> 0 | H10: =Datasets!G65 -> 0 | I10: =Datasets!H65 -> 0 | J10: =Datasets!I65 -> 0 | ... CX10: =Datasets!CW65 -> 0.3373
A11: EI00 | B11: Industrial | C11: =Datasets!B66 -> 0.0994 | D11: =Datasets!C66 -> 0.0999 | E11: =Datasets!D66 -> 0.1003 | F11: =Datasets!E66 -> 0.0992 | G11: =Datasets!F66 -> 0.0983 | H11: =Datasets!G66 -> 0.0983 | I11: =Datasets!H66 -> 0.0982 | J11: =Datasets!I66 -> 0.098 | ... CX11: =Datasets!CW66 -> 0.062
A12: ET00 | B12: Transportation | C12: =Datasets!B67 -> 0.2387 | D12: =Datasets!C67 -> 0.2522 | E12: =Datasets!D67 -> 0.2527 | F12: =Datasets!E67 -> 0.2596 | G12: =Datasets!F67 -> 0.2659 | H12: =Datasets!G67 -> 0.2693 | I12: =Datasets!H67 -> 0.269 | J12: =Datasets!I67 -> 0.2621 | ... CX12: =Datasets!CW67 -> 0.1489
A13: EO00 | B13: Other equipment | C13: =Datasets!B68 -> 0.1179 | D13: =Datasets!C68 -> 0.1179 | E13: =Datasets!D68 -> 0.1179 | F13: =Datasets!E68 -> 0.1179 | G13: =Datasets!F68 -> 0.1179 | H13: =Datasets!G68 -> 0.15 | I13: =Datasets!H68 -> 0.15 | J13: =Datasets!I68 -> 0.15 | ... CX13: =Datasets!CW68 -> 0.1496
A14: ST00 | B14: Structures | C14: =Datasets!B69 -> 0.0237 | D14: =Datasets!C69 -> 0.0237 | E14: =Datasets!D69 -> 0.0237 | F14: =Datasets!E69 -> 0.0237 | G14: =Datasets!F69 -> 0.0237 | H14: =Datasets!G69 -> 0.0237 | I14: =Datasets!H69 -> 0.0237 | J14: =Datasets!I69 -> 0.0237 | ... CX14: =Datasets!CW69 -> 0.0242
A15: SCHC | B15: Commercial and healthcare | C15: =Datasets!B70 -> 0.0262 | D15: =Datasets!C70 -> 0.0262 | E15: =Datasets!D70 -> 0.0262 | F15: =Datasets!E70 -> 0.0262 | G15: =Datasets!F70 -> 0.0262 | H15: =Datasets!G70 -> 0.0262 | I15: =Datasets!H70 -> 0.0262 | J15: =Datasets!I70 -> 0.0262 | ... CX15: =Datasets!CW70 -> 0.0248
A16: IP00 | B16: Intellectual property products | C16: =Datasets!B71 -> 0.16 | D16: =Datasets!C71 -> 0.16 | E16: =Datasets!D71 -> 0.16 | F16: =Datasets!E71 -> 0.16 | G16: =Datasets!F71 -> 0.16 | H16: =Datasets!G71 -> 0.16 | I16: =Datasets!H71 -> 0.16 | J16: =Datasets!I71 -> 0.16 | ... CX16: =Datasets!CW71 -> 0.3985

Sheet 2213
A1: 2213 - Water, Sewage, and Other Systems
A2: Implied Depreciation Rates for Private Nonresidential Fixed Assets
A3: Updated September 26, 2025
A5: Asset Codes | B5: NIPA Asset Types | C5: 1925 | D5: 1926 | E5: 1927 | F5: 1928 | G5: 1929 | H5: 1930 | I5: 1931 | J5: 1932 | K5: 1933 | L5: 1934 | M5: 1935 | N5: 1936 | O5: 1937 | P5: 1938 | Q5: 1939 | R5: 1940 | S5: 1941 | T5: 1942 | U5: 1943 | V5: 1944 | W5: 1945 | X5: 1946 | Y5: 1947 | Z5: 1948 | AA5: 1949 | AB5: 1950 | AC5: 1951 | AD5: 1952 | AE5: 1953 | AF5: 1954 | AG5: 1955 | AH5: 1956 | AI5: 1957 | AJ5: 1958 | AK5: 1959 | AL5: 1960 | AM5: 1961 | AN5: 1962 | AO5: 1963 | AP5: 1964 | AQ5: 1965 | AR5: 1966 | AS5: 1967 | AT5: 1968 | AU5: 1969 | AV5: 1970 | AW5: 1971 | AX5: 1972 | AY5: 1973 | AZ5: 1974 | BA5: 1975 | BB5: 1976 | BC5: 1977 | BD5: 1978 | BE5: 1979 | BF5: 1980 | BG5: 1981 | BH5: 1982 | BI5: 1983 | BJ5: 1984 | BK5: 1985 | BL5: 1986 | BM5: 1987 | BN5: 1988 | BO5: 1989 | BP5: 1990 | BQ5: 1991 | BR5: 1992 | BS5: 1993 | BT5: 1994 | BU5: 1995 | BV5: 1996 | BW5: 1997 | BX5: 1998 | BY5: 1999 | BZ5: 2000 | CA5: 2001 | CB5: 2002 | CC5: 2003 | CD5: 2004 | CE5: 2005 | CF5: 2006 | CG5: 2007 | CH5: 2008 | CI5: 2009 | CJ5: 2010 | CK5: 2011 | CL5: 2012 | CM5: 2013 | CN5: 2014 | CO5: 2015 | CP5: 2016 | CQ5: 2017 | CR5: 2018 | CS5: 2019 | CT5: 2020 | CU5: 2021 | CV5: 2022 | CW5: 2023 | CX5: 2024
A7: ES00 | B7: Equipment, structures, and intellectual property products | C7: =Datasets!B72 -> 0.0251 | D7: =Datasets!C72 -> 0.026 | E7: =Datasets!D72 -> 0.0264 | F7: =Datasets!E72 -> 0.0266 | G7: =Datasets!F72 -> 0.0269 | H7: =Datasets!G72 -> 0.0273 | I7: =Datasets!H72 -> 0.0275 | J7: =Datasets!I72 -> 0.0275 | ... CX7: =Datasets!CW72 -> 0.066
A8: EQ00 | B8: Equipment | C8: =Datasets!B73 -> 0.0574 | D8: =Datasets!C73 -> 0.0607 | E8: =Datasets!D73 -> 0.0609 | F8: =Datasets!E73 -> 0.0614 | G8: =Datasets!F73 -> 0.0616 | H8: =Datasets!G73 -> 0.0615 | I8: =Datasets!H73 -> 0.0614 | J8: =Datasets!I73 -> 0.0612 | ... CX8: =Datasets!CW73 -> 0.1447
A9: EP00 | B9: Information | C9: =Datasets!B74 -> 0.135 | D9: =Datasets!C74 -> 0.135 | E9: =Datasets!D74 -> 0.135 | F9: =Datasets!E74 -> 0.135 | G9: =Datasets!F74 -> 0.135 | H9: =Datasets!G74 -> 0.135 | I9: =Datasets!H74 -> 0.135 | J9: =Datasets!I74 -> 0.135 | ... CX9: =Datasets!CW74 -> 0.1563
A10: EP11 | B10: Computers | C10: =Datasets!B75 -> 0 | D10: =Datasets!C75 -> 0 | E10: =Datasets!D75 -> 0 | F10: =Datasets!E75 -> 0 | G10: =Datasets!F75 -> 0 | H10: =Datasets!G75 -> 0 | I10: =Datasets!H75 -> 0 | J10: =Datasets!I75 -> 0 | ... CX10: =Datasets!CW75 -> 0.3322
A11: EI00 | B11: Industrial | C11: =Datasets!B76 -> 0.0526 | D11: =Datasets!C76 -> 0.0525 | E11: =Datasets!D76 -> 0.0525 | F11: =Datasets!E76 -> 0.0525 | G11: =Datasets!F76 -> 0.0525 | H11: =Datasets!G76 -> 0.0524 | I11: =Datasets!H76 -> 0.0525 | J11: =Datasets!I76 -> 0.0525 | ... CX11: =Datasets!CW76 -> 0.0844
A12: ET00 | B12: Transportation | C12: =Datasets!B77 -> 0.2387 | D12: =Datasets!C77 -> 0.2522 | E12: =Datasets!D77 -> 0.2527 | F12: =Datasets!E77 -> 0.2596 | G12: =Datasets!F77 -> 0.2659 | H12: =Datasets!G77 -> 0.2693 | I12: =Datasets!H77 -> 0.269 | J12: =Datasets!I77 -> 0.2621 | ... CX12: =Datasets!CW77 -> 0.1919
A13: EO00 | B13: Other equipment | C13: =Datasets!B78 -> 0 | D13: =Datasets!C78 -> 0 | E13: =Datasets!D78 -> 0 | F13: =Datasets!E78 -> 0 | G13: =Datasets!F78 -> 0 | H13: =Datasets!G78 -> 0.15 | I13: =Datasets!H78 -> 0.15 | J13: =Datasets!I78 -> 0.15 | ... CX13: =Datasets!CW78 -> 0.1493
A14: ST00 | B14: Structures | C14: =Datasets!B79 -> 0.0225 | D14: =Datasets!C79 -> 0.0225 | E14: =Datasets!D79 -> 0.0225 | F14: =Datasets!E79 -> 0.0225 | G14: =Datasets!F79 -> 0.0225 | H14: =Datasets!G79 -> 0.0225 | I14: =Datasets!H79 -> 0.0225 | J14: =Datasets!I79 -> 0.0225 | ... CX14: =Datasets!CW79 -> 0.0233
A15: SCHC | B15: Commercial and healthcare | C15: =Datasets!B80 -> 0.0247 | D15: =Datasets!C80 -> 0.0247 | E15: =Datasets!D80 -> 0.0247 | F15: =Datasets!E80 -> 0.0247 | G15: =Datasets!F80 -> 0.0247 | H15: =Datasets!G80 -> 0.0247 | I15: =Datasets!H80 -> 0.0247 | J15: =Datasets!I80 -> 0.0247 | ... CX15: =Datasets!CW80 -> 0.0253
A16: IP00 | B16: Intellectual property products | C16: =Datasets!B81 -> 0.16 | D16: =Datasets!C81 -> 0.16 | E16: =Datasets!D81 -> 0.16 | F16: =Datasets!E81 -> 0.16 | G16: =Datasets!F81 -> 0.16 | H16: =Datasets!G81 -> 0.16 | I16: =Datasets!H81 -> 0.16 | J16: =Datasets!I81 -> 0.16 | ... CX16: =Datasets!CW81 -> 0.4189

Sheet 2300
A1: 2300 - Construction
A2: Implied Depreciation Rates for Private Nonresidential Fixed Assets
A3: Updated September 26, 2025
A5: Asset Codes | B5: NIPA Asset Types | C5: 1925 | D5: 1926 | E5: 1927 | F5: 1928 | G5: 1929 | H5: 1930 | I5: 1931 | J5: 1932 | K5: 1933 | L5: 1934 | M5: 1935 | N5: 1936 | O5: 1937 | P5: 1938 | Q5: 1939 | R5: 1940 | S5: 1941 | T5: 1942 | U5: 1943 | V5: 1944 | W5: 1945 | X5: 1946 | Y5: 1947 | Z5: 1948 | AA5: 1949 | AB5: 1950 | AC5: 1951 | AD5: 1952 | AE5: 1953 | AF5: 1954 | AG5: 1955 | AH5: 1956 | AI5: 1957 | AJ5: 1958 | AK5: 1959 | AL5: 1960 | AM5: 1961 | AN5: 1962 | AO5: 1963 | AP5: 1964 | AQ5: 1965 | AR5: 1966 | AS5: 1967 | AT5: 1968 | AU5: 1969 | AV5: 1970 | AW5: 1971 | AX5: 1972 | AY5: 1973 | AZ5: 1974 | BA5: 1975 | BB5: 1976 | BC5: 1977 | BD5: 1978 | BE5: 1979 | BF5: 1980 | BG5: 1981 | BH5: 1982 | BI5: 1983 | BJ5: 1984 | BK5: 1985 | BL5: 1986 | BM5: 1987 | BN5: 1988 | BO5: 1989 | BP5: 1990 | BQ5: 1991 | BR5: 1992 | BS5: 1993 | BT5: 1994 | BU5: 1995 | BV5: 1996 | BW5: 1997 | BX5: 1998 | BY5: 1999 | BZ5: 2000 | CA5: 2001 | CB5: 2002 | CC5: 2003 | CD5: 2004 | CE5: 2005 | CF5: 2006 | CG5: 2007 | CH5: 2008 | CI5: 2009 | CJ5: 2010 | CK5: 2011 | CL5: 2012 | CM5: 2013 | CN5: 2014 | CO5: 2015 | CP5: 2016 | CQ5: 2017 | CR5: 2018 | CS5: 2019 | CT5: 2020 | CU5: 2021 | CV5: 2022 | CW5: 2023 | CX5: 2024
A7: ES00 | B7: Equipment, structures, and intellectual property products | C7: =Datasets!B82 -> 0.1525 | D7: =Datasets!C82 -> 0.1518 | E7: =Datasets!D82 -> 0.15 | F7: =Datasets!E82 -> 0.1492 | G7: =Datasets!F82 -> 0.1483 | H7: =Datasets!G82 -> 0.147 | I7: =Datasets!H82 -> 0.1459 | J7: =Datasets!I82 -> 0.1444 | ... CX7: =Datasets!CW82 -> 0.1348
A8: EQ00 | B8: Equipment | C8: =Datasets!B83 -> 0.1559 | D8: =Datasets!C83 -> 0.1555 | E8: =Datasets!D83 -> 0.1541 | F8: =Datasets!E83 -> 0.1534 | G8: =Datasets!F83 -> 0.1528 | H8: =Datasets!G83 -> 0.1522 | I8: =Datasets!H83 -> 0.1517 | J8: =Datasets!I83 -> 0.1511 | ... CX8: =Datasets!CW83 -> 0.1636
A9: EP00 | B9: Information | C9: =Datasets!B84 -> 0 | D9: =Datasets!C84 -> 0 | E9: =Datasets!D84 -> 0 | F9: =Datasets!E84 -> 0 | G9: =Datasets!F84 -> 0 | H9: =Datasets!G84 -> 0 | I9: =Datasets!H84 -> 0 | J9: =Datasets!I84 -> 0 | ... CX9: =Datasets!CW84 -> 0.2075
A10: EP11 | B10: Computers | C10: =Datasets!B85 -> 0 | D10: =Datasets!C85 -> 0 | E10: =Datasets!D85 -> 0 | F10: =Datasets!E85 -> 0 | G10: =Datasets!F85 -> 0 | H10: =Datasets!G85 -> 0 | I10: =Datasets!H85 -> 0 | J10: =Datasets!I85 -> 0 | ... CX10: =Datasets!CW85 -> 0.3396
A11: EI00 | B11: Industrial | C11: =Datasets!B86 -> 0.1642 | D11: =Datasets!C86 -> 0.1543 | E11: =Datasets!D86 -> 0.1458 | F11: =Datasets!E86 -> 0.141 | G11: =Datasets!F86 -> 0.1376 | H11: =Datasets!G86 -> 0.1347 | I11: =Datasets!H86 -> 0.1327 | J11: =Datasets!I86 -> 0.1304 | ... CX11: =Datasets!CW86 -> 0.0995
A12: ET00 | B12: Transportation | C12: =Datasets!B87 -> 0.2387 | D12: =Datasets!C87 -> 0.2522 | E12: =Datasets!D87 -> 0.2527 | F12: =Datasets!E87 -> 0.2596 | G12: =Datasets!F87 -> 0.2659 | H12: =Datasets!G87 -> 0.2693 | I12: =Datasets!H87 -> 0.269 | J12: =Datasets!I87 -> 0.2621 | ... CX12: =Datasets!CW87 -> 0.1883
A13: EO00 | B13: Other equipment | C13: =Datasets!B88 -> 0.1519 | D13: =Datasets!C88 -> 0.1521 | E13: =Datasets!D88 -> 0.1523 | F13: =Datasets!E88 -> 0.1525 | G13: =Datasets!F88 -> 0.1526 | H13: =Datasets!G88 -> 0.1527 | I13: =Datasets!H88 -> 0.1528 | J13: =Datasets!I88 -> 0.1529 | ... CX13: =Datasets!CW88 -> 0.1545
A14: ST00 | B14: Structures | C14: =Datasets!B89 -> 0.0239 | D14: =Datasets!C89 -> 0.0239 | E14: =Datasets!D89 -> 0.0239 | F14: =Datasets!E89 -> 0.024 | G14: =Datasets!F89 -> 0.024 | H14: =Datasets!G89 -> 0.024 | I14: =Datasets!H89 -> 0.024 | J14: =Datasets!I89 -> 0.024 | ... CX14: =Datasets!CW89 -> 0.0259
A15: SCHC | B15: Commercial and healthcare | C15: =Datasets!B90 -> 0.0245 | D15: =Datasets!C90 -> 0.0244 | E15: =Datasets!D90 -> 0.0243 | F15: =Datasets!E90 -> 0.0243 | G15: =Datasets!F90 -> 0.0244 | H15: =Datasets!G90 -> 0.0244 | I15: =Datasets!H90 -> 0.0244 | J15: =Datasets!I90 -> 0.0244 | ... CX15: =Datasets!CW90 -> 0.0246
A16: IP00 | B16: Intellectual property products | C16: =Datasets!B91 -> 0.16 | D16: =Datasets!C91 -> 0.16 | E16: =Datasets!D91 -> 0.16 | F16: =Datasets!E91 -> 0.16 | G16: =Datasets!F91 -> 0.16 | H16: =Datasets!G91 -> 0.16 | I16: =Datasets!H91 -> 0.16 | J16: =Datasets!I91 -> 0.16 | ... CX16: =Datasets!CW91 -> 0.2855

Sheet 3210
A1: 3210 - Wood Products
A2: Implied Depreciation Rates for Private Nonresidential Fixed Assets
A3: Updated September 26, 2025
A5: Asset Codes | B5: NIPA Asset Types | C5: 1925 | D5: 1926 | E5: 1927 | F5: 1928 | G5: 1929 | H5: 1930 | I5: 1931 | J5: 1932 | K5: 1933 | L5: 1934 | M5: 1935 | N5: 1936 | O5: 1937 | P5: 1938 | Q5: 1939 | R5: 1940 | S5: 1941 | T5: 1942 | U5: 1943 | V5: 1944 | W5: 1945 | X5: 1946 | Y5: 1947 | Z5: 1948 | AA5: 1949 | AB5: 1950 | AC5: 1951 | AD5: 1952 | AE5: 1953 | AF5: 1954 | AG5: 1955 | AH5: 1956 | AI5: 1957 | AJ5: 1958 | AK5: 1959 | AL5: 1960 | AM5: 1961 | AN5: 1962 | AO5: 1963 | AP5: 1964 | AQ5: 1965 | AR5: 1966 | AS5: 1967 | AT5: 1968 | AU5: 1969 | AV5: 1970 | AW5: 1971 | AX5: 1972 | AY5: 1973 | AZ5: 1974 | BA5: 1975 | BB5: 1976 | BC5: 1977 | BD5: 1978 | BE5: 1979 | BF5: 1980 | BG5: 1981 | BH5: 1982 | BI5: 1983 | BJ5: 1984 | BK5: 1985 | BL5: 1986 | BM5: 1987 | BN5: 1988 | BO5: 1989 | BP5: 1990 | BQ5: 1991 | BR5: 1992 | BS5: 1993 | BT5: 1994 | BU5: 1995 | BV5: 1996 | BW5: 1997 | BX5: 1998 | BY5: 1999 | BZ5: 2000 | CA5: 2001 | CB5: 2002 | CC5: 2003 | CD5: 2004 | CE5: 2005 | CF5: 2006 | CG5: 2007 | CH5: 2008 | CI5: 2009 | CJ5: 2010 | CK5: 2011 | CL5: 2012 | CM5: 2013 | CN5: 2014 | CO5: 2015 | CP5: 2016 | CQ5: 2017 | CR5: 2018 | CS5: 2019 | CT5: 2020 | CU5: 2021 | CV5: 2022 | CW5: 2023 | CX5: 2024
A7: ES00 | B7: Equipment, structures, and intellectual property products | C7: =Datasets!B92 -> 0.0637 | D7: =Datasets!C92 -> 0.0675 | E7: =Datasets!D92 -> 0.0688 | F7: =Datasets!E92 -> 0.0687 | G7: =Datasets!F92 -> 0.0683 | H7: =Datasets!G92 -> 0.0672 | I7: =Datasets!H92 -> 0.0655 | J7: =Datasets!I92 -> 0.0639 | ... CX7: =Datasets!CW92 -> 0.0962
A8: EQ00 | B8: Equipment | C8: =Datasets!B93 -> 0.1393 | D8: =Datasets!C93 -> 0.1407 | E8: =Datasets!D93 -> 0.1409 | F8: =Datasets!E93 -> 0.1414 | G8: =Datasets!F93 -> 0.1417 | H8: =Datasets!G93 -> 0.1419 | I8: =Datasets!H93 -> 0.1421 | J8: =Datasets!I93 -> 0.142 | ... CX8: =Datasets!CW93 -> 0.1416
A9: EP00 | B9: Information | C9: =Datasets!B94 -> 0.135 | D9: =Datasets!C94 -> 0.135 | E9: =Datasets!D94 -> 0.135 | F9: =Datasets!E94 -> 0.135 | G9: =Datasets!F94 -> 0.135 | H9: =Datasets!G94 -> 0.135 | I9: =Datasets!H94 -> 0.135 | J9: =Datasets!I94 -> 0.135 | ... CX9: =Datasets!CW94 -> 0.1989
A10: EP11 | B10: Computers | C10: =Datasets!B95 -> 0 | D10: =Datasets!C95 -> 0 | E10: =Datasets!D95 -> 0 | F10: =Datasets!E95 -> 0 | G10: =Datasets!F95 -> 0 | H10: =Datasets!G95 -> 0 | I10: =Datasets!H95 -> 0 | J10: =Datasets!I95 -> 0 | ... CX10: =Datasets!CW95 -> 0.3382
A11: EI00 | B11: Industrial | C11: =Datasets!B96 -> 0.1371 | D11: =Datasets!C96 -> 0.1371 | E11: =Datasets!D96 -> 0.1372 | F11: =Datasets!E96 -> 0.1372 | G11: =Datasets!F96 -> 0.1371 | H11: =Datasets!G96 -> 0.1371 | I11: =Datasets!H96 -> 0.137 | J11: =Datasets!I96 -> 0.1369 | ... CX11: =Datasets!CW96 -> 0.1342
A12: ET00 | B12: Transportation | C12: =Datasets!B97 -> 0.2387 | D12: =Datasets!C97 -> 0.2522 | E12: =Datasets!D97 -> 0.2527 | F12: =Datasets!E97 -> 0.2596 | G12: =Datasets!F97 -> 0.2659 | H12: =Datasets!G97 -> 0.2693 | I12: =Datasets!H97 -> 0.269 | J12: =Datasets!I97 -> 0.2621 | ... CX12: =Datasets!CW97 -> 0.1922
A13: EO00 | B13: Other equipment | C13: =Datasets!B98 -> 0 | D13: =Datasets!C98 -> 0 | E13: =Datasets!D98 -> 0 | F13: =Datasets!E98 -> 0 | G13: =Datasets!F98 -> 0 | H13: =Datasets!G98 -> 0 | I13: =Datasets!H98 -> 0 | J13: =Datasets!I98 -> 0 | ... CX13: =Datasets!CW98 -> 0.1511
A14: ST00 | B14: Structures | C14: =Datasets!B99 -> 0.0313 | D14: =Datasets!C99 -> 0.0313 | E14: =Datasets!D99 -> 0.0313 | F14: =Datasets!E99 -> 0.0313 | G14: =Datasets!F99 -> 0.0313 | H14: =Datasets!G99 -> 0.0313 | I14: =Datasets!H99 -> 0.0313 | J14: =Datasets!I99 -> 0.0313 | ... CX14: =Datasets!CW99 -> 0.0309
A15: SCHC | B15: Commercial and healthcare | C15: =Datasets!B100 -> 0.0247 | D15: =Datasets!C100 -> 0.0247 | E15: =Datasets!D100 -> 0.0247 | F15: =Datasets!E100 -> 0.0247 | G15: =Datasets!F100 -> 0.0247 | H15: =Datasets!G100 -> 0.0247 | I15: =Datasets!H100 -> 0.0247 | J15: =Datasets!I100 -> 0.0247 | ... CX15: =Datasets!CW100 -> 0.0247
A16: IP00 | B16: Intellectual property products | C16: =Datasets!B101 -> 0 | D16: =Datasets!C101 -> 0 | E16: =Datasets!D101 -> 0 | F16: =Datasets!E101 -> 0 | G16: =Datasets!F101 -> 0 | H16: =Datasets!G101 -> 0 | I16: =Datasets!H101 -> 0 | J16: =Datasets!I101 -> 0 | ... CX16: =Datasets!CW101 -> 0.3155

Sheet 3270
A1: 3270 - Nonmetallic Mineral Products
A2: Implied Depreciation Rates for Private Nonresidential Fixed Assets
A3: Updated September 26, 2025
A5: Asset Codes | B5: NIPA Asset Types | C5: 1925 | D5: 1926 | E5: 1927 | F5: 1928 | G5: 1929 | H5: 1930 | I5: 1931 | J5: 1932 | K5: 1933 | L5: 1934 | M5: 1935 | N5: 1936 | O5: 1937 | P5: 1938 | Q5: 1939 | R5: 1940 | S5: 1941 | T5: 1942 | U5: 1943 | V5: 1944 | W5: 1945 | X5: 1946 | Y5: 1947 | Z5: 1948 | AA5: 1949 | AB5: 1950 | AC5: 1951 | AD5: 1952 | AE5: 1953 | AF5: 1954 | AG5: 1955 | AH5: 1956 | AI5: 1957 | AJ5: 1958 | AK5: 1959 | AL5: 1960 | AM5: 1961 | AN5: 1962 | AO5: 1963 | AP5: 1964 | AQ5: 1965 | AR5: 1966 | AS5: 1967 | AT5: 1968 | AU5: 1969 | AV5: 1970 | AW5: 1971 | AX5: 1972 | AY5: 1973 | AZ5: 1974 | BA5: 1975 | BB5: 1976 | BC5: 1977 | BD5: 1978 | BE5: 1979 | BF5: 1980 | BG5: 1981 | BH5: 1982 | BI5: 1983 | BJ5: 1984 | BK5: 1985 | BL5: 1986 | BM5: 1987 | BN5: 1988 | BO5: 1989 | BP5: 1990 | BQ5: 1991 | BR5: 1992 | BS5: 1993 | BT5: 1994 | BU5: 1995 | BV5: 1996 | BW5: 1997 | BX5: 1998 | BY5: 1999 | BZ5: 2000 | CA5: 2001 | CB5: 2002 | CC5: 2003 | CD5: 2004 | CE5: 2005 | CF5: 2006 | CG5: 2007 | CH5: 2008 | CI5: 2009 | CJ5: 2010 | CK5: 2011 | CL5: 2012 | CM5: 2013 | CN5: 2014 | CO5: 2015 | CP5: 2016 | CQ5: 2017 | CR5: 2018 | CS5: 2019 | CT5: 2020 | CU5: 2021 | CV5: 2022 | CW5: 2023 | CX5: 2024
A7: ES00 | B7: Equipment, structures, and intellectual property products | C7: =Datasets!B102 -> 0.0397 | D7: =Datasets!C102 -> 0.0411 | E7: =Datasets!D102 -> 0.0418 | F7: =Datasets!E102 -> 0.0422 | G7: =Datasets!F102 -> 0.0427 | H7: =Datasets!G102 -> 0.0432 | I7: =Datasets!H102 -> 0.0436 | J7: =Datasets!I102 -> 0.0437 | ... CX7: =Datasets!CW102 -> 0.098
A8: EQ00 | B8: Equipment | C8: =Datasets!B103 -> 0.0915 | D8: =Datasets!C103 -> 0.0934 | E8: =Datasets!D103 -> 0.0935 | F8: =Datasets!E103 -> 0.0939 | G8: =Datasets!F103 -> 0.0942 | H8: =Datasets!G103 -> 0.0942 | I8: =Datasets!H103 -> 0.0941 | J8: =Datasets!I103 -> 0.0939 | ... CX8: =Datasets!CW103 -> 0.1119
A9: EP00 | B9: Information | C9: =Datasets!B104 -> 0.135 | D9: =Datasets!C104 -> 0.135 | E9: =Datasets!D104 -> 0.135 | F9: =Datasets!E104 -> 0.135 | G9: =Datasets!F104 -> 0.135 | H9: =Datasets!G104 -> 0.135 | I9: =Datasets!H104 -> 0.135 | J9: =Datasets!I104 -> 0.135 | ... CX9: =Datasets!CW104 -> 0.1419
A10: EP11 | B10: Computers | C10: =Datasets!B105 -> 0 | D10: =Datasets!C105 -> 0 | E10: =Datasets!D105 -> 0 | F10: =Datasets!E105 -> 0 | G10: =Datasets!F105 -> 0 | H10: =Datasets!G105 -> 0 | I10: =Datasets!H105 -> 0 | J10: =Datasets!I105 -> 0 | ... CX10: =Datasets!CW105 -> 0.339
A11: EI00 | B11: Industrial | C11: =Datasets!B106 -> 0.089 | D11: =Datasets!C106 -> 0.089 | E11: =Datasets!D106 -> 0.0889 | F11: =Datasets!E106 -> 0.089 | G11: =Datasets!F106 -> 0.0891 | H11: =Datasets!G106 -> 0.0892 | I11: =Datasets!H106 -> 0.0893 | J11: =Datasets!I106 -> 0.0892 | ... CX11: =Datasets!CW106 -> 0.0901
A12: ET00 | B12: Transportation | C12: =Datasets!B107 -> 0.2387 | D12: =Datasets!C107 -> 0.2522 | E12: =Datasets!D107 -> 0.2527 | F12: =Datasets!E107 -> 0.2596 | G12: =Datasets!F107 -> 0.2659 | H12: =Datasets!G107 -> 0.2693 | I12: =Datasets!H107 -> 0.269 | J12: =Datasets!I107 -> 0.2621 | ... CX12: =Datasets!CW107 -> 0.1857
A13: EO00 | B13: Other equipment | C13: =Datasets!B108 -> 0 | D13: =Datasets!C108 -> 0 | E13: =Datasets!D108 -> 0 | F13: =Datasets!E108 -> 0 | G13: =Datasets!F108 -> 0.1179 | H13: =Datasets!G108 -> 0.1179 | I13: =Datasets!H108 -> 0.1179 | J13: =Datasets!I108 -> 0.1179 | ... CX13: =Datasets!CW108 -> 0.1542
A14: ST00 | B14: Structures | C14: =Datasets!B109 -> 0.0314 | D14: =Datasets!C109 -> 0.0313 | E14: =Datasets!D109 -> 0.0313 | F14: =Datasets!E109 -> 0.0313 | G14: =Datasets!F109 -> 0.0313 | H14: =Datasets!G109 -> 0.0313 | I14: =Datasets!H109 -> 0.0313 | J14: =Datasets!I109 -> 0.0313 | ... CX14: =Datasets!CW109 -> 0.0312
A15: SCHC | B15: Commercial and healthcare | C15: =Datasets!B110 -> 0.0247 | D15: =Datasets!C110 -> 0.0247 | E15: =Datasets!D110 -> 0.0247 | F15: =Datasets!E110 -> 0.0247 | G15: =Datasets!F110 -> 0.0247 | H15: =Datasets!G110 -> 0.0247 | I15: =Datasets!H110 -> 0.0247 | J15: =Datasets!I110 -> 0.0247 | ... CX15: =Datasets!CW110 -> 0.0244
A16: IP00 | B16: Intellectual property products | C16: =Datasets!B111 -> 0.16 | D16: =Datasets!C111 -> 0.16 | E16: =Datasets!D111 -> 0.16 | F16: =Datasets!E111 -> 0.16 | G16: =Datasets!F111 -> 0.16 | H16: =Datasets!G111 -> 0.16 | I16: =Datasets!H111 -> 0.16 | J16: =Datasets!I111 -> 0.16 | ... CX16: =Datasets!CW111 -> 0.1672

Sheet 3310
A1: 3310 - Primary Metals
A2: Implied Depreciation Rates for Private Nonresidential Fixed Assets
A3: Updated September 26, 2025
A5: Asset Codes | B5: NIPA Asset Types | C5: 1925 | D5: 1926 | E5: 1927 | F5: 1928 | G5: 1929 | H5: 1930 | I5: 1931 | J5: 1932 | K5: 1933 | L5: 1934 | M5: 1935 | N5: 1936 | O5: 1937 | P5: 1938 | Q5: 1939 | R5: 1940 | S5: 1941 | T5: 1942 | U5: 1943 | V5: 1944 | W5: 1945 | X5: 1946 | Y5: 1947 | Z5: 1948 | AA5: 1949 | AB5: 1950 | AC5: 1951 | AD5: 1952 | AE5: 1953 | AF5: 1954 | AG5: 1955 | AH5: 1956 | AI5: 1957 | AJ5: 1958 | AK5: 1959 | AL5: 1960 | AM5: 1961 | AN5: 1962 | AO5: 1963 | AP5: 1964 | AQ5: 1965 | AR5: 1966 | AS5: 1967 | AT5: 1968 | AU5: 1969 | AV5: 1970 | AW5: 1971 | AX5: 1972 | AY5: 1973 | AZ5: 1974 | BA5: 1975 | BB5: 1976 | BC5: 1977 | BD5: 1978 | BE5: 1979 | BF5: 1980 | BG5: 1981 | BH5: 1982 | BI5: 1983 | BJ5: 1984 | BK5: 1985 | BL5: 1986 | BM5: 1987 | BN5: 1988 | BO5: 1989 | BP5: 1990 | BQ5: 1991 | BR5: 1992 | BS5: 1993 | BT5: 1994 | BU5: 1995 | BV5: 1996 | BW5: 1997 | BX5: 1998 | BY5: 1999 | BZ5: 2000 | CA5: 2001 | CB5: 2002 | CC5: 2003 | CD5: 2004 | CE5: 2005 | CF5: 2006 | CG5: 2007 | CH5: 2008 | CI5: 2009 | CJ5: 2010 | CK5: 2011 | CL5: 2012 | CM5: 2013 | CN5: 2014 | CO5: 2015 | CP5: 2016 | CQ5: 2017 | CR5: 2018 | CS5: 2019 | CT5: 2020 | CU5: 2021 | CV5: 2022 | CW5: 2023 | CX5: 2024
A7: ES00 | B7: Equipment, structures, and intellectual property products | C7: =Datasets!B112 -> 0.0463 | D7: =Datasets!C112 -> 0.046 | E7: =Datasets!D112 -> 0.0453 | F7: =Datasets!E112 -> 0.0447 | G7: =Datasets!F112 -> 0.0442 | H7: =Datasets!G112 -> 0.0439 | I7: =Datasets!H112 -> 0.0436 | J7: =Datasets!I112 -> 0.0434 | ... CX7: =Datasets!CW112 -> 0.0697
A8: EQ00 | B8: Equipment | C8: =Datasets!B113 -> 0.0698 | D8: =Datasets!C113 -> 0.0697 | E8: =Datasets!D113 -> 0.0688 | F8: =Datasets!E113 -> 0.0683 | G8: =Datasets!F113 -> 0.0679 | H8: =Datasets!G113 -> 0.0677 | I8: =Datasets!H113 -> 0.0673 | J8: =Datasets!I113 -> 0.0669 | ... CX8: =Datasets!CW113 -> 0.0743
A9: EP00 | B9: Information | C9: =Datasets!B114 -> 0.135 | D9: =Datasets!C114 -> 0.135 | E9: =Datasets!D114 -> 0.135 | F9: =Datasets!E114 -> 0.135 | G9: =Datasets!F114 -> 0.135 | H9: =Datasets!G114 -> 0.135 | I9: =Datasets!H114 -> 0.135 | J9: =Datasets!I114 -> 0.135 | ... CX9: =Datasets!CW114 -> 0.1837
A10: EP11 | B10: Computers | C10: =Datasets!B115 -> 0 | D10: =Datasets!C115 -> 0 | E10: =Datasets!D115 -> 0 | F10: =Datasets!E115 -> 0 | G10: =Datasets!F115 -> 0 | H10: =Datasets!G115 -> 0 | I10: =Datasets!H115 -> 0 | J10: =Datasets!I115 -> 0 | ... CX10: =Datasets!CW115 -> 0.3404
A11: EI00 | B11: Industrial | C11: =Datasets!B116 -> 0.0623 | D11: =Datasets!C116 -> 0.0625 | E11: =Datasets!D116 -> 0.0626 | F11: =Datasets!E116 -> 0.0626 | G11: =Datasets!F116 -> 0.0627 | H11: =Datasets!G116 -> 0.0629 | I11: =Datasets!H116 -> 0.0629 | J11: =Datasets!I116 -> 0.063 | ... CX11: =Datasets!CW116 -> 0.0698
A12: ET00 | B12: Transportation | C12: =Datasets!B117 -> 0.2387 | D12: =Datasets!C117 -> 0.2522 | E12: =Datasets!D117 -> 0.2527 | F12: =Datasets!E117 -> 0.2596 | G12: =Datasets!F117 -> 0.2659 | H12: =Datasets!G117 -> 0.2693 | I12: =Datasets!H117 -> 0.269 | J12: =Datasets!I117 -> 0.2621 | ... CX12: =Datasets!CW117 -> 0.1483
A13: EO00 | B13: Other equipment | C13: =Datasets!B118 -> 0.1179 | D13: =Datasets!C118 -> 0.1179 | E13: =Datasets!D118 -> 0.1179 | F13: =Datasets!E118 -> 0.1179 | G13: =Datasets!F118 -> 0.1179 | H13: =Datasets!G118 -> 0.1179 | I13: =Datasets!H118 -> 0.1179 | J13: =Datasets!I118 -> 0.1179 | ... CX13: =Datasets!CW118 -> 0.1477
A14: ST00 | B14: Structures | C14: =Datasets!B119 -> 0.031 | D14: =Datasets!C119 -> 0.031 | E14: =Datasets!D119 -> 0.031 | F14: =Datasets!E119 -> 0.031 | G14: =Datasets!F119 -> 0.0309 | H14: =Datasets!G119 -> 0.0309 | I14: =Datasets!H119 -> 0.0309 | J14: =Datasets!I119 -> 0.0309 | ... CX14: =Datasets!CW119 -> 0.031
A15: SCHC | B15: Commercial and healthcare | C15: =Datasets!B120 -> 0.0247 | D15: =Datasets!C120 -> 0.0247 | E15: =Datasets!D120 -> 0.0247 | F15: =Datasets!E120 -> 0.0247 | G15: =Datasets!F120 -> 0.0247 | H15: =Datasets!G120 -> 0.0247 | I15: =Datasets!H120 -> 0.0247 | J15: =Datasets!I120 -> 0.0247 | ... CX15: =Datasets!CW120 -> 0.0246
A16: IP00 | B16: Intellectual property products | C16: =Datasets!B121 -> 0.16 | D16: =Datasets!C121 -> 0.16 | E16: =Datasets!D121 -> 0.16 | F16: =Datasets!E121 -> 0.16 | G16: =Datasets!F121 -> 0.16 | H16: =Datasets!G121 -> 0.16 | I16: =Datasets!H121 -> 0.16 | J16: =Datasets!I121 -> 0.16 | ... CX16: =Datasets!CW121 -> 0.1802

Sheet 3320
A1: 3320 - Fabricated Metal Products
A2: Implied Depreciation Rates for Private Nonresidential Fixed Assets
A3: Updated September 26, 2025
A5: Asset Codes | B5: NIPA Asset Types | C5: 1925 | D5: 1926 | E5: 1927 | F5: 1928 | G5: 1929 | H5: 1930 | I5: 1931 | J5: 1932 | K5: 1933 | L5: 1934 | M5: 1935 | N5: 1936 | O5: 1937 | P5: 1938 | Q5: 1939 | R5: 1940 | S5: 1941 | T5: 1942 | U5: 1943 | V5: 1944 | W5: 1945 | X5: 1946 | Y5: 1947 | Z5: 1948 | AA5: 1949 | AB5: 1950 | AC5: 1951 | AD5: 1952 | AE5: 1953 | AF5: 1954 | AG5: 1955 | AH5: 1956 | AI5: 1957 | AJ5: 1958 | AK5: 1959 | AL5: 1960 | AM5: 1961 | AN5: 1962 | AO5: 1963 | AP5: 1964 | AQ5: 1965 | AR5: 1966 | AS5: 1967 | AT5: 1968 | AU5: 1969 | AV5: 1970 | AW5: 1971 | AX5: 1972 | AY5: 1973 | AZ5: 1974 | BA5: 1975 | BB5: 1976 | BC5: 1977 | BD5: 1978 | BE5: 1979 | BF5: 1980 | BG5: 1981 | BH5: 1982 | BI5: 1983 | BJ5: 1984 | BK5: 1985 | BL5: 1986 | BM5: 1987 | BN5: 1988 | BO5: 1989 | BP5: 1990 | BQ5: 1991 | BR5: 1992 | BS5: 1993 | BT5: 1994 | BU5: 1995 | BV5: 1996 | BW5: 1997 | BX5: 1998 | BY5: 1999 | BZ5: 2000 | CA5: 2001 | CB5: 2002 | CC5: 2003 | CD5: 2004 | CE5: 2005 | CF5: 2006 | CG5: 2007 | CH5: 2008 | CI5: 2009 | CJ5: 2010 | CK5: 2011 | CL5: 2012 | CM5: 2013 | CN5: 2014 | CO5: 2015 | CP5: 2016 | CQ5: 2017 | CR5: 2018 | CS5: 2019 | CT5: 2020 | CU5: 2021 | CV5: 2022 | CW5: 2023 | CX5: 2024
A7: ES00 | B7: Equipment, structures, and intellectual property products | C7: =Datasets!B122 -> 0.0463 | D7: =Datasets!C122 -> 0.0493 | E7: =Datasets!D122 -> 0.0502 | F7: =Datasets!E122 -> 0.0511 | G7: =Datasets!F122 -> 0.0519 | H7: =Datasets!G122 -> 0.0525 | I7: =Datasets!H122 -> 0.0532 | J7: =Datasets!I122 -> 0.0535 | ... CX7: =Datasets!CW122 -> 0.0833
A8: EQ00 | B8: Equipment | C8: =Datasets!B123 -> 0.0942 | D8: =Datasets!C123 -> 0.0997 | E8: =Datasets!D123 -> 0.0985 | F8: =Datasets!E123 -> 0.0976 | G8: =Datasets!F123 -> 0.0963 | H8: =Datasets!G123 -> 0.0946 | I8: =Datasets!H123 -> 0.093 | J8: =Datasets!I123 -> 0.0914 | ... CX8: =Datasets!CW123 -> 0.088
A9: EP00 | B9: Information | C9: =Datasets!B124 -> 0.135 | D9: =Datasets!C124 -> 0.135 | E9: =Datasets!D124 -> 0.135 | F9: =Datasets!E124 -> 0.135 | G9: =Datasets!F124 -> 0.135 | H9: =Datasets!G124 -> 0.135 | I9: =Datasets!H124 -> 0.135 | J9: =Datasets!I124 -> 0.135 | ... CX9: =Datasets!CW124 -> 0.1866
A10: EP11 | B10: Computers | C10: =Datasets!B125 -> 0 | D10: =Datasets!C125 -> 0 | E10: =Datasets!D125 -> 0 | F10: =Datasets!E125 -> 0 | G10: =Datasets!F125 -> 0 | H10: =Datasets!G125 -> 0 | I10: =Datasets!H125 -> 0 | J10: =Datasets!I125 -> 0 | ... CX10: =Datasets!CW125 -> 0.3394
A11: EI00 | B11: Industrial | C11: =Datasets!B126 -> 0.0785 | D11: =Datasets!C126 -> 0.0784 | E11: =Datasets!D126 -> 0.0781 | F11: =Datasets!E126 -> 0.0779 | G11: =Datasets!F126 -> 0.0778 | H11: =Datasets!G126 -> 0.0774 | I11: =Datasets!H126 -> 0.077 | J11: =Datasets!I126 -> 0.0767 | ... CX11: =Datasets!CW126 -> 0.0822
A12: ET00 | B12: Transportation | C12: =Datasets!B127 -> 0.2387 | D12: =Datasets!C127 -> 0.2522 | E12: =Datasets!D127 -> 0.2527 | F12: =Datasets!E127 -> 0.2596 | G12: =Datasets!F127 -> 0.2659 | H12: =Datasets!G127 -> 0.2693 | I12: =Datasets!H127 -> 0.269 | J12: =Datasets!I127 -> 0.2621 | ... CX12: =Datasets!CW127 -> 0.1805
A13: EO00 | B13: Other equipment | C13: =Datasets!B128 -> 0.1179 | D13: =Datasets!C128 -> 0.1179 | E13: =Datasets!D128 -> 0.1179 | F13: =Datasets!E128 -> 0.1179 | G13: =Datasets!F128 -> 0.1179 | H13: =Datasets!G128 -> 0.1179 | I13: =Datasets!H128 -> 0.1179 | J13: =Datasets!I128 -> 0.1179 | ... CX13: =Datasets!CW128 -> 0.1457
A14: ST00 | B14: Structures | C14: =Datasets!B129 -> 0.0312 | D14: =Datasets!C129 -> 0.0312 | E14: =Datasets!D129 -> 0.0311 | F14: =Datasets!E129 -> 0.0311 | G14: =Datasets!F129 -> 0.0311 | H14: =Datasets!G129 -> 0.0311 | I14: =Datasets!H129 -> 0.0311 | J14: =Datasets!I129 -> 0.0311 | ... CX14: =Datasets!CW129 -> 0.0309
A15: SCHC | B15: Commercial and healthcare | C15: =Datasets!B130 -> 0.0247 | D15: =Datasets!C130 -> 0.0247 | E15: =Datasets!D130 -> 0.0247 | F15: =Datasets!E130 -> 0.0247 | G15: =Datasets!F130 -> 0.0247 | H15: =Datasets!G130 -> 0.0247 | I15: =Datasets!H130 -> 0.0247 | J15: =Datasets!I130 -> 0.0247 | ... CX15: =Datasets!CW130 -> 0.0242
A16: IP00 | B16: Intellectual property products | C16: =Datasets!B131 -> 0.16 | D16: =Datasets!C131 -> 0.16 | E16: =Datasets!D131 -> 0.16 | F16: =Datasets!E131 -> 0.16 | G16: =Datasets!F131 -> 0.16 | H16: =Datasets!G131 -> 0.16 | I16: =Datasets!H131 -> 0.16 | J16: =Datasets!I131 -> 0.16 | ... CX16: =Datasets!CW131 -> 0.1819

Sheet 3330
A1: 3330 - Machinery
A2: Implied Depreciation Rates for Private Nonresidential Fixed Assets
A3: Updated September 26, 2025
A5: Asset Codes | B5: NIPA Asset Types | C5: 1925 | D5: 1926 | E5: 1927 | F5: 1928 | G5: 1929 | H5: 1930 | I5: 1931 | J5: 1932 | K5: 1933 | L5: 1934 | M5: 1935 | N5: 1936 | O5: 1937 | P5: 1938 | Q5: 1939 | R5: 1940 | S5: 1941 | T5: 1942 | U5: 1943 | V5: 1944 | W5: 1945 | X5: 1946 | Y5: 1947 | Z5: 1948 | AA5: 1949 | AB5: 1950 | AC5: 1951 | AD5: 1952 | AE5: 1953 | AF5: 1954 | AG5: 1955 | AH5: 1956 | AI5: 1957 | AJ5: 1958 | AK5: 1959 | AL5: 1960 | AM5: 1961 | AN5: 1962 | AO5: 1963 | AP5: 1964 | AQ5: 1965 | AR5: 1966 | AS5: 1967 | AT5: 1968 | AU5: 1969 | AV5: 1970 | AW5: 1971 | AX5: 1972 | AY5: 1973 | AZ5: 1974 | BA5: 1975 | BB5: 1976 | BC5: 1977 | BD5: 1978 | BE5: 1979 | BF5: 1980 | BG5: 1981 | BH5: 1982 | BI5: 1983 | BJ5: 1984 | BK5: 1985 | BL5: 1986 | BM5: 1987 | BN5: 1988 | BO5: 1989 | BP5: 1990 | BQ5: 1991 | BR5: 1992 | BS5: 1993 | BT5: 1994 | BU5: 1995 | BV5: 1996 | BW5: 1997 | BX5: 1998 | BY5: 1999 | BZ5: 2000 | CA5: 2001 | CB5: 2002 | CC5: 2003 | CD5: 2004 | CE5: 2005 | CF5: 2006 | CG5: 2007 | CH5: 2008 | CI5: 2009 | CJ5: 2010 | CK5: 2011 | CL5: 2012 | CM5: 2013 | CN5: 2014 | CO5: 2015 | CP5: 2016 | CQ5: 2017 | CR5: 2018 | CS5: 2019 | CT5: 2020 | CU5: 2021 | CV5: 2022 | CW5: 2023 | CX5: 2024
A7: ES00 | B7: Equipment, structures, and intellectual property products | C7: =Datasets!B132 -> 0.0606 | D7: =Datasets!C132 -> 0.0697 | E7: =Datasets!D132 -> 0.0708 | F7: =Datasets!E132 -> 0.0712 | G7: =Datasets!F132 -> 0.0709 | H7: =Datasets!G132 -> 0.0701 | I7: =Datasets!H132 -> 0.0698 | J7: =Datasets!I132 -> 0.0699 | ... CX7: =Datasets!CW132 -> 0.1001
A8: EQ00 | B8: Equipment | C8: =Datasets!B133 -> 0.1391 | D8: =Datasets!C133 -> 0.163 | E8: =Datasets!D133 -> 0.149 | F8: =Datasets!E133 -> 0.1361 | G8: =Datasets!F133 -> 0.1266 | H8: =Datasets!G133 -> 0.115 | I8: =Datasets!H133 -> 0.1062 | J8: =Datasets!I133 -> 0.1008 | ... CX8: =Datasets!CW133 -> 0.09
A9: EP00 | B9: Information | C9: =Datasets!B134 -> 0.135 | D9: =Datasets!C134 -> 0.135 | E9: =Datasets!D134 -> 0.135 | F9: =Datasets!E134 -> 0.135 | G9: =Datasets!F134 -> 0.135 | H9: =Datasets!G134 -> 0.135 | I9: =Datasets!H134 -> 0.135 | J9: =Datasets!I134 -> 0.135 | ... CX9: =Datasets!CW134 -> 0.1665
A10: EP11 | B10: Computers | C10: =Datasets!B135 -> 0 | D10: =Datasets!C135 -> 0 | E10: =Datasets!D135 -> 0 | F10: =Datasets!E135 -> 0 | G10: =Datasets!F135 -> 0 | H10: =Datasets!G135 -> 0 | I10: =Datasets!H135 -> 0 | J10: =Datasets!I135 -> 0 | ... CX10: =Datasets!CW135 -> 0.339
A11: EI00 | B11: Industrial | C11: =Datasets!B136 -> 0.0733 | D11: =Datasets!C136 -> 0.073 | E11: =Datasets!D136 -> 0.0722 | F11: =Datasets!E136 -> 0.072 | G11: =Datasets!F136 -> 0.0719 | H11: =Datasets!G136 -> 0.0713 | I11: =Datasets!H136 -> 0.0708 | J11: =Datasets!I136 -> 0.0705 | ... CX11: =Datasets!CW136 -> 0.078
A12: ET00 | B12: Transportation | C12: =Datasets!B137 -> 0.2387 | D12: =Datasets!C137 -> 0.2522 | E12: =Datasets!D137 -> 0.2527 | F12: =Datasets!E137 -> 0.2596 | G12: =Datasets!F137 -> 0.2659 | H12: =Datasets!G137 -> 0.2693 | I12: =Datasets!H137 -> 0.269 | J12: =Datasets!I137 -> 0.2621 | ... CX12: =Datasets!CW137 -> 0.1622
A13: EO00 | B13: Other equipment | C13: =Datasets!B138 -> 0 | D13: =Datasets!C138 -> 0 | E13: =Datasets!D138 -> 0.1179 | F13: =Datasets!E138 -> 0.1179 | G13: =Datasets!F138 -> 0.1179 | H13: =Datasets!G138 -> 0.1179 | I13: =Datasets!H138 -> 0.1179 | J13: =Datasets!I138 -> 0.1179 | ... CX13: =Datasets!CW138 -> 0.1463
A14: ST00 | B14: Structures | C14: =Datasets!B139 -> 0.0303 | D14: =Datasets!C139 -> 0.0302 | E14: =Datasets!D139 -> 0.0301 | F14: =Datasets!E139 -> 0.0301 | G14: =Datasets!F139 -> 0.03 | H14: =Datasets!G139 -> 0.03 | I14: =Datasets!H139 -> 0.03 | J14: =Datasets!I139 -> 0.03 | ... CX14: =Datasets!CW139 -> 0.0305
A15: SCHC | B15: Commercial and healthcare | C15: =Datasets!B140 -> 0.0247 | D15: =Datasets!C140 -> 0.0247 | E15: =Datasets!D140 -> 0.0247 | F15: =Datasets!E140 -> 0.0247 | G15: =Datasets!F140 -> 0.0247 | H15: =Datasets!G140 -> 0.0247 | I15: =Datasets!H140 -> 0.0247 | J15: =Datasets!I140 -> 0.0247 | ... CX15: =Datasets!CW140 -> 0.0242
A16: IP00 | B16: Intellectual property products | C16: =Datasets!B141 -> 0.16 | D16: =Datasets!C141 -> 0.16 | E16: =Datasets!D141 -> 0.16 | F16: =Datasets!E141 -> 0.16 | G16: =Datasets!F141 -> 0.16 | H16: =Datasets!G141 -> 0.16 | I16: =Datasets!H141 -> 0.16 | J16: =Datasets!I141 -> 0.16 | ... CX16: =Datasets!CW141 -> 0.1801

Sheet 3340
A1: 3340 - Computer and Electronic Products
A2: Implied Depreciation Rates for Private Nonresidential Fixed Assets
A3: Updated September 26, 2025
A5: Asset Codes | B5: NIPA Asset Types | C5: 1925 | D5: 1926 | E5: 1927 | F5: 1928 | G5: 1929 | H5: 1930 | I5: 1931 | J5: 1932 | K5: 1933 | L5: 1934 | M5: 1935 | N5: 1936 | O5: 1937 | P5: 1938 | Q5: 1939 | R5: 1940 | S5: 1941 | T5: 1942 | U5: 1943 | V5: 1944 | W5: 1945 | X5: 1946 | Y5: 1947 | Z5: 1948 | AA5: 1949 | AB5: 1950 | AC5: 1951 | AD5: 1952 | AE5: 1953 | AF5: 1954 | AG5: 1955 | AH5: 1956 | AI5: 1957 | AJ5: 1958 | AK5: 1959 | AL5: 1960 | AM5: 1961 | AN5: 1962 | AO5: 1963 | AP5: 1964 | AQ5: 1965 | AR5: 1966 | AS5: 1967 | AT5: 1968 | AU5: 1969 | AV5: 1970 | AW5: 1971 | AX5: 1972 | AY5: 1973 | AZ5: 1974 | BA5: 1975 | BB5: 1976 | BC5: 1977 | BD5: 1978 | BE5: 1979 | BF5: 1980 | BG5: 1981 | BH5: 1982 | BI5: 1983 | BJ5: 1984 | BK5: 1985 | BL5: 1986 | BM5: 1987 | BN5: 1988 | BO5: 1989 | BP5: 1990 | BQ5: 1991 | BR5: 1992 | BS5: 1993 | BT5: 1994 | BU5: 1995 | BV5: 1996 | BW5: 1997 | BX5: 1998 | BY5: 1999 | BZ5: 2000 | CA5: 2001 | CB5: 2002 | CC5: 2003 | CD5: 2004 | CE5: 2005 | CF5: 2006 | CG5: 2007 | CH5: 2008 | CI5: 2009 | CJ5: 2010 | CK5: 2011 | CL5: 2012 | CM5: 2013 | CN5: 2014 | CO5: 2015 | CP5: 2016 | CQ5: 2017 | CR5: 2018 | CS5: 2019 | CT5: 2020 | CU5: 2021 | CV5: 2022 | CW5: 2023 | CX5: 2024
A7: ES00 | B7: Equipment, structures, and intellectual property products | C7: =Datasets!B142 -> 0.079 | D7: =Datasets!C142 -> 0.0856 | E7: =Datasets!D142 -> 0.0872 | F7: =Datasets!E142 -> 0.0883 | G7: =Datasets!F142 -> 0.0889 | H7: =Datasets!G142 -> 0.0892 | I7: =Datasets!H142 -> 0.0902 | J7: =Datasets!I142 -> 0.0909 | ... CX7: =Datasets!CW142 -> 0.1884
A8: EQ00 | B8: Equipment | C8: =Datasets!B143 -> 0.1569 | D8: =Datasets!C143 -> 0.1705 | E8: =Datasets!D143 -> 0.1684 | F8: =Datasets!E143 -> 0.1679 | G8: =Datasets!F143 -> 0.1665 | H8: =Datasets!G143 -> 0.1617 | I8: =Datasets!H143 -> 0.1564 | J8: =Datasets!I143 -> 0.1519 | ... CX8: =Datasets!CW143 -> 0.131
A9: EP00 | B9: Information | C9: =Datasets!B144 -> 0.135 | D9: =Datasets!C144 -> 0.135 | E9: =Datasets!D144 -> 0.1105 | F9: =Datasets!E144 -> 0.1102 | G9: =Datasets!F144 -> 0.1101 | H9: =Datasets!G144 -> 0.1101 | I9: =Datasets!H144 -> 0.1101 | J9: =Datasets!I144 -> 0.1101 | ... CX9: =Datasets!CW144 -> 0.1538
A10: EP11 | B10: Computers | C10: =Datasets!B145 -> 0 | D10: =Datasets!C145 -> 0 | E10: =Datasets!D145 -> 0 | F10: =Datasets!E145 -> 0 | G10: =Datasets!F145 -> 0 | H10: =Datasets!G145 -> 0 | I10: =Datasets!H145 -> 0 | J10: =Datasets!I145 -> 0 | ... CX10: =Datasets!CW145 -> 0.3377
A11: EI00 | B11: Industrial | C11: =Datasets!B146 -> 0.1245 | D11: =Datasets!C146 -> 0.1242 | E11: =Datasets!D146 -> 0.1233 | F11: =Datasets!E146 -> 0.1223 | G11: =Datasets!F146 -> 0.1217 | H11: =Datasets!G146 -> 0.1206 | I11: =Datasets!H146 -> 0.1194 | J11: =Datasets!I146 -> 0.1186 | ... CX11: =Datasets!CW146 -> 0.1133
A12: ET00 | B12: Transportation | C12: =Datasets!B147 -> 0.2387 | D12: =Datasets!C147 -> 0.2522 | E12: =Datasets!D147 -> 0.2527 | F12: =Datasets!E147 -> 0.2596 | G12: =Datasets!F147 -> 0.2659 | H12: =Datasets!G147 -> 0.2693 | I12: =Datasets!H147 -> 0.269 | J12: =Datasets!I147 -> 0.2621 | ... CX12: =Datasets!CW147 -> 0.1286
A13: EO00 | B13: Other equipment | C13: =Datasets!B148 -> 0.1211 | D13: =Datasets!C148 -> 0.1216 | E13: =Datasets!D148 -> 0.1228 | F13: =Datasets!E148 -> 0.1236 | G13: =Datasets!F148 -> 0.1222 | H13: =Datasets!G148 -> 0.1197 | I13: =Datasets!H148 -> 0.1189 | J13: =Datasets!I148 -> 0.1188 | ... CX13: =Datasets!CW148 -> 0.1478
A14: ST00 | B14: Structures | C14: =Datasets!B149 -> 0.0303 | D14: =Datasets!C149 -> 0.0302 | E14: =Datasets!D149 -> 0.0302 | F14: =Datasets!E149 -> 0.0302 | G14: =Datasets!F149 -> 0.0303 | H14: =Datasets!G149 -> 0.0303 | I14: =Datasets!H149 -> 0.0303 | J14: =Datasets!I149 -> 0.0303 | ... CX14: =Datasets!CW149 -> 0.0307
A15: SCHC | B15: Commercial and healthcare | C15: =Datasets!B150 -> 0.0247 | D15: =Datasets!C150 -> 0.0247 | E15: =Datasets!D150 -> 0.0247 | F15: =Datasets!E150 -> 0.0247 | G15: =Datasets!F150 -> 0.0247 | H15: =Datasets!G150 -> 0.0247 | I15: =Datasets!H150 -> 0.0247 | J15: =Datasets!I150 -> 0.0247 | ... CX15: =Datasets!CW150 -> 0.0247
A16: IP00 | B16: Intellectual property products | C16: =Datasets!B151 -> 0.2708 | D16: =Datasets!C151 -> 0.2708 | E16: =Datasets!D151 -> 0.2707 | F16: =Datasets!E151 -> 0.2707 | G16: =Datasets!F151 -> 0.2713 | H16: =Datasets!G151 -> 0.2722 | I16: =Datasets!H151 -> 0.2728 | J16: =Datasets!I151 -> 0.2725 | ... CX16: =Datasets!CW151 -> 0.2899

Sheet 3350
A1: 3350 - Electrical Equipment, Appliances, and Components
A2: Implied Depreciation Rates for Private Nonresidential Fixed Assets
A3: Updated September 26, 2025
A5: Asset Codes | B5: NIPA Asset Types | C5: 1925 | D5: 1926 | E5: 1927 | F5: 1928 | G5: 1929 | H5: 1930 | I5: 1931 | J5: 1932 | K5: 1933 | L5: 1934 | M5: 1935 | N5: 1936 | O5: 1937 | P5: 1938 | Q5: 1939 | R5: 1940 | S5: 1941 | T5: 1942 | U5: 1943 | V5: 1944 | W5: 1945 | X5: 1946 | Y5: 1947 | Z5: 1948 | AA5: 1949 | AB5: 1950 | AC5: 1951 | AD5: 1952 | AE5: 1953 | AF5: 1954 | AG5: 1955 | AH5: 1956 | AI5: 1957 | AJ5: 1958 | AK5: 1959 | AL5: 1960 | AM5: 1961 | AN5: 1962 | AO5: 1963 | AP5: 1964 | AQ5: 1965 | AR5: 1966 | AS5: 1967 | AT5: 1968 | AU5: 1969 | AV5: 1970 | AW5: 1971 | AX5: 1972 | AY5: 1973 | AZ5: 1974 | BA5: 1975 | BB5: 1976 | BC5: 1977 | BD5: 1978 | BE5: 1979 | BF5: 1980 | BG5: 1981 | BH5: 1982 | BI5: 1983 | BJ5: 1984 | BK5: 1985 | BL5: 1986 | BM5: 1987 | BN5: 1988 | BO5: 1989 | BP5: 1990 | BQ5: 1991 | BR5: 1992 | BS5: 1993 | BT5: 1994 | BU5: 1995 | BV5: 1996 | BW5: 1997 | BX5: 1998 | BY5: 1999 | BZ5: 2000 | CA5: 2001 | CB5: 2002 | CC5: 2003 | CD5: 2004 | CE5: 2005 | CF5: 2006 | CG5: 2007 | CH5: 2008 | CI5: 2009 | CJ5: 2010 | CK5: 2011 | CL5: 2012 | CM5: 2013 | CN5: 2014 | CO5: 2015 | CP5: 2016 | CQ5: 2017 | CR5: 2018 | CS5: 2019 | CT5: 2020 | CU5: 2021 | CV5: 2022 | CW5: 2023 | CX5: 2024
A7: ES00 | B7: Equipment, structures, and intellectual property products | C7: =Datasets!B152 -> 0.0967 | D7: =Datasets!C152 -> 0.0978 | E7: =Datasets!D152 -> 0.0966 | F7: =Datasets!E152 -> 0.0963 | G7: =Datasets!F152 -> 0.0959 | H7: =Datasets!G152 -> 0.0962 | I7: =Datasets!H152 -> 0.0978 | J7: =Datasets!I152 -> 0.0996 | ... CX7: =Datasets!CW152 -> 0.1115
A8: EQ00 | B8: Equipment | C8: =Datasets!B153 -> 0.1737 | D8: =Datasets!C153 -> 0.171 | E8: =Datasets!D153 -> 0.1627 | F8: =Datasets!E153 -> 0.1583 | G8: =Datasets!F153 -> 0.1544 | H8: =Datasets!G153 -> 0.1489 | I8: =Datasets!H153 -> 0.1437 | J8: =Datasets!I153 -> 0.1398 | ... CX8: =Datasets!CW153 -> 0.1203
A9: EP00 | B9: Information | C9: =Datasets!B154 -> 0 | D9: =Datasets!C154 -> 0 | E9: =Datasets!D154 -> 0.11 | F9: =Datasets!E154 -> 0.11 | G9: =Datasets!F154 -> 0.11 | H9: =Datasets!G154 -> 0.11 | I9: =Datasets!H154 -> 0.11 | J9: =Datasets!I154 -> 0.11 | ... CX9: =Datasets!CW154 -> 0.1884
A10: EP11 | B10: Computers | C10: =Datasets!B155 -> 0 | D10: =Datasets!C155 -> 0 | E10: =Datasets!D155 -> 0 | F10: =Datasets!E155 -> 0 | G10: =Datasets!F155 -> 0 | H10: =Datasets!G155 -> 0 | I10: =Datasets!H155 -> 0 | J10: =Datasets!I155 -> 0 | ... CX10: =Datasets!CW155 -> 0.3401
A11: EI00 | B11: Industrial | C11: =Datasets!B156 -> 0.1264 | D11: =Datasets!C156 -> 0.1261 | E11: =Datasets!D156 -> 0.1254 | F11: =Datasets!E156 -> 0.1245 | G11: =Datasets!F156 -> 0.1236 | H11: =Datasets!G156 -> 0.1224 | I11: =Datasets!H156 -> 0.1212 | J11: =Datasets!I156 -> 0.1203 | ... CX11: =Datasets!CW156 -> 0.1056
A12: ET00 | B12: Transportation | C12: =Datasets!B157 -> 0.2387 | D12: =Datasets!C157 -> 0.2522 | E12: =Datasets!D157 -> 0.2527 | F12: =Datasets!E157 -> 0.2596 | G12: =Datasets!F157 -> 0.2659 | H12: =Datasets!G157 -> 0.2693 | I12: =Datasets!H157 -> 0.269 | J12: =Datasets!I157 -> 0.2621 | ... CX12: =Datasets!CW157 -> 0.1349
A13: EO00 | B13: Other equipment | C13: =Datasets!B158 -> 0 | D13: =Datasets!C158 -> 0 | E13: =Datasets!D158 -> 0 | F13: =Datasets!E158 -> 0 | G13: =Datasets!F158 -> 0 | H13: =Datasets!G158 -> 0.1179 | I13: =Datasets!H158 -> 0.1179 | J13: =Datasets!I158 -> 0.1179 | ... CX13: =Datasets!CW158 -> 0.1498
A14: ST00 | B14: Structures | C14: =Datasets!B159 -> 0.0298 | D14: =Datasets!C159 -> 0.0297 | E14: =Datasets!D159 -> 0.0296 | F14: =Datasets!E159 -> 0.0295 | G14: =Datasets!F159 -> 0.0294 | H14: =Datasets!G159 -> 0.0294 | I14: =Datasets!H159 -> 0.0293 | J14: =Datasets!I159 -> 0.0293 | ... CX14: =Datasets!CW159 -> 0.0298
A15: SCHC | B15: Commercial and healthcare | C15: =Datasets!B160 -> 0.0247 | D15: =Datasets!C160 -> 0.0247 | E15: =Datasets!D160 -> 0.0247 | F15: =Datasets!E160 -> 0.0247 | G15: =Datasets!F160 -> 0.0247 | H15: =Datasets!G160 -> 0.0247 | I15: =Datasets!H160 -> 0.0247 | J15: =Datasets!I160 -> 0.0247 | ... CX15: =Datasets!CW160 -> 0.0246
A16: IP00 | B16: Intellectual property products | C16: =Datasets!B161 -> 0.16 | D16: =Datasets!C161 -> 0.16 | E16: =Datasets!D161 -> 0.16 | F16: =Datasets!E161 -> 0.16 | G16: =Datasets!F161 -> 0.16 | H16: =Datasets!G161 -> 0.16 | I16: =Datasets!H161 -> 0.16 | J16: =Datasets!I161 -> 0.16 | ... CX16: =Datasets!CW161 -> 0.1768

Sheet 336M
A1: 336M - Motor Vehicles, Bodies and Trailers, and Parts
A2: Implied Depreciation Rates for Private Nonresidential Fixed Assets
A3: Updated September 26, 2025
A5: Asset Codes | B5: NIPA Asset Types | C5: 1925 | D5: 1926 | E5: 1927 | F5: 1928 | G5: 1929 | H5: 1930 | I5: 1931 | J5: 1932 | K5: 1933 | L5: 1934 | M5: 1935 | N5: 1936 | O5: 1937 | P5: 1938 | Q5: 1939 | R5: 1940 | S5: 1941 | T5: 1942 | U5: 1943 | V5: 1944 | W5: 1945 | X5: 1946 | Y5: 1947 | Z5: 1948 | AA5: 1949 | AB5: 1950 | AC5: 1951 | AD5: 1952 | AE5: 1953 | AF5: 1954 | AG5: 1955 | AH5: 1956 | AI5: 1957 | AJ5: 1958 | AK5: 1959 | AL5: 1960 | AM5: 1961 | AN5: 1962 | AO5: 1963 | AP5: 1964 | AQ5: 1965 | AR5: 1966 | AS5: 1967 | AT5: 1968 | AU5: 1969 | AV5: 1970 | AW5: 1971 | AX5: 1972 | AY5: 1973 | AZ5: 1974 | BA5: 1975 | BB5: 1976 | BC5: 1977 | BD5: 1978 | BE5: 1979 | BF5: 1980 | BG5: 1981 | BH5: 1982 | BI5: 1983 | BJ5: 1984 | BK5: 1985 | BL5: 1986 | BM5: 1987 | BN5: 1988 | BO5: 1989 | BP5: 1990 | BQ5: 1991 | BR5: 1992 | BS5: 1993 | BT5: 1994 | BU5: 1995 | BV5: 1996 | BW5: 1997 | BX5: 1998 | BY5: 1999 | BZ5: 2000 | CA5: 2001 | CB5: 2002 | CC5: 2003 | CD5: 2004 | CE5: 2005 | CF5: 2006 | CG5: 2007 | CH5: 2008 | CI5: 2009 | CJ5: 2010 | CK5: 2011 | CL5: 2012 | CM5: 2013 | CN5: 2014 | CO5: 2015 | CP5: 2016 | CQ5: 2017 | CR5: 2018 | CS5: 2019 | CT5: 2020 | CU5: 2021 | CV5: 2022 | CW5: 2023 | CX5: 2024
A7: ES00 | B7: Equipment, structures, and intellectual property products | C7: =Datasets!B162 -> 0.0978 | D7: =Datasets!C162 -> 0.0959 | E7: =Datasets!D162 -> 0.0931 | F7: =Datasets!E162 -> 0.0908 | G7: =Datasets!F162 -> 0.0884 | H7: =Datasets!G162 -> 0.0867 | I7: =Datasets!H162 -> 0.0861 | J7: =Datasets!I162 -> 0.0857 | ... CX7: =Datasets!CW162 -> 0.1634
A8: EQ00 | B8: Equipment | C8: =Datasets!B163 -> 0.1265 | D8: =Datasets!C163 -> 0.1284 | E8: =Datasets!D163 -> 0.1293 | F8: =Datasets!E163 -> 0.1306 | G8: =Datasets!F163 -> 0.132 | H8: =Datasets!G163 -> 0.1329 | I8: =Datasets!H163 -> 0.1334 | J8: =Datasets!I163 -> 0.1333 | ... CX8: =Datasets!CW163 -> 0.1353
A9: EP00 | B9: Information | C9: =Datasets!B164 -> 0.135 | D9: =Datasets!C164 -> 0.135 | E9: =Datasets!D164 -> 0.135 | F9: =Datasets!E164 -> 0.135 | G9: =Datasets!F164 -> 0.135 | H9: =Datasets!G164 -> 0.135 | I9: =Datasets!H164 -> 0.135 | J9: =Datasets!I164 -> 0.135 | ... CX9: =Datasets!CW164 -> 0.1706
A10: EP11 | B10: Computers | C10: =Datasets!B165 -> 0 | D10: =Datasets!C165 -> 0 | E10: =Datasets!D165 -> 0 | F10: =Datasets!E165 -> 0 | G10: =Datasets!F165 -> 0 | H10: =Datasets!G165 -> 0 | I10: =Datasets!H165 -> 0 | J10: =Datasets!I165 -> 0 | ... CX10: =Datasets!CW165 -> 0.3391
A11: EI00 | B11: Industrial | C11: =Datasets!B166 -> 0.123 | D11: =Datasets!C166 -> 0.1232 | E11: =Datasets!D166 -> 0.1234 | F11: =Datasets!E166 -> 0.1238 | G11: =Datasets!F166 -> 0.1243 | H11: =Datasets!G166 -> 0.1248 | I11: =Datasets!H166 -> 0.1251 | J11: =Datasets!I166 -> 0.1253 | ... CX11: =Datasets!CW166 -> 0.128
A12: ET00 | B12: Transportation | C12: =Datasets!B167 -> 0.2387 | D12: =Datasets!C167 -> 0.2522 | E12: =Datasets!D167 -> 0.2527 | F12: =Datasets!E167 -> 0.2596 | G12: =Datasets!F167 -> 0.2659 | H12: =Datasets!G167 -> 0.2693 | I12: =Datasets!H167 -> 0.269 | J12: =Datasets!I167 -> 0.2621 | ... CX12: =Datasets!CW167 -> 0.1711
A13: EO00 | B13: Other equipment | C13: =Datasets!B168 -> 0.1199 | D13: =Datasets!C168 -> 0.1203 | E13: =Datasets!D168 -> 0.1207 | F13: =Datasets!E168 -> 0.121 | G13: =Datasets!F168 -> 0.1187 | H13: =Datasets!G168 -> 0.1181 | I13: =Datasets!H168 -> 0.118 | J13: =Datasets!I168 -> 0.118 | ... CX13: =Datasets!CW168 -> 0.1478
A14: ST00 | B14: Structures | C14: =Datasets!B169 -> 0.0309 | D14: =Datasets!C169 -> 0.0309 | E14: =Datasets!D169 -> 0.0309 | F14: =Datasets!E169 -> 0.0309 | G14: =Datasets!F169 -> 0.0309 | H14: =Datasets!G169 -> 0.0309 | I14: =Datasets!H169 -> 0.0309 | J14: =Datasets!I169 -> 0.0309 | ... CX14: =Datasets!CW169 -> 0.0313
A15: SCHC | B15: Commercial and healthcare | C15: =Datasets!B170 -> 0.0247 | D15: =Datasets!C170 -> 0.0247 | E15: =Datasets!D170 -> 0.0247 | F15: =Datasets!E170 -> 0.0247 | G15: =Datasets!F170 -> 0.0247 | H15: =Datasets!G170 -> 0.0247 | I15: =Datasets!H170 -> 0.0247 | J15: =Datasets!I170 -> 0.0247 | ... CX15: =Datasets!CW170 -> 0.0245
A16: IP00 | B16: Intellectual property products | C16: =Datasets!B171 -> 0.31 | D16: =Datasets!C171 -> 0.31 | E16: =Datasets!D171 -> 0.31 | F16: =Datasets!E171 -> 0.31 | G16: =Datasets!F171 -> 0.31 | H16: =Datasets!G171 -> 0.31 | I16: =Datasets!H171 -> 0.31 | J16: =Datasets!I171 -> 0.31 | ... CX16: =Datasets!CW171 -> 0.3155

Sheet 336O
A1: 336O - Other Transportation Equipment
A2: Implied Depreciation Rates for Private Nonresidential Fixed Assets
A3: Updated September 26, 2025
A5: Asset Codes | B5: NIPA Asset Types | C5: 1925 | D5: 1926 | E5: 1927 | F5: 1928 | G5: 1929 | H5: 1930 | I5: 1931 | J5: 1932 | K5: 1933 | L5: 1934 | M5: 1935 | N5: 1936 | O5: 1937 | P5: 1938 | Q5: 1939 | R5: 1940 | S5: 1941 | T5: 1942 | U5: 1943 | V5: 1944 | W5: 1945 | X5: 1946 | Y5: 1947 | Z5: 1948 | AA5: 1949 | AB5: 1950 | AC5: 1951 | AD5: 1952 | AE5: 1953 | AF5: 1954 | AG5: 1955 | AH5: 1956 | AI5: 1957 | AJ5: 1958 | AK5: 1959 | AL5: 1960 | AM5: 1961 | AN5: 1962 | AO5: 1963 | AP5: 1964 | AQ5: 1965 | AR5: 1966 | AS5: 1967 | AT5: 1968 | AU5: 1969 | AV5: 1970 | AW5: 1971 | AX5: 1972 | AY5: 1973 | AZ5: 1974 | BA5: 1975 | BB5: 1976 | BC5: 1977 | BD5: 1978 | BE5: 1979 | BF5: 1980 | BG5: 1981 | BH5: 1982 | BI5: 1983 | BJ5: 1984 | BK5: 1985 | BL5: 1986 | BM5: 1987 | BN5: 1988 | BO5: 1989 | BP5: 1990 | BQ5: 1991 | BR5: 1992 | BS5: 1993 | BT5: 1994 | BU5: 1995 | BV5: 1996 | BW5: 1997 | BX5: 1998 | BY5: 1999 | BZ5: 2000 | CA5: 2001 | CB5: 2002 | CC5: 2003 | CD5: 2004 | CE5: 2005 | CF5: 2006 | CG5: 2007 | CH5: 2008 | CI5: 2009 | CJ5: 2010 | CK5: 2011 | CL5: 2012 | CM5: 2013 | CN5: 2014 | CO5: 2015 | CP5: 2016 | CQ5: 2017 | CR5: 2018 | CS5: 2019 | CT5: 2020 | CU5: 2021 | CV5: 2022 | CW5: 2023 | CX5: 2024
A7: ES00 | B7: Equipment, structures, and intellectual property products | C7: =Datasets!B172 -> 0.0379 | D7: =Datasets!C172 -> 0.0403 | E7: =Datasets!D172 -> 0.0412 | F7: =Datasets!E172 -> 0.0421 | G7: =Datasets!F172 -> 0.0428 | H7: =Datasets!G172 -> 0.0434 | I7: =Datasets!H172 -> 0.0436 | J7: =Datasets!I172 -> 0.0435 | ... CX7: =Datasets!CW172 -> 0.1322
A8: EQ00 | B8: Equipment | C8: =Datasets!B173 -> 0.1229 | D8: =Datasets!C173 -> 0.1341 | E8: =Datasets!D173 -> 0.1347 | F8: =Datasets!E173 -> 0.1358 | G8: =Datasets!F173 -> 0.1356 | H8: =Datasets!G173 -> 0.1341 | I8: =Datasets!H173 -> 0.1322 | J8: =Datasets!I173 -> 0.1301 | ... CX8: =Datasets!CW173 -> 0.1171
A9: EP00 | B9: Information | C9: =Datasets!B174 -> 0.135 | D9: =Datasets!C174 -> 0.135 | E9: =Datasets!D174 -> 0.135 | F9: =Datasets!E174 -> 0.135 | G9: =Datasets!F174 -> 0.135 | H9: =Datasets!G174 -> 0.135 | I9: =Datasets!H174 -> 0.135 | J9: =Datasets!I174 -> 0.135 | ... CX9: =Datasets!CW174 -> 0.1922
A10: EP11 | B10: Computers | C10: =Datasets!B175 -> 0 | D10: =Datasets!C175 -> 0 | E10: =Datasets!D175 -> 0 | F10: =Datasets!E175 -> 0 | G10: =Datasets!F175 -> 0 | H10: =Datasets!G175 -> 0 | I10: =Datasets!H175 -> 0 | J10: =Datasets!I175 -> 0 | ... CX10: =Datasets!CW175 -> 0.3382
A11: EI00 | B11: Industrial | C11: =Datasets!B176 -> 0.1068 | D11: =Datasets!C176 -> 0.1063 | E11: =Datasets!D176 -> 0.1056 | F11: =Datasets!E176 -> 0.1051 | G11: =Datasets!F176 -> 0.1046 | H11: =Datasets!G176 -> 0.1038 | I11: =Datasets!H176 -> 0.1029 | J11: =Datasets!I176 -> 0.1021 | ... CX11: =Datasets!CW176 -> 0.1029
A12: ET00 | B12: Transportation | C12: =Datasets!B177 -> 0.2387 | D12: =Datasets!C177 -> 0.2522 | E12: =Datasets!D177 -> 0.2527 | F12: =Datasets!E177 -> 0.2596 | G12: =Datasets!F177 -> 0.2659 | H12: =Datasets!G177 -> 0.2693 | I12: =Datasets!H177 -> 0.269 | J12: =Datasets!I177 -> 0.2621 | ... CX12: =Datasets!CW177 -> 0.1094
A13: EO00 | B13: Other equipment | C13: =Datasets!B178 -> 0 | D13: =Datasets!C178 -> 0 | E13: =Datasets!D178 -> 0.1179 | F13: =Datasets!E178 -> 0.1179 | G13: =Datasets!F178 -> 0.1179 | H13: =Datasets!G178 -> 0.1179 | I13: =Datasets!H178 -> 0.1179 | J13: =Datasets!I178 -> 0.1179 | ... CX13: =Datasets!CW178 -> 0.1493
A14: ST00 | B14: Structures | C14: =Datasets!B179 -> 0.0311 | D14: =Datasets!C179 -> 0.0311 | E14: =Datasets!D179 -> 0.0311 | F14: =Datasets!E179 -> 0.031 | G14: =Datasets!F179 -> 0.031 | H14: =Datasets!G179 -> 0.031 | I14: =Datasets!H179 -> 0.031 | J14: =Datasets!I179 -> 0.031 | ... CX14: =Datasets!CW179 -> 0.0308
A15: SCHC | B15: Commercial and healthcare | C15: =Datasets!B180 -> 0.0247 | D15: =Datasets!C180 -> 0.0247 | E15: =Datasets!D180 -> 0.0247 | F15: =Datasets!E180 -> 0.0247 | G15: =Datasets!F180 -> 0.0247 | H15: =Datasets!G180 -> 0.0247 | I15: =Datasets!H180 -> 0.0247 | J15: =Datasets!I180 -> 0.0247 | ... CX15: =Datasets!CW180 -> 0.0242
A16: IP00 | B16: Intellectual property products | C16: =Datasets!B181 -> 0.16 | D16: =Datasets!C181 -> 0.16 | E16: =Datasets!D181 -> 0.16 | F16: =Datasets!E181 -> 0.16 | G16: =Datasets!F181 -> 0.16 | H16: =Datasets!G181 -> 0.16 | I16: =Datasets!H181 -> 0.16 | J16: =Datasets!I181 -> 0.16 | ... CX16: =Datasets!CW181 -> 0.227

Sheet 3370
A1: 3370 - Furniture and Related Products
A2: Implied Depreciation Rates for Private Nonresidential Fixed Assets
A3: Updated September 26, 2025
A5: Asset Codes | B5: NIPA Asset Types | C5: 1925 | D5: 1926 | E5: 1927 | F5: 1928 | G5: 1929 | H5: 1930 | I5: 1931 | J5: 1932 | K5: 1933 | L5: 1934 | M5: 1935 | N5: 1936 | O5: 1937 | P5: 1938 | Q5: 1939 | R5: 1940 | S5: 1941 | T5: 1942 | U5: 1943 | V5: 1944 | W5: 1945 | X5: 1946 | Y5: 1947 | Z5: 1948 | AA5: 1949 | AB5: 1950 | AC5: 1951 | AD5: 1952 | AE5: 1953 | AF5: 1954 | AG5: 1955 | AH5: 1956 | AI5: 1957 | AJ5: 1958 | AK5: 1959 | AL5: 1960 | AM5: 1961 | AN5: 1962 | AO5: 1963 | AP5: 1964 | AQ5: 1965 | AR5: 1966 | AS5: 1967 | AT5: 1968 | AU5: 1969 | AV5: 1970 | AW5: 1971 | AX5: 1972 | AY5: 1973 | AZ5: 1974 | BA5: 1975 | BB5: 1976 | BC5: 1977 | BD5: 1978 | BE5: 1979 | BF5: 1980 | BG5: 1981 | BH5: 1982 | BI5: 1983 | BJ5: 1984 | BK5: 1985 | BL5: 1986 | BM5: 1987 | BN5: 1988 | BO5: 1989 | BP5: 1990 | BQ5: 1991 | BR5: 1992 | BS5: 1993 | BT5: 1994 | BU5: 1995 | BV5: 1996 | BW5: 1997 | BX5: 1998 | BY5: 1999 | BZ5: 2000 | CA5: 2001 | CB5: 2002 | CC5: 2003 | CD5: 2004 | CE5: 2005 | CF5: 2006 | CG5: 2007 | CH5: 2008 | CI5: 2009 | CJ5: 2010 | CK5: 2011 | CL5: 2012 | CM5: 2013 | CN5: 2014 | CO5: 2015 | CP5: 2016 | CQ5: 2017 | CR5: 2018 | CS5: 2019 | CT5: 2020 | CU5: 2021 | CV5: 2022 | CW5: 2023 | CX5: 2024
A7: ES00 | B7: Equipment, structures, and intellectual property products | C7: =Datasets!B182 -> 0.046 | D7: =Datasets!C182 -> 0.049 | E7: =Datasets!D182 -> 0.0508 | F7: =Datasets!E182 -> 0.0526 | G7: =Datasets!F182 -> 0.0543 | H7: =Datasets!G182 -> 0.0561 | I7: =Datasets!H182 -> 0.057 | J7: =Datasets!I182 -> 0.0567 | ... CX7: =Datasets!CW182 -> 0.1027
A8: EQ00 | B8: Equipment | C8: =Datasets!B183 -> 0.1292 | D8: =Datasets!C183 -> 0.1333 | E8: =Datasets!D183 -> 0.1329 | F8: =Datasets!E183 -> 0.1331 | G8: =Datasets!F183 -> 0.1333 | H8: =Datasets!G183 -> 0.1325 | I8: =Datasets!H183 -> 0.1318 | J8: =Datasets!I183 -> 0.1311 | ... CX8: =Datasets!CW183 -> 0.1331
A9: EP00 | B9: Information | C9: =Datasets!B184 -> 0.135 | D9: =Datasets!C184 -> 0.135 | E9: =Datasets!D184 -> 0.135 | F9: =Datasets!E184 -> 0.135 | G9: =Datasets!F184 -> 0.135 | H9: =Datasets!G184 -> 0.135 | I9: =Datasets!H184 -> 0.135 | J9: =Datasets!I184 -> 0.135 | ... CX9: =Datasets!CW184 -> 0.1949
A10: EP11 | B10: Computers | C10: =Datasets!B185 -> 0 | D10: =Datasets!C185 -> 0 | E10: =Datasets!D185 -> 0 | F10: =Datasets!E185 -> 0 | G10: =Datasets!F185 -> 0 | H10: =Datasets!G185 -> 0 | I10: =Datasets!H185 -> 0 | J10: =Datasets!I185 -> 0 | ... CX10: =Datasets!CW185 -> 0.3409
A11: EI00 | B11: Industrial | C11: =Datasets!B186 -> 0.1227 | D11: =Datasets!C186 -> 0.1224 | E11: =Datasets!D186 -> 0.1221 | F11: =Datasets!E186 -> 0.1224 | G11: =Datasets!F186 -> 0.1232 | H11: =Datasets!G186 -> 0.1234 | I11: =Datasets!H186 -> 0.1234 | J11: =Datasets!I186 -> 0.1231 | ... CX11: =Datasets!CW186 -> 0.1203
A12: ET00 | B12: Transportation | C12: =Datasets!B187 -> 0.2387 | D12: =Datasets!C187 -> 0.2522 | E12: =Datasets!D187 -> 0.2527 | F12: =Datasets!E187 -> 0.2596 | G12: =Datasets!F187 -> 0.2659 | H12: =Datasets!G187 -> 0.2693 | I12: =Datasets!H187 -> 0.269 | J12: =Datasets!I187 -> 0.2621 | ... CX12: =Datasets!CW187 -> 0.1822
A13: EO00 | B13: Other equipment | C13: =Datasets!B188 -> 0.1562 | D13: =Datasets!C188 -> 0.1563 | E13: =Datasets!D188 -> 0.1566 | F13: =Datasets!E188 -> 0.1568 | G13: =Datasets!F188 -> 0.12 | H13: =Datasets!G188 -> 0.1186 | I13: =Datasets!H188 -> 0.1184 | J13: =Datasets!I188 -> 0.1184 | ... CX13: =Datasets!CW188 -> 0.1366
A14: ST00 | B14: Structures | C14: =Datasets!B189 -> 0.0314 | D14: =Datasets!C189 -> 0.0314 | E14: =Datasets!D189 -> 0.0314 | F14: =Datasets!E189 -> 0.0314 | G14: =Datasets!F189 -> 0.0314 | H14: =Datasets!G189 -> 0.0314 | I14: =Datasets!H189 -> 0.0314 | J14: =Datasets!I189 -> 0.0314 | ... CX14: =Datasets!CW189 -> 0.0302
A15: SCHC | B15: Commercial and healthcare | C15: =Datasets!B190 -> 0 | D15: =Datasets!C190 -> 0 | E15: =Datasets!D190 -> 0 | F15: =Datasets!E190 -> 0 | G15: =Datasets!F190 -> 0 | H15: =Datasets!G190 -> 0 | I15: =Datasets!H190 -> 0 | J15: =Datasets!I190 -> 0 | ... CX15: =Datasets!CW190 -> 0.024
A16: IP00 | B16: Intellectual property products | C16: =Datasets!B191 -> 0 | D16: =Datasets!C191 -> 0 | E16: =Datasets!D191 -> 0 | F16: =Datasets!E191 -> 0 | G16: =Datasets!F191 -> 0 | H16: =Datasets!G191 -> 0 | I16: =Datasets!H191 -> 0 | J16: =Datasets!I191 -> 0 | ... CX16: =Datasets!CW191 -> 0.2307

Sheet 3380
A1: 3380 - Medical Equipment and Supplies
A2: Implied Depreciation Rates for Private Nonresidential Fixed Assets
A3: Updated September 26, 2025
A5: Asset Codes | B5: NIPA Asset Types | C5: 1925 | D5: 1926 | E5: 1927 | F5: 1928 | G5: 1929 | H5: 1930 | I5: 1931 | J5: 1932 | K5: 1933 | L5: 1934 | M5: 1935 | N5: 1936 | O5: 1937 | P5: 1938 | Q5: 1939 | R5: 1940 | S5: 1941 | T5: 1942 | U5: 1943 | V5: 1944 | W5: 1945 | X5: 1946 | Y5: 1947 | Z5: 1948 | AA5: 1949 | AB5: 1950 | AC5: 1951 | AD5: 1952 | AE5: 1953 | AF5: 1954 | AG5: 1955 | AH5: 1956 | AI5: 1957 | AJ5: 1958 | AK5: 1959 | AL5: 1960 | AM5: 1961 | AN5: 1962 | AO5: 1963 | AP5: 1964 | AQ5: 1965 | AR5: 1966 | AS5: 1967 | AT5: 1968 | AU5: 1969 | AV5: 1970 | AW5: 1971 | AX5: 1972 | AY5: 1973 | AZ5: 1974 | BA5: 1975 | BB5: 1976 | BC5: 1977 | BD5: 1978 | BE5: 1979 | BF5: 1980 | BG5: 1981 | BH5: 1982 | BI5: 1983 | BJ5: 1984 | BK5: 1985 | BL5: 1986 | BM5: 1987 | BN5: 1988 | BO5: 1989 | BP5: 1990 | BQ5: 1991 | BR5: 1992 | BS5: 1993 | BT5: 1994 | BU5: 1995 | BV5: 1996 | BW5: 1997 | BX5: 1998 | BY5: 1999 | BZ5: 2000 | CA5: 2001 | CB5: 2002 | CC5: 2003 | CD5: 2004 | CE5: 2005 | CF5: 2006 | CG5: 2007 | CH5: 2008 | CI5: 2009 | CJ5: 2010 | CK5: 2011 | CL5: 2012 | CM5: 2013 | CN5: 2014 | CO5: 2015 | CP5: 2016 | CQ5: 2017 | CR5: 2018 | CS5: 2019 | CT5: 2020 | CU5: 2021 | CV5: 2022 | CW5: 2023 | CX5: 2024
A7: ES00 | B7: Equipment, structures, and intellectual property products | C7: =Datasets!B192 -> 0.0614 | D7: =Datasets!C192 -> 0.0679 | E7: =Datasets!D192 -> 0.0702 | F7: =Datasets!E192 -> 0.0719 | G7: =Datasets!F192 -> 0.0738 | H7: =Datasets!G192 -> 0.0751 | I7: =Datasets!H192 -> 0.0754 | J7: =Datasets!I192 -> 0.0748 | ... CX7: =Datasets!CW192 -> 0.1432
A8: EQ00 | B8: Equipment | C8: =Datasets!B193 -> 0.1403 | D8: =Datasets!C193 -> 0.1472 | E8: =Datasets!D193 -> 0.1477 | F8: =Datasets!E193 -> 0.1488 | G8: =Datasets!F193 -> 0.1484 | H8: =Datasets!G193 -> 0.1466 | I8: =Datasets!H193 -> 0.1452 | J8: =Datasets!I193 -> 0.144 | ... CX8: =Datasets!CW193 -> 0.1522
A9: EP00 | B9: Information | C9: =Datasets!B194 -> 0.135 | D9: =Datasets!C194 -> 0.135 | E9: =Datasets!D194 -> 0.135 | F9: =Datasets!E194 -> 0.135 | G9: =Datasets!F194 -> 0.135 | H9: =Datasets!G194 -> 0.135 | I9: =Datasets!H194 -> 0.135 | J9: =Datasets!I194 -> 0.135 | ... CX9: =Datasets!CW194 -> 0.1721
A10: EP11 | B10: Computers | C10: =Datasets!B195 -> 0 | D10: =Datasets!C195 -> 0 | E10: =Datasets!D195 -> 0 | F10: =Datasets!E195 -> 0 | G10: =Datasets!F195 -> 0 | H10: =Datasets!G195 -> 0 | I10: =Datasets!H195 -> 0 | J10: =Datasets!I195 -> 0 | ... CX10: =Datasets!CW195 -> 0.338
A11: EI00 | B11: Industrial | C11: =Datasets!B196 -> 0.1327 | D11: =Datasets!C196 -> 0.1322 | E11: =Datasets!D196 -> 0.1319 | F11: =Datasets!E196 -> 0.1322 | G11: =Datasets!F196 -> 0.1322 | H11: =Datasets!G196 -> 0.1316 | I11: =Datasets!H196 -> 0.131 | J11: =Datasets!I196 -> 0.1307 | ... CX11: =Datasets!CW196 -> 0.1228
A12: ET00 | B12: Transportation | C12: =Datasets!B197 -> 0.2387 | D12: =Datasets!C197 -> 0.2522 | E12: =Datasets!D197 -> 0.2527 | F12: =Datasets!E197 -> 0.2596 | G12: =Datasets!F197 -> 0.2659 | H12: =Datasets!G197 -> 0.2693 | I12: =Datasets!H197 -> 0.269 | J12: =Datasets!I197 -> 0.2621 | ... CX12: =Datasets!CW197 -> 0.1863
A13: EO00 | B13: Other equipment | C13: =Datasets!B198 -> 0.1197 | D13: =Datasets!C198 -> 0.1207 | E13: =Datasets!D198 -> 0.1206 | F13: =Datasets!E198 -> 0.1201 | G13: =Datasets!F198 -> 0.119 | H13: =Datasets!G198 -> 0.1201 | I13: =Datasets!H198 -> 0.1214 | J13: =Datasets!I198 -> 0.122 | ... CX13: =Datasets!CW198 -> 0.1437
A14: ST00 | B14: Structures | C14: =Datasets!B199 -> 0.0312 | D14: =Datasets!C199 -> 0.0311 | E14: =Datasets!D199 -> 0.0311 | F14: =Datasets!E199 -> 0.0311 | G14: =Datasets!F199 -> 0.0312 | H14: =Datasets!G199 -> 0.0312 | I14: =Datasets!H199 -> 0.0312 | J14: =Datasets!I199 -> 0.0312 | ... CX14: =Datasets!CW199 -> 0.0308
A15: SCHC | B15: Commercial and healthcare | C15: =Datasets!B200 -> 0.0247 | D15: =Datasets!C200 -> 0.0247 | E15: =Datasets!D200 -> 0.0247 | F15: =Datasets!E200 -> 0.0247 | G15: =Datasets!F200 -> 0.0247 | H15: =Datasets!G200 -> 0.0247 | I15: =Datasets!H200 -> 0.0247 | J15: =Datasets!I200 -> 0.0247 | ... CX15: =Datasets!CW200 -> 0.0241
A16: IP00 | B16: Intellectual property products | C16: =Datasets!B201 -> 0.16 | D16: =Datasets!C201 -> 0.16 | E16: =Datasets!D201 -> 0.16 | F16: =Datasets!E201 -> 0.16 | G16: =Datasets!F201 -> 0.16 | H16: =Datasets!G201 -> 0.16 | I16: =Datasets!H201 -> 0.16 | J16: =Datasets!I201 -> 0.16 | ... CX16: =Datasets!CW201 -> 0.2058

Sheet 3390
A1: 3390 - Other Manufacturing
A2: Implied Depreciation Rates for Private Nonresidential Fixed Assets
A3: Updated September 26, 2025
A5: Asset Codes | B5: NIPA Asset Types | C5: 1925 | D5: 1926 | E5: 1927 | F5: 1928 | G5: 1929 | H5: 1930 | I5: 1931 | J5: 1932 | K5: 1933 | L5: 1934 | M5: 1935 | N5: 1936 | O5: 1937 | P5: 1938 | Q5: 1939 | R5: 1940 | S5: 1941 | T5: 1942 | U5: 1943 | V5: 1944 | W5: 1945 | X5: 1946 | Y5: 1947 | Z5: 1948 | AA5: 1949 | AB5: 1950 | AC5: 1951 | AD5: 1952 | AE5: 1953 | AF5: 1954 | AG5: 1955 | AH5: 1956 | AI5: 1957 | AJ5: 1958 | AK5: 1959 | AL5: 1960 | AM5: 1961 | AN5: 1962 | AO5: 1963 | AP5: 1964 | AQ5: 1965 | AR5: 1966 | AS5: 1967 | AT5: 1968 | AU5: 1969 | AV5: 1970 | AW5: 1971 | AX5: 1972 | AY5: 1973 | AZ5: 1974 | BA5: 1975 | BB5: 1976 | BC5: 1977 | BD5: 1978 | BE5: 1979 | BF5: 1980 | BG5: 1981 | BH5: 1982 | BI5: 1983 | BJ5: 1984 | BK5: 1985 | BL5: 1986 | BM5: 1987 | BN5: 1988 | BO5: 1989 | BP5: 1990 | BQ5: 1991 | BR5: 1992 | BS5: 1993 | BT5: 1994 | BU5: 1995 | BV5: 1996 | BW5: 1997 | BX5: 1998 | BY5: 1999 | BZ5: 2000 | CA5: 2001 | CB5: 2002 | CC5: 2003 | CD5: 2004 | CE5: 2005 | CF5: 2006 | CG5: 2007 | CH5: 2008 | CI5: 2009 | CJ5: 2010 | CK5: 2011 | CL5: 2012 | CM5: 2013 | CN5: 2014 | CO5: 2015 | CP5: 2016 | CQ5: 2017 | CR5: 2018 | CS5: 2019 | CT5: 2020 | CU5: 2021 | CV5: 2022 | CW5: 2023 | CX5: 2024
A7: ES00 | B7: Equipment, structures, and intellectual property products | C7: =Datasets!B202 -> 0.0438 | D7: =Datasets!C202 -> 0.0461 | E7: =Datasets!D202 -> 0.0469 | F7: =Datasets!E202 -> 0.0473 | G7: =Datasets!F202 -> 0.0478 | H7: =Datasets!G202 -> 0.0479 | I7: =Datasets!H202 -> 0.0478 | J7: =Datasets!I202 -> 0.0477 | ... CX7: =Datasets!CW202 -> 0.1126
A8: EQ00 | B8: Equipment | C8: =Datasets!B203 -> 0.108 | D8: =Datasets!C203 -> 0.1109 | E8: =Datasets!D203 -> 0.1111 | F8: =Datasets!E203 -> 0.1118 | G8: =Datasets!F203 -> 0.1122 | H8: =Datasets!G203 -> 0.1123 | I8: =Datasets!H203 -> 0.1122 | J8: =Datasets!I203 -> 0.1117 | ... CX8: =Datasets!CW203 -> 0.1174
A9: EP00 | B9: Information | C9: =Datasets!B204 -> 0.1381 | D9: =Datasets!C204 -> 0.1381 | E9: =Datasets!D204 -> 0.1378 | F9: =Datasets!E204 -> 0.1375 | G9: =Datasets!F204 -> 0.1372 | H9: =Datasets!G204 -> 0.1368 | I9: =Datasets!H204 -> 0.1364 | J9: =Datasets!I204 -> 0.1361 | ... CX9: =Datasets!CW204 -> 0.1876
A10: EP11 | B10: Computers | C10: =Datasets!B205 -> 0 | D10: =Datasets!C205 -> 0 | E10: =Datasets!D205 -> 0 | F10: =Datasets!E205 -> 0 | G10: =Datasets!F205 -> 0 | H10: =Datasets!G205 -> 0 | I10: =Datasets!H205 -> 0 | J10: =Datasets!I205 -> 0 | ... CX10: =Datasets!CW205 -> 0.3413
A11: EI00 | B11: Industrial | C11: =Datasets!B206 -> 0.103 | D11: =Datasets!C206 -> 0.1027 | E11: =Datasets!D206 -> 0.1026 | F11: =Datasets!E206 -> 0.1027 | G11: =Datasets!F206 -> 0.1029 | H11: =Datasets!G206 -> 0.1029 | I11: =Datasets!H206 -> 0.1027 | J11: =Datasets!I206 -> 0.1026 | ... CX11: =Datasets!CW206 -> 0.1029
A12: ET00 | B12: Transportation | C12: =Datasets!B207 -> 0.2387 | D12: =Datasets!C207 -> 0.2522 | E12: =Datasets!D207 -> 0.2527 | F12: =Datasets!E207 -> 0.2596 | G12: =Datasets!F207 -> 0.2659 | H12: =Datasets!G207 -> 0.2693 | I12: =Datasets!H207 -> 0.269 | J12: =Datasets!I207 -> 0.2621 | ... CX12: =Datasets!CW207 -> 0.1648
A13: EO00 | B13: Other equipment | C13: =Datasets!B208 -> 0.1676 | D13: =Datasets!C208 -> 0.1661 | E13: =Datasets!D208 -> 0.1645 | F13: =Datasets!E208 -> 0.1637 | G13: =Datasets!F208 -> 0.1215 | H13: =Datasets!G208 -> 0.1191 | I13: =Datasets!H208 -> 0.1189 | J13: =Datasets!I208 -> 0.1189 | ... CX13: =Datasets!CW208 -> 0.1454
A14: ST00 | B14: Structures | C14: =Datasets!B209 -> 0.0314 | D14: =Datasets!C209 -> 0.0314 | E14: =Datasets!D209 -> 0.0314 | F14: =Datasets!E209 -> 0.0314 | G14: =Datasets!F209 -> 0.0314 | H14: =Datasets!G209 -> 0.0314 | I14: =Datasets!H209 -> 0.0314 | J14: =Datasets!I209 -> 0.0314 | ... CX14: =Datasets!CW209 -> 0.0307
A15: SCHC | B15: Commercial and healthcare | C15: =Datasets!B210 -> 0.0248 | D15: =Datasets!C210 -> 0.0248 | E15: =Datasets!D210 -> 0.0248 | F15: =Datasets!E210 -> 0.0248 | G15: =Datasets!F210 -> 0.0248 | H15: =Datasets!G210 -> 0.0248 | I15: =Datasets!H210 -> 0.0248 | J15: =Datasets!I210 -> 0.0248 | ... CX15: =Datasets!CW210 -> 0.0249
A16: IP00 | B16: Intellectual property products | C16: =Datasets!B211 -> 0.16 | D16: =Datasets!C211 -> 0.16 | E16: =Datasets!D211 -> 0.16 | F16: =Datasets!E211 -> 0.16 | G16: =Datasets!F211 -> 0.16 | H16: =Datasets!G211 -> 0.16 | I16: =Datasets!H211 -> 0.16 | J16: =Datasets!I211 -> 0.16 | ... CX16: =Datasets!CW211 -> 0.1766

Sheet 3110
A1: 3110 - Food Manufacturing
A2: Implied Depreciation Rates for Private Nonresidential Fixed Assets
A3: Updated September 26, 2025
A5: Asset Codes | B5: NIPA Asset Types | C5: 1925 | D5: 1926 | E5: 1927 | F5: 1928 | G5: 1929 | H5: 1930 | I5: 1931 | J5: 1932 | K5: 1933 | L5: 1934 | M5: 1935 | N5: 1936 | O5: 1937 | P5: 1938 | Q5: 1939 | R5: 1940 | S5: 1941 | T5: 1942 | U5: 1943 | V5: 1944 | W5: 1945 | X5: 1946 | Y5: 1947 | Z5: 1948 | AA5: 1949 | AB5: 1950 | AC5: 1951 | AD5: 1952 | AE5: 1953 | AF5: 1954 | AG5: 1955 | AH5: 1956 | AI5: 1957 | AJ5: 1958 | AK5: 1959 | AL5: 1960 | AM5: 1961 | AN5: 1962 | AO5: 1963 | AP5: 1964 | AQ5: 1965 | AR5: 1966 | AS5: 1967 | AT5: 1968 | AU5: 1969 | AV5: 1970 | AW5: 1971 | AX5: 1972 | AY5: 1973 | AZ5: 1974 | BA5: 1975 | BB5: 1976 | BC5: 1977 | BD5: 1978 | BE5: 1979 | BF5: 1980 | BG5: 1981 | BH5: 1982 | BI5: 1983 | BJ5: 1984 | BK5: 1985 | BL5: 1986 | BM5: 1987 | BN5: 1988 | BO5: 1989 | BP5: 1990 | BQ5: 1991 | BR5: 1992 | BS5: 1993 | BT5: 1994 | BU5: 1995 | BV5: 1996 | BW5: 1997 | BX5: 1998 | BY5: 1999 | BZ5: 2000 | CA5: 2001 | CB5: 2002 | CC5: 2003 | CD5: 2004 | CE5: 2005 | CF5: 2006 | CG5: 2007 | CH5: 2008 | CI5: 2009 | CJ5: 2010 | CK5: 2011 | CL5: 2012 | CM5: 2013 | CN5: 2014 | CO5: 2015 | CP5: 2016 | CQ5: 2017 | CR5: 2018 | CS5: 2019 | CT5: 2020 | CU5: 2021 | CV5: 2022 | CW5: 2023 | CX5: 2024
A7: ES00 | B7: Equipment, structures, and intellectual property products | C7: =Datasets!B212 -> 0.0541 | D7: =Datasets!C212 -> 0.0532 | E7: =Datasets!D212 -> 0.0522 | F7: =Datasets!E212 -> 0.0513 | G7: =Datasets!F212 -> 0.0503 | H7: =Datasets!G212 -> 0.0497 | I7: =Datasets!H212 -> 0.0492 | J7: =Datasets!I212 -> 0.0488 | ... CX7: =Datasets!CW212 -> 0.0821
A8: EQ00 | B8: Equipment | C8: =Datasets!B213 -> 0.0839 | D8: =Datasets!C213 -> 0.0843 | E8: =Datasets!D213 -> 0.0844 | F8: =Datasets!E213 -> 0.0845 | G8: =Datasets!F213 -> 0.0847 | H8: =Datasets!G213 -> 0.0848 | I8: =Datasets!H213 -> 0.0849 | J8: =Datasets!I213 -> 0.0848 | ... CX8: =Datasets!CW213 -> 0.096
A9: EP00 | B9: Information | C9: =Datasets!B214 -> 0.135 | D9: =Datasets!C214 -> 0.135 | E9: =Datasets!D214 -> 0.135 | F9: =Datasets!E214 -> 0.135 | G9: =Datasets!F214 -> 0.135 | H9: =Datasets!G214 -> 0.135 | I9: =Datasets!H214 -> 0.135 | J9: =Datasets!I214 -> 0.135 | ... CX9: =Datasets!CW214 -> 0.195
A10: EP11 | B10: Computers | C10: =Datasets!B215 -> 0 | D10: =Datasets!C215 -> 0 | E10: =Datasets!D215 -> 0 | F10: =Datasets!E215 -> 0 | G10: =Datasets!F215 -> 0 | H10: =Datasets!G215 -> 0 | I10: =Datasets!H215 -> 0 | J10: =Datasets!I215 -> 0 | ... CX10: =Datasets!CW215 -> 0.338
A11: EI00 | B11: Industrial | C11: =Datasets!B216 -> 0.0825 | D11: =Datasets!C216 -> 0.0826 | E11: =Datasets!D216 -> 0.0825 | F11: =Datasets!E216 -> 0.0825 | G11: =Datasets!F216 -> 0.0825 | H11: =Datasets!G216 -> 0.0825 | I11: =Datasets!H216 -> 0.0825 | J11: =Datasets!I216 -> 0.0824 | ... CX11: =Datasets!CW216 -> 0.0852
A12: ET00 | B12: Transportation | C12: =Datasets!B217 -> 0.2387 | D12: =Datasets!C217 -> 0.2522 | E12: =Datasets!D217 -> 0.2527 | F12: =Datasets!E217 -> 0.2596 | G12: =Datasets!F217 -> 0.2659 | H12: =Datasets!G217 -> 0.2693 | I12: =Datasets!H217 -> 0.269 | J12: =Datasets!I217 -> 0.2621 | ... CX12: =Datasets!CW217 -> 0.1698
A13: EO00 | B13: Other equipment | C13: =Datasets!B218 -> 0.1451 | D13: =Datasets!C218 -> 0.1458 | E13: =Datasets!D218 -> 0.1462 | F13: =Datasets!E218 -> 0.1465 | G13: =Datasets!F218 -> 0.1444 | H13: =Datasets!G218 -> 0.1417 | I13: =Datasets!H218 -> 0.141 | J13: =Datasets!I218 -> 0.1406 | ... CX13: =Datasets!CW218 -> 0.1452
A14: ST00 | B14: Structures | C14: =Datasets!B219 -> 0.0312 | D14: =Datasets!C219 -> 0.0312 | E14: =Datasets!D219 -> 0.0312 | F14: =Datasets!E219 -> 0.0312 | G14: =Datasets!F219 -> 0.0312 | H14: =Datasets!G219 -> 0.0311 | I14: =Datasets!H219 -> 0.0311 | J14: =Datasets!I219 -> 0.0311 | ... CX14: =Datasets!CW219 -> 0.0311
A15: SCHC | B15: Commercial and healthcare | C15: =Datasets!B220 -> 0.0247 | D15: =Datasets!C220 -> 0.0247 | E15: =Datasets!D220 -> 0.0247 | F15: =Datasets!E220 -> 0.0247 | G15: =Datasets!F220 -> 0.0247 | H15: =Datasets!G220 -> 0.0247 | I15: =Datasets!H220 -> 0.0247 | J15: =Datasets!I220 -> 0.0247 | ... CX15: =Datasets!CW220 -> 0.0241
A16: IP00 | B16: Intellectual property products | C16: =Datasets!B221 -> 0.16 | D16: =Datasets!C221 -> 0.16 | E16: =Datasets!D221 -> 0.16 | F16: =Datasets!E221 -> 0.16 | G16: =Datasets!F221 -> 0.16 | H16: =Datasets!G221 -> 0.16 | I16: =Datasets!H221 -> 0.16 | J16: =Datasets!I221 -> 0.16 | ... CX16: =Datasets!CW221 -> 0.2136

Sheet 3120
A1: 3120 - Beverage and Tobacco Product Manufacturing
A2: Implied Depreciation Rates for Private Nonresidential Fixed Assets
A3: Updated September 26, 2025
A5: Asset Codes | B5: NIPA Asset Types | C5: 1925 | D5: 1926 | E5: 1927 | F5: 1928 | G5: 1929 | H5: 1930 | I5: 1931 | J5: 1932 | K5: 1933 | L5: 1934 | M5: 1935 | N5: 1936 | O5: 1937 | P5: 1938 | Q5: 1939 | R5: 1940 | S5: 1941 | T5: 1942 | U5: 1943 | V5: 1944 | W5: 1945 | X5: 1946 | Y5: 1947 | Z5: 1948 | AA5: 1949 | AB5: 1950 | AC5: 1951 | AD5: 1952 | AE5: 1953 | AF5: 1954 | AG5: 1955 | AH5: 1956 | AI5: 1957 | AJ5: 1958 | AK5: 1959 | AL5: 1960 | AM5: 1961 | AN5: 1962 | AO5: 1963 | AP5: 1964 | AQ5: 1965 | AR5: 1966 | AS5: 1967 | AT5: 1968 | AU5: 1969 | AV5: 1970 | AW5: 1971 | AX5: 1972 | AY5: 1973 | AZ5: 1974 | BA5: 1975 | BB5: 1976 | BC5: 1977 | BD5: 1978 | BE5: 1979 | BF5: 1980 | BG5: 1981 | BH5: 1982 | BI5: 1983 | BJ5: 1984 | BK5: 1985 | BL5: 1986 | BM5: 1987 | BN5: 1988 | BO5: 1989 | BP5: 1990 | BQ5: 1991 | BR5: 1992 | BS5: 1993 | BT5: 1994 | BU5: 1995 | BV5: 1996 | BW5: 1997 | BX5: 1998 | BY5: 1999 | BZ5: 2000 | CA5: 2001 | CB5: 2002 | CC5: 2003 | CD5: 2004 | CE5: 2005 | CF5: 2006 | CG5: 2007 | CH5: 2008 | CI5: 2009 | CJ5: 2010 | CK5: 2011 | CL5: 2012 | CM5: 2013 | CN5: 2014 | CO5: 2015 | CP5: 2016 | CQ5: 2017 | CR5: 2018 | CS5: 2019 | CT5: 2020 | CU5: 2021 | CV5: 2022 | CW5: 2023 | CX5: 2024
A7: ES00 | B7: Equipment, structures, and intellectual property products | C7: =Datasets!B222 -> 0.05 | D7: =Datasets!C222 -> 0.0495 | E7: =Datasets!D222 -> 0.0487 | F7: =Datasets!E222 -> 0.048 | G7: =Datasets!F222 -> 0.0473 | H7: =Datasets!G222 -> 0.0469 | I7: =Datasets!H222 -> 0.0467 | J7: =Datasets!I222 -> 0.0464 | ... CX7: =Datasets!CW222 -> 0.0935
A8: EQ00 | B8: Equipment | C8: =Datasets!B223 -> 0.0814 | D8: =Datasets!C223 -> 0.0823 | E8: =Datasets!D223 -> 0.0825 | F8: =Datasets!E223 -> 0.0828 | G8: =Datasets!F223 -> 0.0832 | H8: =Datasets!G223 -> 0.0836 | I8: =Datasets!H223 -> 0.0839 | J8: =Datasets!I223 -> 0.0838 | ... CX8: =Datasets!CW223 -> 0.1082
A9: EP00 | B9: Information | C9: =Datasets!B224 -> 0.135 | D9: =Datasets!C224 -> 0.135 | E9: =Datasets!D224 -> 0.135 | F9: =Datasets!E224 -> 0.135 | G9: =Datasets!F224 -> 0.135 | H9: =Datasets!G224 -> 0.135 | I9: =Datasets!H224 -> 0.135 | J9: =Datasets!I224 -> 0.135 | ... CX9: =Datasets!CW224 -> 0.1661
A10: EP11 | B10: Computers | C10: =Datasets!B225 -> 0 | D10: =Datasets!C225 -> 0 | E10: =Datasets!D225 -> 0 | F10: =Datasets!E225 -> 0 | G10: =Datasets!F225 -> 0 | H10: =Datasets!G225 -> 0 | I10: =Datasets!H225 -> 0 | J10: =Datasets!I225 -> 0 | ... CX10: =Datasets!CW225 -> 0.3401
A11: EI00 | B11: Industrial | C11: =Datasets!B226 -> 0.0787 | D11: =Datasets!C226 -> 0.0787 | E11: =Datasets!D226 -> 0.0788 | F11: =Datasets!E226 -> 0.0788 | G11: =Datasets!F226 -> 0.0788 | H11: =Datasets!G226 -> 0.0789 | I11: =Datasets!H226 -> 0.0789 | J11: =Datasets!I226 -> 0.0789 | ... CX11: =Datasets!CW226 -> 0.0831
A12: ET00 | B12: Transportation | C12: =Datasets!B227 -> 0.2387 | D12: =Datasets!C227 -> 0.2522 | E12: =Datasets!D227 -> 0.2527 | F12: =Datasets!E227 -> 0.2596 | G12: =Datasets!F227 -> 0.2659 | H12: =Datasets!G227 -> 0.2693 | I12: =Datasets!H227 -> 0.269 | J12: =Datasets!I227 -> 0.2621 | ... CX12: =Datasets!CW227 -> 0.1896
A13: EO00 | B13: Other equipment | C13: =Datasets!B228 -> 0.1404 | D13: =Datasets!C228 -> 0.1423 | E13: =Datasets!D228 -> 0.1435 | F13: =Datasets!E228 -> 0.1443 | G13: =Datasets!F228 -> 0.1314 | H13: =Datasets!G228 -> 0.1336 | I13: =Datasets!H228 -> 0.1368 | J13: =Datasets!I228 -> 0.1384 | ... CX13: =Datasets!CW228 -> 0.1479
A14: ST00 | B14: Structures | C14: =Datasets!B229 -> 0.031 | D14: =Datasets!C229 -> 0.031 | E14: =Datasets!D229 -> 0.031 | F14: =Datasets!E229 -> 0.031 | G14: =Datasets!F229 -> 0.0309 | H14: =Datasets!G229 -> 0.0309 | I14: =Datasets!H229 -> 0.0309 | J14: =Datasets!I229 -> 0.0309 | ... CX14: =Datasets!CW229 -> 0.0303
A15: SCHC | B15: Commercial and healthcare | C15: =Datasets!B230 -> 0.0247 | D15: =Datasets!C230 -> 0.0247 | E15: =Datasets!D230 -> 0.0247 | F15: =Datasets!E230 -> 0.0247 | G15: =Datasets!F230 -> 0.0247 | H15: =Datasets!G230 -> 0.0247 | I15: =Datasets!H230 -> 0.0247 | J15: =Datasets!I230 -> 0.0247 | ... CX15: =Datasets!CW230 -> 0.0241
A16: IP00 | B16: Intellectual property products | C16: =Datasets!B231 -> 0.16 | D16: =Datasets!C231 -> 0.16 | E16: =Datasets!D231 -> 0.16 | F16: =Datasets!E231 -> 0.16 | G16: =Datasets!F231 -> 0.16 | H16: =Datasets!G231 -> 0.16 | I16: =Datasets!H231 -> 0.16 | J16: =Datasets!I231 -> 0.16 | ... CX16: =Datasets!CW231 -> 0.2183

Sheet 313T
A1: 313T - Textile Mills and Textile Product Mills
A2: Implied Depreciation Rates for Private Nonresidential Fixed Assets
A3: Updated September 26, 2025
A5: Asset Codes | B5: NIPA Asset Types | C5: 1925 | D5: 1926 | E5: 1927 | F5: 1928 | G5: 1929 | H5: 1930 | I5: 1931 | J5: 1932 | K5: 1933 | L5: 1934 | M5: 1935 | N5: 1936 | O5: 1937 | P5: 1938 | Q5: 1939 | R5: 1940 | S5: 1941 | T5: 1942 | U5: 1943 | V5: 1944 | W5: 1945 | X5: 1946 | Y5: 1947 | Z5: 1948 | AA5: 1949 | AB5: 1950 | AC5: 1951 | AD5: 1952 | AE5: 1953 | AF5: 1954 | AG5: 1955 | AH5: 1956 | AI5: 1957 | AJ5: 1958 | AK5: 1959 | AL5: 1960 | AM5: 1961 | AN5: 1962 | AO5: 1963 | AP5: 1964 | AQ5: 1965 | AR5: 1966 | AS5: 1967 | AT5: 1968 | AU5: 1969 | AV5: 1970 | AW5: 1971 | AX5: 1972 | AY5: 1973 | AZ5: 1974 | BA5: 1975 | BB5: 1976 | BC5: 1977 | BD5: 1978 | BE5: 1979 | BF5: 1980 | BG5: 1981 | BH5: 1982 | BI5: 1983 | BJ5: 1984 | BK5: 1985 | BL5: 1986 | BM5: 1987 | BN5: 1988 | BO5: 1989 | BP5: 1990 | BQ5: 1991 | BR5: 1992 | BS5: 1993 | BT5: 1994 | BU5: 1995 | BV5: 1996 | BW5: 1997 | BX5: 1998 | BY5: 1999 | BZ5: 2000 | CA5: 2001 | CB5: 2002 | CC5: 2003 | CD5: 2004 | CE5: 2005 | CF5: 2006 | CG5: 2007 | CH5: 2008 | CI5: 2009 | CJ5: 2010 | CK5: 2011 | CL5: 2012 | CM5: 2013 | CN5: 2014 | CO5: 2015 | CP5: 2016 | CQ5: 2017 | CR5: 2018 | CS5: 2019 | CT5: 2020 | CU5: 2021 | CV5: 2022 | CW5: 2023 | CX5: 2024
A7: ES00 | B7: Equipment, structures, and intellectual property products | C7: =Datasets!B232 -> 0.0447 | D7: =Datasets!C232 -> 0.0459 | E7: =Datasets!D232 -> 0.0465 | F7: =Datasets!E232 -> 0.047 | G7: =Datasets!F232 -> 0.0475 | H7: =Datasets!G232 -> 0.0478 | I7: =Datasets!H232 -> 0.0477 | J7: =Datasets!I232 -> 0.0474 | ... CX7: =Datasets!CW232 -> 0.0799
A8: EQ00 | B8: Equipment | C8: =Datasets!B233 -> 0.1045 | D8: =Datasets!C233 -> 0.105 | E8: =Datasets!D233 -> 0.105 | F8: =Datasets!E233 -> 0.1051 | G8: =Datasets!F233 -> 0.1052 | H8: =Datasets!G233 -> 0.1053 | I8: =Datasets!H233 -> 0.1053 | J8: =Datasets!I233 -> 0.1052 | ... CX8: =Datasets!CW233 -> 0.1104
A9: EP00 | B9: Information | C9: =Datasets!B234 -> 0 | D9: =Datasets!C234 -> 0 | E9: =Datasets!D234 -> 0 | F9: =Datasets!E234 -> 0 | G9: =Datasets!F234 -> 0 | H9: =Datasets!G234 -> 0 | I9: =Datasets!H234 -> 0 | J9: =Datasets!I234 -> 0 | ... CX9: =Datasets!CW234 -> 0.2044
A10: EP11 | B10: Computers | C10: =Datasets!B235 -> 0 | D10: =Datasets!C235 -> 0 | E10: =Datasets!D235 -> 0 | F10: =Datasets!E235 -> 0 | G10: =Datasets!F235 -> 0 | H10: =Datasets!G235 -> 0 | I10: =Datasets!H235 -> 0 | J10: =Datasets!I235 -> 0 | ... CX10: =Datasets!CW235 -> 0.3359
A11: EI00 | B11: Industrial | C11: =Datasets!B236 -> 0.1032 | D11: =Datasets!C236 -> 0.1033 | E11: =Datasets!D236 -> 0.1033 | F11: =Datasets!E236 -> 0.1033 | G11: =Datasets!F236 -> 0.1033 | H11: =Datasets!G236 -> 0.1033 | I11: =Datasets!H236 -> 0.1033 | J11: =Datasets!I236 -> 0.1033 | ... CX11: =Datasets!CW236 -> 0.1024
A12: ET00 | B12: Transportation | C12: =Datasets!B237 -> 0.2387 | D12: =Datasets!C237 -> 0.2522 | E12: =Datasets!D237 -> 0.2527 | F12: =Datasets!E237 -> 0.2596 | G12: =Datasets!F237 -> 0.2659 | H12: =Datasets!G237 -> 0.2693 | I12: =Datasets!H237 -> 0.269 | J12: =Datasets!I237 -> 0.2621 | ... CX12: =Datasets!CW237 -> 0.1922
A13: EO00 | B13: Other equipment | C13: =Datasets!B238 -> 0.1179 | D13: =Datasets!C238 -> 0.1179 | E13: =Datasets!D238 -> 0.1179 | F13: =Datasets!E238 -> 0.1179 | G13: =Datasets!F238 -> 0.1179 | H13: =Datasets!G238 -> 0.1179 | I13: =Datasets!H238 -> 0.1179 | J13: =Datasets!I238 -> 0.1179 | ... CX13: =Datasets!CW238 -> 0.1441
A14: ST00 | B14: Structures | C14: =Datasets!B239 -> 0.031 | D14: =Datasets!C239 -> 0.031 | E14: =Datasets!D239 -> 0.031 | F14: =Datasets!E239 -> 0.031 | G14: =Datasets!F239 -> 0.0309 | H14: =Datasets!G239 -> 0.0309 | I14: =Datasets!H239 -> 0.0309 | J14: =Datasets!I239 -> 0.0309 | ... CX14: =Datasets!CW239 -> 0.0306
A15: SCHC | B15: Commercial and healthcare | C15: =Datasets!B240 -> 0.0247 | D15: =Datasets!C240 -> 0.0247 | E15: =Datasets!D240 -> 0.0247 | F15: =Datasets!E240 -> 0.0247 | G15: =Datasets!F240 -> 0.0247 | H15: =Datasets!G240 -> 0.0247 | I15: =Datasets!H240 -> 0.0247 | J15: =Datasets!I240 -> 0.0247 | ... CX15: =Datasets!CW240 -> 0.0247
A16: IP00 | B16: Intellectual property products | C16: =Datasets!B241 -> 0.16 | D16: =Datasets!C241 -> 0.16 | E16: =Datasets!D241 -> 0.16 | F16: =Datasets!E241 -> 0.16 | G16: =Datasets!F241 -> 0.16 | H16: =Datasets!G241 -> 0.16 | I16: =Datasets!H241 -> 0.16 | J16: =Datasets!I241 -> 0.16 | ... CX16: =Datasets!CW241 -> 0.2057

Sheet 315A
A1: 315A - Apparel and Leather and Allied Products
A2: Implied Depreciation Rates for Private Nonresidential Fixed Assets
A3: Updated September 26, 2025
A5: Asset Codes | B5: NIPA Asset Types | C5: 1925 | D5: 1926 | E5: 1927 | F5: 1928 | G5: 1929 | H5: 1930 | I5: 1931 | J5: 1932 | K5: 1933 | L5: 1934 | M5: 1935 | N5: 1936 | O5: 1937 | P5: 1938 | Q5: 1939 | R5: 1940 | S5: 1941 | T5: 1942 | U5: 1943 | V5: 1944 | W5: 1945 | X5: 1946 | Y5: 1947 | Z5: 1948 | AA5: 1949 | AB5: 1950 | AC5: 1951 | AD5: 1952 | AE5: 1953 | AF5: 1954 | AG5: 1955 | AH5: 1956 | AI5: 1957 | AJ5: 1958 | AK5: 1959 | AL5: 1960 | AM5: 1961 | AN5: 1962 | AO5: 1963 | AP5: 1964 | AQ5: 1965 | AR5: 1966 | AS5: 1967 | AT5: 1968 | AU5: 1969 | AV5: 1970 | AW5: 1971 | AX5: 1972 | AY5: 1973 | AZ5: 1974 | BA5: 1975 | BB5: 1976 | BC5: 1977 | BD5: 1978 | BE5: 1979 | BF5: 1980 | BG5: 1981 | BH5: 1982 | BI5: 1983 | BJ5: 1984 | BK5: 1985 | BL5: 1986 | BM5: 1987 | BN5: 1988 | BO5: 1989 | BP5: 1990 | BQ5: 1991 | BR5: 1992 | BS5: 1993 | BT5: 1994 | BU5: 1995 | BV5: 1996 | BW5: 1997 | BX5: 1998 | BY5: 1999 | BZ5: 2000 | CA5: 2001 | CB5: 2002 | CC5: 2003 | CD5: 2004 | CE5: 2005 | CF5: 2006 | CG5: 2007 | CH5: 2008 | CI5: 2009 | CJ5: 2010 | CK5: 2011 | CL5: 2012 | CM5: 2013 | CN5: 2014 | CO5: 2015 | CP5: 2016 | CQ5: 2017 | CR5: 2018 | CS5: 2019 | CT5: 2020 | CU5: 2021 | CV5: 2022 | CW5: 2023 | CX5: 2024
A7: ES00 | B7: Equipment, structures, and intellectual property products | C7: =Datasets!B242 -> 0.042 | D7: =Datasets!C242 -> 0.0436 | E7: =Datasets!D242 -> 0.0448 | F7: =Datasets!E242 -> 0.0459 | G7: =Datasets!F242 -> 0.0467 | H7: =Datasets!G242 -> 0.0468 | I7: =Datasets!H242 -> 0.0468 | J7: =Datasets!I242 -> 0.0465 | ... CX7: =Datasets!CW242 -> 0.0853
A8: EQ00 | B8: Equipment | C8: =Datasets!B243 -> 0.1161 | D8: =Datasets!C243 -> 0.1169 | E8: =Datasets!D243 -> 0.1161 | F8: =Datasets!E243 -> 0.1157 | G8: =Datasets!F243 -> 0.1156 | H8: =Datasets!G243 -> 0.1156 | I8: =Datasets!H243 -> 0.1155 | J8: =Datasets!I243 -> 0.1152 | ... CX8: =Datasets!CW243 -> 0.1188
A9: EP00 | B9: Information | C9: =Datasets!B244 -> 0 | D9: =Datasets!C244 -> 0 | E9: =Datasets!D244 -> 0 | F9: =Datasets!E244 -> 0 | G9: =Datasets!F244 -> 0 | H9: =Datasets!G244 -> 0 | I9: =Datasets!H244 -> 0 | J9: =Datasets!I244 -> 0 | ... CX9: =Datasets!CW244 -> 0.1648
A10: EP11 | B10: Computers | C10: =Datasets!B245 -> 0 | D10: =Datasets!C245 -> 0 | E10: =Datasets!D245 -> 0 | F10: =Datasets!E245 -> 0 | G10: =Datasets!F245 -> 0 | H10: =Datasets!G245 -> 0 | I10: =Datasets!H245 -> 0 | J10: =Datasets!I245 -> 0 | ... CX10: =Datasets!CW245 -> 0.3412
A11: EI00 | B11: Industrial | C11: =Datasets!B246 -> 0.1103 | D11: =Datasets!C246 -> 0.1103 | E11: =Datasets!D246 -> 0.1103 | F11: =Datasets!E246 -> 0.1103 | G11: =Datasets!F246 -> 0.1103 | H11: =Datasets!G246 -> 0.1104 | I11: =Datasets!H246 -> 0.1104 | J11: =Datasets!I246 -> 0.1104 | ... CX11: =Datasets!CW246 -> 0.0997
A12: ET00 | B12: Transportation | C12: =Datasets!B247 -> 0.2387 | D12: =Datasets!C247 -> 0.2522 | E12: =Datasets!D247 -> 0.2527 | F12: =Datasets!E247 -> 0.2596 | G12: =Datasets!F247 -> 0.2659 | H12: =Datasets!G247 -> 0.2693 | I12: =Datasets!H247 -> 0.269 | J12: =Datasets!I247 -> 0.2621 | ... CX12: =Datasets!CW247 -> 0.1393
A13: EO00 | B13: Other equipment | C13: =Datasets!B248 -> 0.155 | D13: =Datasets!C248 -> 0.155 | E13: =Datasets!D248 -> 0.155 | F13: =Datasets!E248 -> 0.155 | G13: =Datasets!F248 -> 0.1179 | H13: =Datasets!G248 -> 0.1179 | I13: =Datasets!H248 -> 0.1179 | J13: =Datasets!I248 -> 0.1179 | ... CX13: =Datasets!CW248 -> 0.136
A14: ST00 | B14: Structures | C14: =Datasets!B249 -> 0.0311 | D14: =Datasets!C249 -> 0.031 | E14: =Datasets!D249 -> 0.031 | F14: =Datasets!E249 -> 0.0309 | G14: =Datasets!F249 -> 0.0309 | H14: =Datasets!G249 -> 0.0308 | I14: =Datasets!H249 -> 0.0308 | J14: =Datasets!I249 -> 0.0308 | ... CX14: =Datasets!CW249 -> 0.0289
A15: SCHC | B15: Commercial and healthcare | C15: =Datasets!B250 -> 0.0247 | D15: =Datasets!C250 -> 0.0247 | E15: =Datasets!D250 -> 0.0247 | F15: =Datasets!E250 -> 0.0247 | G15: =Datasets!F250 -> 0.0247 | H15: =Datasets!G250 -> 0.0247 | I15: =Datasets!H250 -> 0.0247 | J15: =Datasets!I250 -> 0.0247 | ... CX15: =Datasets!CW250 -> 0.0246
A16: IP00 | B16: Intellectual property products | C16: =Datasets!B251 -> 0.16 | D16: =Datasets!C251 -> 0.16 | E16: =Datasets!D251 -> 0.16 | F16: =Datasets!E251 -> 0.16 | G16: =Datasets!F251 -> 0.16 | H16: =Datasets!G251 -> 0.16 | I16: =Datasets!H251 -> 0.16 | J16: =Datasets!I251 -> 0.16 | ... CX16: =Datasets!CW251 -> 0.186

Sheet 3220
A1: 3220 - Paper Products
A2: Implied Depreciation Rates for Private Nonresidential Fixed Assets
A3: Updated September 26, 2025
A5: Asset Codes | B5: NIPA Asset Types | C5: 1925 | D5: 1926 | E5: 1927 | F5: 1928 | G5: 1929 | H5: 1930 | I5: 1931 | J5: 1932 | K5: 1933 | L5: 1934 | M5: 1935 | N5: 1936 | O5: 1937 | P5: 1938 | Q5: 1939 | R5: 1940 | S5: 1941 | T5: 1942 | U5: 1943 | V5: 1944 | W5: 1945 | X5: 1946 | Y5: 1947 | Z5: 1948 | AA5: 1949 | AB5: 1950 | AC5: 1951 | AD5: 1952 | AE5: 1953 | AF5: 1954 | AG5: 1955 | AH5: 1956 | AI5: 1957 | AJ5: 1958 | AK5: 1959 | AL5: 1960 | AM5: 1961 | AN5: 1962 | AO5: 1963 | AP5: 1964 | AQ5: 1965 | AR5: 1966 | AS5: 1967 | AT5: 1968 | AU5: 1969 | AV5: 1970 | AW5: 1971 | AX5: 1972 | AY5: 1973 | AZ5: 1974 | BA5: 1975 | BB5: 1976 | BC5: 1977 | BD5: 1978 | BE5: 1979 | BF5: 1980 | BG5: 1981 | BH5: 1982 | BI5: 1983 | BJ5: 1984 | BK5: 1985 | BL5: 1986 | BM5: 1987 | BN5: 1988 | BO5: 1989 | BP5: 1990 | BQ5: 1991 | BR5: 1992 | BS5: 1993 | BT5: 1994 | BU5: 1995 | BV5: 1996 | BW5: 1997 | BX5: 1998 | BY5: 1999 | BZ5: 2000 | CA5: 2001 | CB5: 2002 | CC5: 2003 | CD5: 2004 | CE5: 2005 | CF5: 2006 | CG5: 2007 | CH5: 2008 | CI5: 2009 | CJ5: 2010 | CK5: 2011 | CL5: 2012 | CM5: 2013 | CN5: 2014 | CO5: 2015 | CP5: 2016 | CQ5: 2017 | CR5: 2018 | CS5: 2019 | CT5: 2020 | CU5: 2021 | CV5: 2022 | CW5: 2023 | CX5: 2024
A7: ES00 | B7: Equipment, structures, and intellectual property products | C7: =Datasets!B252 -> 0.0494 | D7: =Datasets!C252 -> 0.0511 | E7: =Datasets!D252 -> 0.0514 | F7: =Datasets!E252 -> 0.0517 | G7: =Datasets!F252 -> 0.052 | H7: =Datasets!G252 -> 0.0523 | I7: =Datasets!H252 -> 0.0525 | J7: =Datasets!I252 -> 0.0525 | ... CX7: =Datasets!CW252 -> 0.0928
A8: EQ00 | B8: Equipment | C8: =Datasets!B253 -> 0.1262 | D8: =Datasets!C253 -> 0.1262 | E8: =Datasets!D253 -> 0.1222 | F8: =Datasets!E253 -> 0.1197 | G8: =Datasets!F253 -> 0.1173 | H8: =Datasets!G253 -> 0.1146 | I8: =Datasets!H253 -> 0.1124 | J8: =Datasets!I253 -> 0.1108 | ... CX8: =Datasets!CW253 -> 0.1078
A9: EP00 | B9: Information | C9: =Datasets!B254 -> 0 | D9: =Datasets!C254 -> 0 | E9: =Datasets!D254 -> 0 | F9: =Datasets!E254 -> 0 | G9: =Datasets!F254 -> 0 | H9: =Datasets!G254 -> 0 | I9: =Datasets!H254 -> 0 | J9: =Datasets!I254 -> 0 | ... CX9: =Datasets!CW254 -> 0.2196
A10: EP11 | B10: Computers | C10: =Datasets!B255 -> 0 | D10: =Datasets!C255 -> 0 | E10: =Datasets!D255 -> 0 | F10: =Datasets!E255 -> 0 | G10: =Datasets!F255 -> 0 | H10: =Datasets!G255 -> 0 | I10: =Datasets!H255 -> 0 | J10: =Datasets!I255 -> 0 | ... CX10: =Datasets!CW255 -> 0.339
A11: EI00 | B11: Industrial | C11: =Datasets!B256 -> 0.1016 | D11: =Datasets!C256 -> 0.1016 | E11: =Datasets!D256 -> 0.1015 | F11: =Datasets!E256 -> 0.1012 | G11: =Datasets!F256 -> 0.1007 | H11: =Datasets!G256 -> 0.1 | I11: =Datasets!H256 -> 0.0995 | J11: =Datasets!I256 -> 0.0994 | ... CX11: =Datasets!CW256 -> 0.1037
A12: ET00 | B12: Transportation | C12: =Datasets!B257 -> 0.2387 | D12: =Datasets!C257 -> 0.2522 | E12: =Datasets!D257 -> 0.2527 | F12: =Datasets!E257 -> 0.2596 | G12: =Datasets!F257 -> 0.2659 | H12: =Datasets!G257 -> 0.2693 | I12: =Datasets!H257 -> 0.269 | J12: =Datasets!I257 -> 0.2621 | ... CX12: =Datasets!CW257 -> 0.1679
A13: EO00 | B13: Other equipment | C13: =Datasets!B258 -> 0 | D13: =Datasets!C258 -> 0 | E13: =Datasets!D258 -> 0 | F13: =Datasets!E258 -> 0 | G13: =Datasets!F258 -> 0 | H13: =Datasets!G258 -> 0 | I13: =Datasets!H258 -> 0 | J13: =Datasets!I258 -> 0 | ... CX13: =Datasets!CW258 -> 0.1433
A14: ST00 | B14: Structures | C14: =Datasets!B259 -> 0.0313 | D14: =Datasets!C259 -> 0.0313 | E14: =Datasets!D259 -> 0.0313 | F14: =Datasets!E259 -> 0.0313 | G14: =Datasets!F259 -> 0.0313 | H14: =Datasets!G259 -> 0.0313 | I14: =Datasets!H259 -> 0.0313 | J14: =Datasets!I259 -> 0.0313 | ... CX14: =Datasets!CW259 -> 0.0311
A15: SCHC | B15: Commercial and healthcare | C15: =Datasets!B260 -> 0.0247 | D15: =Datasets!C260 -> 0.0247 | E15: =Datasets!D260 -> 0.0247 | F15: =Datasets!E260 -> 0.0247 | G15: =Datasets!F260 -> 0.0247 | H15: =Datasets!G260 -> 0.0247 | I15: =Datasets!H260 -> 0.0247 | J15: =Datasets!I260 -> 0.0247 | ... CX15: =Datasets!CW260 -> 0.0248
A16: IP00 | B16: Intellectual property products | C16: =Datasets!B261 -> 0.16 | D16: =Datasets!C261 -> 0.16 | E16: =Datasets!D261 -> 0.16 | F16: =Datasets!E261 -> 0.16 | G16: =Datasets!F261 -> 0.16 | H16: =Datasets!G261 -> 0.16 | I16: =Datasets!H261 -> 0.16 | J16: =Datasets!I261 -> 0.16 | ... CX16: =Datasets!CW261 -> 0.2053

Sheet 3230
A1: 3230 - Printing and Related Support Activities
A2: Implied Depreciation Rates for Private Nonresidential Fixed Assets
A3: Updated September 26, 2025
A5: Asset Codes | B5: NIPA Asset Types | C5: 1925 | D5: 1926 | E5: 1927 | F5: 1928 | G5: 1929 | H5: 1930 | I5: 1931 | J5: 1932 | K5: 1933 | L5: 1934 | M5: 1935 | N5: 1936 | O5: 1937 | P5: 1938 | Q5: 1939 | R5: 1940 | S5: 1941 | T5: 1942 | U5: 1943 | V5: 1944 | W5: 1945 | X5: 1946 | Y5: 1947 | Z5: 1948 | AA5: 1949 | AB5: 1950 | AC5: 1951 | AD5: 1952 | AE5: 1953 | AF5: 1954 | AG5: 1955 | AH5: 1956 | AI5: 1957 | AJ5: 1958 | AK5: 1959 | AL5: 1960 | AM5: 1961 | AN5: 1962 | AO5: 1963 | AP5: 1964 | AQ5: 1965 | AR5: 1966 | AS5: 1967 | AT5: 1968 | AU5: 1969 | AV5: 1970 | AW5: 1971 | AX5: 1972 | AY5: 1973 | AZ5: 1974 | BA5: 1975 | BB5: 1976 | BC5: 1977 | BD5: 1978 | BE5: 1979 | BF5: 1980 | BG5: 1981 | BH5: 1982 | BI5: 1983 | BJ5: 1984 | BK5: 1985 | BL5: 1986 | BM5: 1987 | BN5: 1988 | BO5: 1989 | BP5: 1990 | BQ5: 1991 | BR5: 1992 | BS5: 1993 | BT5: 1994 | BU5: 1995 | BV5: 1996 | BW5: 1997 | BX5: 1998 | BY5: 1999 | BZ5: 2000 | CA5: 2001 | CB5: 2002 | CC5: 2003 | CD5: 2004 | CE5: 2005 | CF5: 2006 | CG5: 2007 | CH5: 2008 | CI5: 2009 | CJ5: 2010 | CK5: 2011 | CL5: 2012 | CM5: 2013 | CN5: 2014 | CO5: 2015 | CP5: 2016 | CQ5: 2017 | CR5: 2018 | CS5: 2019 | CT5: 2020 | CU5: 2021 | CV5: 2022 | CW5: 2023 | CX5: 2024
A7: ES00 | B7: Equipment, structures, and intellectual property products | C7: =Datasets!B262 -> 0.076 | D7: =Datasets!C262 -> 0.0806 | E7: =Datasets!D262 -> 0.0821 | F7: =Datasets!E262 -> 0.0829 | G7: =Datasets!F262 -> 0.0837 | H7: =Datasets!G262 -> 0.0841 | I7: =Datasets!H262 -> 0.0839 | J7: =Datasets!I262 -> 0.0833 | ... CX7: =Datasets!CW262 -> 0.1037
A8: EQ00 | B8: Equipment | C8: =Datasets!B263 -> 0.1154 | D8: =Datasets!C263 -> 0.118 | E8: =Datasets!D263 -> 0.1179 | F8: =Datasets!E263 -> 0.1182 | G8: =Datasets!F263 -> 0.1181 | H8: =Datasets!G263 -> 0.118 | I8: =Datasets!H263 -> 0.1177 | J8: =Datasets!I263 -> 0.1174 | ... CX8: =Datasets!CW263 -> 0.1263
A9: EP00 | B9: Information | C9: =Datasets!B264 -> 0.1443 | D9: =Datasets!C264 -> 0.1441 | E9: =Datasets!D264 -> 0.1436 | F9: =Datasets!E264 -> 0.143 | G9: =Datasets!F264 -> 0.1426 | H9: =Datasets!G264 -> 0.1416 | I9: =Datasets!H264 -> 0.1404 | J9: =Datasets!I264 -> 0.1398 | ... CX9: =Datasets!CW264 -> 0.2515
A10: EP11 | B10: Computers | C10: =Datasets!B265 -> 0 | D10: =Datasets!C265 -> 0 | E10: =Datasets!D265 -> 0 | F10: =Datasets!E265 -> 0 | G10: =Datasets!F265 -> 0 | H10: =Datasets!G265 -> 0 | I10: =Datasets!H265 -> 0 | J10: =Datasets!I265 -> 0 | ... CX10: =Datasets!CW265 -> 0.3383
A11: EI00 | B11: Industrial | C11: =Datasets!B266 -> 0.1102 | D11: =Datasets!C266 -> 0.1103 | E11: =Datasets!D266 -> 0.1103 | F11: =Datasets!E266 -> 0.1103 | G11: =Datasets!F266 -> 0.1103 | H11: =Datasets!G266 -> 0.1104 | I11: =Datasets!H266 -> 0.1104 | J11: =Datasets!I266 -> 0.1104 | ... CX11: =Datasets!CW266 -> 0.1114
A12: ET00 | B12: Transportation | C12: =Datasets!B267 -> 0.2387 | D12: =Datasets!C267 -> 0.2522 | E12: =Datasets!D267 -> 0.2527 | F12: =Datasets!E267 -> 0.2596 | G12: =Datasets!F267 -> 0.2659 | H12: =Datasets!G267 -> 0.2693 | I12: =Datasets!H267 -> 0.269 | J12: =Datasets!I267 -> 0.2621 | ... CX12: =Datasets!CW267 -> 0.1906
A13: EO00 | B13: Other equipment | C13: =Datasets!B268 -> 0.1788 | D13: =Datasets!C268 -> 0.1781 | E13: =Datasets!D268 -> 0.1775 | F13: =Datasets!E268 -> 0.1771 | G13: =Datasets!F268 -> 0.1192 | H13: =Datasets!G268 -> 0.1184 | I13: =Datasets!H268 -> 0.1183 | J13: =Datasets!I268 -> 0.1183 | ... CX13: =Datasets!CW268 -> 0.1494
A14: ST00 | B14: Structures | C14: =Datasets!B269 -> 0.0312 | D14: =Datasets!C269 -> 0.0312 | E14: =Datasets!D269 -> 0.0312 | F14: =Datasets!E269 -> 0.0312 | G14: =Datasets!F269 -> 0.0312 | H14: =Datasets!G269 -> 0.0312 | I14: =Datasets!H269 -> 0.0312 | J14: =Datasets!I269 -> 0.0312 | ... CX14: =Datasets!CW269 -> 0.031
A15: SCHC | B15: Commercial and healthcare | C15: =Datasets!B270 -> 0.0247 | D15: =Datasets!C270 -> 0.0247 | E15: =Datasets!D270 -> 0.0247 | F15: =Datasets!E270 -> 0.0247 | G15: =Datasets!F270 -> 0.0247 | H15: =Datasets!G270 -> 0.0247 | I15: =Datasets!H270 -> 0.0247 | J15: =Datasets!I270 -> 0.0247 | ... CX15: =Datasets!CW270 -> 0.0243
A16: IP00 | B16: Intellectual property products | C16: =Datasets!B271 -> 0.16 | D16: =Datasets!C271 -> 0.16 | E16: =Datasets!D271 -> 0.16 | F16: =Datasets!E271 -> 0.16 | G16: =Datasets!F271 -> 0.16 | H16: =Datasets!G271 -> 0.16 | I16: =Datasets!H271 -> 0.16 | J16: =Datasets!I271 -> 0.16 | ... CX16: =Datasets!CW271 -> 0.2445

Sheet 3240
A1: 3240 - Petroleum and Coal Products
A2: Implied Depreciation Rates for Private Nonresidential Fixed Assets
A3: Updated September 26, 2025
A5: Asset Codes | B5: NIPA Asset Types | C5: 1925 | D5: 1926 | E5: 1927 | F5: 1928 | G5: 1929 | H5: 1930 | I5: 1931 | J5: 1932 | K5: 1933 | L5: 1934 | M5: 1935 | N5: 1936 | O5: 1937 | P5: 1938 | Q5: 1939 | R5: 1940 | S5: 1941 | T5: 1942 | U5: 1943 | V5: 1944 | W5: 1945 | X5: 1946 | Y5: 1947 | Z5: 1948 | AA5: 1949 | AB5: 1950 | AC5: 1951 | AD5: 1952 | AE5: 1953 | AF5: 1954 | AG5: 1955 | AH5: 1956 | AI5: 1957 | AJ5: 1958 | AK5: 1959 | AL5: 1960 | AM5: 1961 | AN5: 1962 | AO5: 1963 | AP5: 1964 | AQ5: 1965 | AR5: 1966 | AS5: 1967 | AT5: 1968 | AU5: 1969 | AV5: 1970 | AW5: 1971 | AX5: 1972 | AY5: 1973 | AZ5: 1974 | BA5: 1975 | BB5: 1976 | BC5: 1977 | BD5: 1978 | BE5: 1979 | BF5: 1980 | BG5: 1981 | BH5: 1982 | BI5: 1983 | BJ5: 1984 | BK5: 1985 | BL5: 1986 | BM5: 1987 | BN5: 1988 | BO5: 1989 | BP5: 1990 | BQ5: 1991 | BR5: 1992 | BS5: 1993 | BT5: 1994 | BU5: 1995 | BV5: 1996 | BW5: 1997 | BX5: 1998 | BY5: 1999 | BZ5: 2000 | CA5: 2001 | CB5: 2002 | CC5: 2003 | CD5: 2004 | CE5: 2005 | CF5: 2006 | CG5: 2007 | CH5: 2008 | CI5: 2009 | CJ5: 2010 | CK5: 2011 | CL5: 2012 | CM5: 2013 | CN5: 2014 | CO5: 2015 | CP5: 2016 | CQ5: 2017 | CR5: 2018 | CS5: 2019 | CT5: 2020 | CU5: 2021 | CV5: 2022 | CW5: 2023 | CX5: 2024
A7: ES00 | B7: Equipment, structures, and intellectual property products | C7: =Datasets!B272 -> 0.0706 | D7: =Datasets!C272 -> 0.0727 | E7: =Datasets!D272 -> 0.0713 | F7: =Datasets!E272 -> 0.0683 | G7: =Datasets!F272 -> 0.0654 | H7: =Datasets!G272 -> 0.0625 | I7: =Datasets!H272 -> 0.0607 | J7: =Datasets!I272 -> 0.0602 | ... CX7: =Datasets!CW272 -> 0.0898
A8: EQ00 | B8: Equipment | C8: =Datasets!B273 -> 0.0781 | D8: =Datasets!C273 -> 0.0801 | E8: =Datasets!D273 -> 0.0803 | F8: =Datasets!E273 -> 0.0806 | G8: =Datasets!F273 -> 0.0808 | H8: =Datasets!G273 -> 0.0809 | I8: =Datasets!H273 -> 0.0809 | J8: =Datasets!I273 -> 0.0806 | ... CX8: =Datasets!CW273 -> 0.0926
A9: EP00 | B9: Information | C9: =Datasets!B274 -> 0.135 | D9: =Datasets!C274 -> 0.135 | E9: =Datasets!D274 -> 0.135 | F9: =Datasets!E274 -> 0.135 | G9: =Datasets!F274 -> 0.135 | H9: =Datasets!G274 -> 0.135 | I9: =Datasets!H274 -> 0.135 | J9: =Datasets!I274 -> 0.135 | ... CX9: =Datasets!CW274 -> 0.1484
A10: EP11 | B10: Computers | C10: =Datasets!B275 -> 0 | D10: =Datasets!C275 -> 0 | E10: =Datasets!D275 -> 0 | F10: =Datasets!E275 -> 0 | G10: =Datasets!F275 -> 0 | H10: =Datasets!G275 -> 0 | I10: =Datasets!H275 -> 0 | J10: =Datasets!I275 -> 0 | ... CX10: =Datasets!CW275 -> 0.3406
A11: EI00 | B11: Industrial | C11: =Datasets!B276 -> 0.0752 | D11: =Datasets!C276 -> 0.0752 | E11: =Datasets!D276 -> 0.0752 | F11: =Datasets!E276 -> 0.0751 | G11: =Datasets!F276 -> 0.075 | H11: =Datasets!G276 -> 0.075 | I11: =Datasets!H276 -> 0.075 | J11: =Datasets!I276 -> 0.075 | ... CX11: =Datasets!CW276 -> 0.0771
A12: ET00 | B12: Transportation | C12: =Datasets!B277 -> 0.2387 | D12: =Datasets!C277 -> 0.2522 | E12: =Datasets!D277 -> 0.2527 | F12: =Datasets!E277 -> 0.2596 | G12: =Datasets!F277 -> 0.2659 | H12: =Datasets!G277 -> 0.2693 | I12: =Datasets!H277 -> 0.269 | J12: =Datasets!I277 -> 0.2621 | ... CX12: =Datasets!CW277 -> 0.1772
A13: EO00 | B13: Other equipment | C13: =Datasets!B278 -> 0.125 | D13: =Datasets!C278 -> 0.1273 | E13: =Datasets!D278 -> 0.1286 | F13: =Datasets!E278 -> 0.1287 | G13: =Datasets!F278 -> 0.1183 | H13: =Datasets!G278 -> 0.1181 | I13: =Datasets!H278 -> 0.1181 | J13: =Datasets!I278 -> 0.1181 | ... CX13: =Datasets!CW278 -> 0.1495
A14: ST00 | B14: Structures | C14: =Datasets!B279 -> 0.028 | D14: =Datasets!C279 -> 0.028 | E14: =Datasets!D279 -> 0.0286 | F14: =Datasets!E279 -> 0.0292 | G14: =Datasets!F279 -> 0.0296 | H14: =Datasets!G279 -> 0.0299 | I14: =Datasets!H279 -> 0.03 | J14: =Datasets!I279 -> 0.0301 | ... CX14: =Datasets!CW279 -> 0.0307
A15: SCHC | B15: Commercial and healthcare | C15: =Datasets!B280 -> 0.0247 | D15: =Datasets!C280 -> 0.0247 | E15: =Datasets!D280 -> 0.0247 | F15: =Datasets!E280 -> 0.0247 | G15: =Datasets!F280 -> 0.0247 | H15: =Datasets!G280 -> 0.0247 | I15: =Datasets!H280 -> 0.0247 | J15: =Datasets!I280 -> 0.0247 | ... CX15: =Datasets!CW280 -> 0.0248
A16: IP00 | B16: Intellectual property products | C16: =Datasets!B281 -> 0.16 | D16: =Datasets!C281 -> 0.16 | E16: =Datasets!D281 -> 0.16 | F16: =Datasets!E281 -> 0.16 | G16: =Datasets!F281 -> 0.16 | H16: =Datasets!G281 -> 0.16 | I16: =Datasets!H281 -> 0.16 | J16: =Datasets!I281 -> 0.16 | ... CX16: =Datasets!CW281 -> 0.1755

Sheet 3250
A1: 3250 - Chemical Products
A2: Implied Depreciation Rates for Private Nonresidential Fixed Assets
A3: Updated September 26, 2025
A5: Asset Codes | B5: NIPA Asset Types | C5: 1925 | D5: 1926 | E5: 1927 | F5: 1928 | G5: 1929 | H5: 1930 | I5: 1931 | J5: 1932 | K5: 1933 | L5: 1934 | M5: 1935 | N5: 1936 | O5: 1937 | P5: 1938 | Q5: 1939 | R5: 1940 | S5: 1941 | T5: 1942 | U5: 1943 | V5: 1944 | W5: 1945 | X5: 1946 | Y5: 1947 | Z5: 1948 | AA5: 1949 | AB5: 1950 | AC5: 1951 | AD5: 1952 | AE5: 1953 | AF5: 1954 | AG5: 1955 | AH5: 1956 | AI5: 1957 | AJ5: 1958 | AK5: 1959 | AL5: 1960 | AM5: 1961 | AN5: 1962 | AO5: 1963 | AP5: 1964 | AQ5: 1965 | AR5: 1966 | AS5: 1967 | AT5: 1968 | AU5: 1969 | AV5: 1970 | AW5: 1971 | AX5: 1972 | AY5: 1973 | AZ5: 1974 | BA5: 1975 | BB5: 1976 | BC5: 1977 | BD5: 1978 | BE5: 1979 | BF5: 1980 | BG5: 1981 | BH5: 1982 | BI5: 1983 | BJ5: 1984 | BK5: 1985 | BL5: 1986 | BM5: 1987 | BN5: 1988 | BO5: 1989 | BP5: 1990 | BQ5: 1991 | BR5: 1992 | BS5: 1993 | BT5: 1994 | BU5: 1995 | BV5: 1996 | BW5: 1997 | BX5: 1998 | BY5: 1999 | BZ5: 2000 | CA5: 2001 | CB5: 2002 | CC5: 2003 | CD5: 2004 | CE5: 2005 | CF5: 2006 | CG5: 2007 | CH5: 2008 | CI5: 2009 | CJ5: 2010 | CK5: 2011 | CL5: 2012 | CM5: 2013 | CN5: 2014 | CO5: 2015 | CP5: 2016 | CQ5: 2017 | CR5: 2018 | CS5: 2019 | CT5: 2020 | CU5: 2021 | CV5: 2022 | CW5: 2023 | CX5: 2024
A7: ES00 | B7: Equipment, structures, and intellectual property products | C7: =Datasets!B282 -> 0.0631 | D7: =Datasets!C282 -> 0.0628 | E7: =Datasets!D282 -> 0.0612 | F7: =Datasets!E282 -> 0.06 | G7: =Datasets!F282 -> 0.0589 | H7: =Datasets!G282 -> 0.0583 | I7: =Datasets!H282 -> 0.0582 | J7: =Datasets!I282 -> 0.0581 | ... CX7: =Datasets!CW282 -> 0.0998
A8: EQ00 | B8: Equipment | C8: =Datasets!B283 -> 0.1088 | D8: =Datasets!C283 -> 0.1119 | E8: =Datasets!D283 -> 0.112 | F8: =Datasets!E283 -> 0.1126 | G8: =Datasets!F283 -> 0.1131 | H8: =Datasets!G283 -> 0.1128 | I8: =Datasets!H283 -> 0.112 | J8: =Datasets!I283 -> 0.1111 | ... CX8: =Datasets!CW283 -> 0.116
A9: EP00 | B9: Information | C9: =Datasets!B284 -> 0.135 | D9: =Datasets!C284 -> 0.135 | E9: =Datasets!D284 -> 0.135 | F9: =Datasets!E284 -> 0.135 | G9: =Datasets!F284 -> 0.135 | H9: =Datasets!G284 -> 0.135 | I9: =Datasets!H284 -> 0.135 | J9: =Datasets!I284 -> 0.135 | ... CX9: =Datasets!CW284 -> 0.1562
A10: EP11 | B10: Computers | C10: =Datasets!B285 -> 0 | D10: =Datasets!C285 -> 0 | E10: =Datasets!D285 -> 0 | F10: =Datasets!E285 -> 0 | G10: =Datasets!F285 -> 0 | H10: =Datasets!G285 -> 0 | I10: =Datasets!H285 -> 0 | J10: =Datasets!I285 -> 0 | ... CX10: =Datasets!CW285 -> 0.3385
A11: EI00 | B11: Industrial | C11: =Datasets!B286 -> 0.0938 | D11: =Datasets!C286 -> 0.094 | E11: =Datasets!D286 -> 0.0944 | F11: =Datasets!E286 -> 0.0947 | G11: =Datasets!F286 -> 0.0951 | H11: =Datasets!G286 -> 0.0956 | I11: =Datasets!H286 -> 0.0959 | J11: =Datasets!I286 -> 0.0962 | ... CX11: =Datasets!CW286 -> 0.1033
A12: ET00 | B12: Transportation | C12: =Datasets!B287 -> 0.2387 | D12: =Datasets!C287 -> 0.2522 | E12: =Datasets!D287 -> 0.2527 | F12: =Datasets!E287 -> 0.2596 | G12: =Datasets!F287 -> 0.2659 | H12: =Datasets!G287 -> 0.2693 | I12: =Datasets!H287 -> 0.269 | J12: =Datasets!I287 -> 0.2621 | ... CX12: =Datasets!CW287 -> 0.136
A13: EO00 | B13: Other equipment | C13: =Datasets!B288 -> 0 | D13: =Datasets!C288 -> 0 | E13: =Datasets!D288 -> 0 | F13: =Datasets!E288 -> 0 | G13: =Datasets!F288 -> 0.1179 | H13: =Datasets!G288 -> 0.1179 | I13: =Datasets!H288 -> 0.1179 | J13: =Datasets!I288 -> 0.1179 | ... CX13: =Datasets!CW288 -> 0.1467
A14: ST00 | B14: Structures | C14: =Datasets!B289 -> 0.0309 | D14: =Datasets!C289 -> 0.0309 | E14: =Datasets!D289 -> 0.0308 | F14: =Datasets!E289 -> 0.0308 | G14: =Datasets!F289 -> 0.0308 | H14: =Datasets!G289 -> 0.0308 | I14: =Datasets!H289 -> 0.0308 | J14: =Datasets!I289 -> 0.0308 | ... CX14: =Datasets!CW289 -> 0.0313
A15: SCHC | B15: Commercial and healthcare | C15: =Datasets!B290 -> 0.0247 | D15: =Datasets!C290 -> 0.0247 | E15: =Datasets!D290 -> 0.0247 | F15: =Datasets!E290 -> 0.0247 | G15: =Datasets!F290 -> 0.0247 | H15: =Datasets!G290 -> 0.0247 | I15: =Datasets!H290 -> 0.0247 | J15: =Datasets!I290 -> 0.0247 | ... CX15: =Datasets!CW290 -> 0.0248
A16: IP00 | B16: Intellectual property products | C16: =Datasets!B291 -> 0.1404 | D16: =Datasets!C291 -> 0.1406 | E16: =Datasets!D291 -> 0.1408 | F16: =Datasets!E291 -> 0.1412 | G16: =Datasets!F291 -> 0.1417 | H16: =Datasets!G291 -> 0.142 | I16: =Datasets!H291 -> 0.1424 | J16: =Datasets!I291 -> 0.1431 | ... CX16: =Datasets!CW291 -> 0.1106

Sheet 3260
A1: 3260 - Plastics and Rubber Products
A2: Implied Depreciation Rates for Private Nonresidential Fixed Assets
A3: Updated September 26, 2025
A5: Asset Codes | B5: NIPA Asset Types | C5: 1925 | D5: 1926 | E5: 1927 | F5: 1928 | G5: 1929 | H5: 1930 | I5: 1931 | J5: 1932 | K5: 1933 | L5: 1934 | M5: 1935 | N5: 1936 | O5: 1937 | P5: 1938 | Q5: 1939 | R5: 1940 | S5: 1941 | T5: 1942 | U5: 1943 | V5: 1944 | W5: 1945 | X5: 1946 | Y5: 1947 | Z5: 1948 | AA5: 1949 | AB5: 1950 | AC5: 1951 | AD5: 1952 | AE5: 1953 | AF5: 1954 | AG5: 1955 | AH5: 1956 | AI5: 1957 | AJ5: 1958 | AK5: 1959 | AL5: 1960 | AM5: 1961 | AN5: 1962 | AO5: 1963 | AP5: 1964 | AQ5: 1965 | AR5: 1966 | AS5: 1967 | AT5: 1968 | AU5: 1969 | AV5: 1970 | AW5: 1971 | AX5: 1972 | AY5: 1973 | AZ5: 1974 | BA5: 1975 | BB5: 1976 | BC5: 1977 | BD5: 1978 | BE5: 1979 | BF5: 1980 | BG5: 1981 | BH5: 1982 | BI5: 1983 | BJ5: 1984 | BK5: 1985 | BL5: 1986 | BM5: 1987 | BN5: 1988 | BO5: 1989 | BP5: 1990 | BQ5: 1991 | BR5: 1992 | BS5: 1993 | BT5: 1994 | BU5: 1995 | BV5: 1996 | BW5: 1997 | BX5: 1998 | BY5: 1999 | BZ5: 2000 | CA5: 2001 | CB5: 2002 | CC5: 2003 | CD5: 2004 | CE5: 2005 | CF5: 2006 | CG5: 2007 | CH5: 2008 | CI5: 2009 | CJ5: 2010 | CK5: 2011 | CL5: 2012 | CM5: 2013 | CN5: 2014 | CO5: 2015 | CP5: 2016 | CQ5: 2017 | CR5: 2018 | CS5: 2019 | CT5: 2020 | CU5: 2021 | CV5: 2022 | CW5: 2023 | CX5: 2024
A7: ES00 | B7: Equipment, structures, and intellectual property products | C7: =Datasets!B292 -> 0.0614 | D7: =Datasets!C292 -> 0.0659 | E7: =Datasets!D292 -> 0.0683 | F7: =Datasets!E292 -> 0.0709 | G7: =Datasets!F292 -> 0.073 | H7: =Datasets!G292 -> 0.0754 | I7: =Datasets!H292 -> 0.0776 | J7: =Datasets!I292 -> 0.0787 | ... CX7: =Datasets!CW292 -> 0.1043
A8: EQ00 | B8: Equipment | C8: =Datasets!B293 -> 0.1277 | D8: =Datasets!C293 -> 0.134 | E8: =Datasets!D293 -> 0.134 | F8: =Datasets!E293 -> 0.1343 | G8: =Datasets!F293 -> 0.1345 | H8: =Datasets!G293 -> 0.1335 | I8: =Datasets!H293 -> 0.1321 | J8: =Datasets!I293 -> 0.1309 | ... CX8: =Datasets!CW293 -> 0.1231
A9: EP00 | B9: Information | C9: =Datasets!B294 -> 0.135 | D9: =Datasets!C294 -> 0.135 | E9: =Datasets!D294 -> 0.135 | F9: =Datasets!E294 -> 0.135 | G9: =Datasets!F294 -> 0.135 | H9: =Datasets!G294 -> 0.135 | I9: =Datasets!H294 -> 0.135 | J9: =Datasets!I294 -> 0.135 | ... CX9: =Datasets!CW294 -> 0.1787
A10: EP11 | B10: Computers | C10: =Datasets!B295 -> 0 | D10: =Datasets!C295 -> 0 | E10: =Datasets!D295 -> 0 | F10: =Datasets!E295 -> 0 | G10: =Datasets!F295 -> 0 | H10: =Datasets!G295 -> 0 | I10: =Datasets!H295 -> 0 | J10: =Datasets!I295 -> 0 | ... CX10: =Datasets!CW295 -> 0.3398
A11: EI00 | B11: Industrial | C11: =Datasets!B296 -> 0.1207 | D11: =Datasets!C296 -> 0.1205 | E11: =Datasets!D296 -> 0.1205 | F11: =Datasets!E296 -> 0.1208 | G11: =Datasets!F296 -> 0.1212 | H11: =Datasets!G296 -> 0.1214 | I11: =Datasets!H296 -> 0.1213 | J11: =Datasets!I296 -> 0.1211 | ... CX11: =Datasets!CW296 -> 0.1183
A12: ET00 | B12: Transportation | C12: =Datasets!B297 -> 0.2387 | D12: =Datasets!C297 -> 0.2522 | E12: =Datasets!D297 -> 0.2527 | F12: =Datasets!E297 -> 0.2596 | G12: =Datasets!F297 -> 0.2659 | H12: =Datasets!G297 -> 0.2693 | I12: =Datasets!H297 -> 0.269 | J12: =Datasets!I297 -> 0.2621 | ... CX12: =Datasets!CW297 -> 0.1765
A13: EO00 | B13: Other equipment | C13: =Datasets!B298 -> 0.1241 | D13: =Datasets!C298 -> 0.1263 | E13: =Datasets!D298 -> 0.1272 | F13: =Datasets!E298 -> 0.1269 | G13: =Datasets!F298 -> 0.1244 | H13: =Datasets!G298 -> 0.1185 | I13: =Datasets!H298 -> 0.1183 | J13: =Datasets!I298 -> 0.1183 | ... CX13: =Datasets!CW298 -> 0.1473
A14: ST00 | B14: Structures | C14: =Datasets!B299 -> 0.0313 | D14: =Datasets!C299 -> 0.0313 | E14: =Datasets!D299 -> 0.0312 | F14: =Datasets!E299 -> 0.0312 | G14: =Datasets!F299 -> 0.0312 | H14: =Datasets!G299 -> 0.0312 | I14: =Datasets!H299 -> 0.0312 | J14: =Datasets!I299 -> 0.0312 | ... CX14: =Datasets!CW299 -> 0.0313
A15: SCHC | B15: Commercial and healthcare | C15: =Datasets!B300 -> 0.0247 | D15: =Datasets!C300 -> 0.0247 | E15: =Datasets!D300 -> 0.0247 | F15: =Datasets!E300 -> 0.0247 | G15: =Datasets!F300 -> 0.0247 | H15: =Datasets!G300 -> 0.0247 | I15: =Datasets!H300 -> 0.0247 | J15: =Datasets!I300 -> 0.0247 | ... CX15: =Datasets!CW300 -> 0.024
A16: IP00 | B16: Intellectual property products | C16: =Datasets!B301 -> 0.16 | D16: =Datasets!C301 -> 0.16 | E16: =Datasets!D301 -> 0.16 | F16: =Datasets!E301 -> 0.16 | G16: =Datasets!F301 -> 0.16 | H16: =Datasets!G301 -> 0.16 | I16: =Datasets!H301 -> 0.16 | J16: =Datasets!I301 -> 0.16 | ... CX16: =Datasets!CW301 -> 0.1897

Sheet 4210
A1: 4210 - Wholesale Durable Goods
A2: Implied Depreciation Rates for Private Nonresidential Fixed Assets
A3: Updated September 26, 2025
A5: Asset Codes | B5: NIPA Asset Types | C5: 1925 | D5: 1926 | E5: 1927 | F5: 1928 | G5: 1929 | H5: 1930 | I5: 1931 | J5: 1932 | K5: 1933 | L5: 1934 | M5: 1935 | N5: 1936 | O5: 1937 | P5: 1938 | Q5: 1939 | R5: 1940 | S5: 1941 | T5: 1942 | U5: 1943 | V5: 1944 | W5: 1945 | X5: 1946 | Y5: 1947 | Z5: 1948 | AA5: 1949 | AB5: 1950 | AC5: 1951 | AD5: 1952 | AE5: 1953 | AF5: 1954 | AG5: 1955 | AH5: 1956 | AI5: 1957 | AJ5: 1958 | AK5: 1959 | AL5: 1960 | AM5: 1961 | AN5: 1962 | AO5: 1963 | AP5: 1964 | AQ5: 1965 | AR5: 1966 | AS5: 1967 | AT5: 1968 | AU5: 1969 | AV5: 1970 | AW5: 1971 | AX5: 1972 | AY5: 1973 | AZ5: 1974 | BA5: 1975 | BB5: 1976 | BC5: 1977 | BD5: 1978 | BE5: 1979 | BF5: 1980 | BG5: 1981 | BH5: 1982 | BI5: 1983 | BJ5: 1984 | BK5: 1985 | BL5: 1986 | BM5: 1987 | BN5: 1988 | BO5: 1989 | BP5: 1990 | BQ5: 1991 | BR5: 1992 | BS5: 1993 | BT5: 1994 | BU5: 1995 | BV5: 1996 | BW5: 1997 | BX5: 1998 | BY5: 1999 | BZ5: 2000 | CA5: 2001 | CB5: 2002 | CC5: 2003 | CD5: 2004 | CE5: 2005 | CF5: 2006 | CG5: 2007 | CH5: 2008 | CI5: 2009 | CJ5: 2010 | CK5: 2011 | CL5: 2012 | CM5: 2013 | CN5: 2014 | CO5: 2015 | CP5: 2016 | CQ5: 2017 | CR5: 2018 | CS5: 2019 | CT5: 2020 | CU5: 2021 | CV5: 2022 | CW5: 2023 | CX5: 2024
A7: ES00 | B7: Equipment, structures, and intellectual property products | C7: =Datasets!B302 -> 0.1632 | D7: =Datasets!C302 -> 0.1649 | E7: =Datasets!D302 -> 0.1594 | F7: =Datasets!E302 -> 0.153 | G7: =Datasets!F302 -> 0.1463 | H7: =Datasets!G302 -> 0.1422 | I7: =Datasets!H302 -> 0.1385 | J7: =Datasets!I302 -> 0.1343 | ... CX7: =Datasets!CW302 -> 0.1306
A8: EQ00 | B8: Equipment | C8: =Datasets!B303 -> 0.1908 | D8: =Datasets!C303 -> 0.1932 | E8: =Datasets!D303 -> 0.1877 | F8: =Datasets!E303 -> 0.1815 | G8: =Datasets!F303 -> 0.1747 | H8: =Datasets!G303 -> 0.1701 | I8: =Datasets!H303 -> 0.1666 | J8: =Datasets!I303 -> 0.1633 | ... CX8: =Datasets!CW303 -> 0.1577
A9: EP00 | B9: Information | C9: =Datasets!B304 -> 0.1352 | D9: =Datasets!C304 -> 0.1351 | E9: =Datasets!D304 -> 0.1351 | F9: =Datasets!E304 -> 0.1351 | G9: =Datasets!F304 -> 0.135 | H9: =Datasets!G304 -> 0.135 | I9: =Datasets!H304 -> 0.1349 | J9: =Datasets!I304 -> 0.1349 | ... CX9: =Datasets!CW304 -> 0.2052
A10: EP11 | B10: Computers | C10: =Datasets!B305 -> 0 | D10: =Datasets!C305 -> 0 | E10: =Datasets!D305 -> 0 | F10: =Datasets!E305 -> 0 | G10: =Datasets!F305 -> 0 | H10: =Datasets!G305 -> 0 | I10: =Datasets!H305 -> 0 | J10: =Datasets!I305 -> 0 | ... CX10: =Datasets!CW305 -> 0.3119
A11: EI00 | B11: Industrial | C11: =Datasets!B306 -> 0.1045 | D11: =Datasets!C306 -> 0.1046 | E11: =Datasets!D306 -> 0.1045 | F11: =Datasets!E306 -> 0.1045 | G11: =Datasets!F306 -> 0.1044 | H11: =Datasets!G306 -> 0.1042 | I11: =Datasets!H306 -> 0.104 | J11: =Datasets!I306 -> 0.1038 | ... CX11: =Datasets!CW306 -> 0.1049
A12: ET00 | B12: Transportation | C12: =Datasets!B307 -> 0.2199 | D12: =Datasets!C307 -> 0.2271 | E12: =Datasets!D307 -> 0.2258 | F12: =Datasets!E307 -> 0.2284 | G12: =Datasets!F307 -> 0.2297 | H12: =Datasets!G307 -> 0.2288 | I12: =Datasets!H307 -> 0.2267 | J12: =Datasets!I307 -> 0.2222 | ... CX12: =Datasets!CW307 -> 0.1862
A13: EO00 | B13: Other equipment | C13: =Datasets!B308 -> 0.1446 | D13: =Datasets!C308 -> 0.1452 | E13: =Datasets!D308 -> 0.1451 | F13: =Datasets!E308 -> 0.1442 | G13: =Datasets!F308 -> 0.1423 | H13: =Datasets!G308 -> 0.1407 | I13: =Datasets!H308 -> 0.1401 | J13: =Datasets!I308 -> 0.1398 | ... CX13: =Datasets!CW308 -> 0.1455
A14: ST00 | B14: Structures | C14: =Datasets!B309 -> 0.0249 | D14: =Datasets!C309 -> 0.0249 | E14: =Datasets!D309 -> 0.0249 | F14: =Datasets!E309 -> 0.0249 | G14: =Datasets!F309 -> 0.0249 | H14: =Datasets!G309 -> 0.0248 | I14: =Datasets!H309 -> 0.0248 | J14: =Datasets!I309 -> 0.0248 | ... CX14: =Datasets!CW309 -> 0.0251
A15: SCHC | B15: Commercial and healthcare | C15: =Datasets!B310 -> 0.0249 | D15: =Datasets!C310 -> 0.0249 | E15: =Datasets!D310 -> 0.0249 | F15: =Datasets!E310 -> 0.0249 | G15: =Datasets!F310 -> 0.0249 | H15: =Datasets!G310 -> 0.0248 | I15: =Datasets!H310 -> 0.0248 | J15: =Datasets!I310 -> 0.0249 | ... CX15: =Datasets!CW310 -> 0.0239
A16: IP00 | B16: Intellectual property products | C16: =Datasets!B311 -> 0.16 | D16: =Datasets!C311 -> 0.16 | E16: =Datasets!D311 -> 0.16 | F16: =Datasets!E311 -> 0.16 | G16: =Datasets!F311 -> 0.16 | H16: =Datasets!G311 -> 0.16 | I16: =Datasets!H311 -> 0.16 | J16: =Datasets!I311 -> 0.16 | ... CX16: =Datasets!CW311 -> 0.302

Sheet 4220
A1: 4220 - Wholesale Nondurable Goods
A2: Implied Depreciation Rates for Private Nonresidential Fixed Assets
A3: Updated September 26, 2025
A5: Asset Codes | B5: NIPA Asset Types | C5: 1925 | D5: 1926 | E5: 1927 | F5: 1928 | G5: 1929 | H5: 1930 | I5: 1931 | J5: 1932 | K5: 1933 | L5: 1934 | M5: 1935 | N5: 1936 | O5: 1937 | P5: 1938 | Q5: 1939 | R5: 1940 | S5: 1941 | T5: 1942 | U5: 1943 | V5: 1944 | W5: 1945 | X5: 1946 | Y5: 1947 | Z5: 1948 | AA5: 1949 | AB5: 1950 | AC5: 1951 | AD5: 1952 | AE5: 1953 | AF5: 1954 | AG5: 1955 | AH5: 1956 | AI5: 1957 | AJ5: 1958 | AK5: 1959 | AL5: 1960 | AM5: 1961 | AN5: 1962 | AO5: 1963 | AP5: 1964 | AQ5: 1965 | AR5: 1966 | AS5: 1967 | AT5: 1968 | AU5: 1969 | AV5: 1970 | AW5: 1971 | AX5: 1972 | AY5: 1973 | AZ5: 1974 | BA5: 1975 | BB5: 1976 | BC5: 1977 | BD5: 1978 | BE5: 1979 | BF5: 1980 | BG5: 1981 | BH5: 1982 | BI5: 1983 | BJ5: 1984 | BK5: 1985 | BL5: 1986 | BM5: 1987 | BN5: 1988 | BO5: 1989 | BP5: 1990 | BQ5: 1991 | BR5: 1992 | BS5: 1993 | BT5: 1994 | BU5: 1995 | BV5: 1996 | BW5: 1997 | BX5: 1998 | BY5: 1999 | BZ5: 2000 | CA5: 2001 | CB5: 2002 | CC5: 2003 | CD5: 2004 | CE5: 2005 | CF5: 2006 | CG5: 2007 | CH5: 2008 | CI5: 2009 | CJ5: 2010 | CK5: 2011 | CL5: 2012 | CM5: 2013 | CN5: 2014 | CO5: 2015 | CP5: 2016 | CQ5: 2017 | CR5: 2018 | CS5: 2019 | CT5: 2020 | CU5: 2021 | CV5: 2022 | CW5: 2023 | CX5: 2024
A7: ES00 | B7: Equipment, structures, and intellectual property products | C7: =Datasets!B312 -> 0.1214 | D7: =Datasets!C312 -> 0.1191 | E7: =Datasets!D312 -> 0.1119 | F7: =Datasets!E312 -> 0.1051 | G7: =Datasets!F312 -> 0.0983 | H7: =Datasets!G312 -> 0.0943 | I7: =Datasets!H312 -> 0.0909 | J7: =Datasets!I312 -> 0.0869 | ... CX7: =Datasets!CW312 -> 0.1045
A8: EQ00 | B8: Equipment | C8: =Datasets!B313 -> 0.192 | D8: =Datasets!C313 -> 0.1922 | E8: =Datasets!D313 -> 0.1838 | F8: =Datasets!E313 -> 0.1747 | G8: =Datasets!F313 -> 0.1646 | H8: =Datasets!G313 -> 0.1571 | I8: =Datasets!H313 -> 0.152 | J8: =Datasets!I313 -> 0.1479 | ... CX8: =Datasets!CW313 -> 0.1509
A9: EP00 | B9: Information | C9: =Datasets!B314 -> 0.1416 | D9: =Datasets!C314 -> 0.1415 | E9: =Datasets!D314 -> 0.1399 | F9: =Datasets!E314 -> 0.1375 | G9: =Datasets!F314 -> 0.1361 | H9: =Datasets!G314 -> 0.1351 | I9: =Datasets!H314 -> 0.1339 | J9: =Datasets!I314 -> 0.1333 | ... CX9: =Datasets!CW314 -> 0.2167
A10: EP11 | B10: Computers | C10: =Datasets!B315 -> 0 | D10: =Datasets!C315 -> 0 | E10: =Datasets!D315 -> 0 | F10: =Datasets!E315 -> 0 | G10: =Datasets!F315 -> 0 | H10: =Datasets!G315 -> 0 | I10: =Datasets!H315 -> 0 | J10: =Datasets!I315 -> 0 | ... CX10: =Datasets!CW315 -> 0.3367
A11: EI00 | B11: Industrial | C11: =Datasets!B316 -> 0.1013 | D11: =Datasets!C316 -> 0.1015 | E11: =Datasets!D316 -> 0.1016 | F11: =Datasets!E316 -> 0.1018 | G11: =Datasets!F316 -> 0.1019 | H11: =Datasets!G316 -> 0.1017 | I11: =Datasets!H316 -> 0.1014 | J11: =Datasets!I316 -> 0.1011 | ... CX11: =Datasets!CW316 -> 0.1055
A12: ET00 | B12: Transportation | C12: =Datasets!B317 -> 0.232 | D12: =Datasets!C317 -> 0.2421 | E12: =Datasets!D317 -> 0.2409 | F12: =Datasets!E317 -> 0.2449 | G12: =Datasets!F317 -> 0.2482 | H12: =Datasets!G317 -> 0.2495 | I12: =Datasets!H317 -> 0.2481 | J12: =Datasets!I317 -> 0.2423 | ... CX12: =Datasets!CW317 -> 0.1847
A13: EO00 | B13: Other equipment | C13: =Datasets!B318 -> 0.1432 | D13: =Datasets!C318 -> 0.144 | E13: =Datasets!D318 -> 0.1438 | F13: =Datasets!E318 -> 0.1425 | G13: =Datasets!F318 -> 0.1396 | H13: =Datasets!G318 -> 0.1374 | I13: =Datasets!H318 -> 0.1369 | J13: =Datasets!I318 -> 0.1367 | ... CX13: =Datasets!CW318 -> 0.1447
A14: ST00 | B14: Structures | C14: =Datasets!B319 -> 0.0247 | D14: =Datasets!C319 -> 0.0247 | E14: =Datasets!D319 -> 0.0248 | F14: =Datasets!E319 -> 0.0247 | G14: =Datasets!F319 -> 0.0247 | H14: =Datasets!G319 -> 0.0247 | I14: =Datasets!H319 -> 0.0247 | J14: =Datasets!I319 -> 0.0247 | ... CX14: =Datasets!CW319 -> 0.0246
A15: SCHC | B15: Commercial and healthcare | C15: =Datasets!B320 -> 0.0247 | D15: =Datasets!C320 -> 0.0247 | E15: =Datasets!D320 -> 0.0248 | F15: =Datasets!E320 -> 0.0247 | G15: =Datasets!F320 -> 0.0247 | H15: =Datasets!G320 -> 0.0247 | I15: =Datasets!H320 -> 0.0247 | J15: =Datasets!I320 -> 0.0247 | ... CX15: =Datasets!CW320 -> 0.0234
A16: IP00 | B16: Intellectual property products | C16: =Datasets!B321 -> 0.16 | D16: =Datasets!C321 -> 0.16 | E16: =Datasets!D321 -> 0.16 | F16: =Datasets!E321 -> 0.16 | G16: =Datasets!F321 -> 0.16 | H16: =Datasets!G321 -> 0.16 | I16: =Datasets!H321 -> 0.16 | J16: =Datasets!I321 -> 0.16 | ... CX16: =Datasets!CW321 -> 0.2964

Sheet 4410
A1: 4410 - Motor Vehicle and Parts Dealers
A2: Implied Depreciation Rates for Private Nonresidential Fixed Assets
A3: Updated September 26, 2025
A5: Asset Codes | B5: NIPA Asset Types | C5: 1925 | D5: 1926 | E5: 1927 | F5: 1928 | G5: 1929 | H5: 1930 | I5: 1931 | J5: 1932 | K5: 1933 | L5: 1934 | M5: 1935 | N5: 1936 | O5: 1937 | P5: 1938 | Q5: 1939 | R5: 1940 | S5: 1941 | T5: 1942 | U5: 1943 | V5: 1944 | W5: 1945 | X5: 1946 | Y5: 1947 | Z5: 1948 | AA5: 1949 | AB5: 1950 | AC5: 1951 | AD5: 1952 | AE5: 1953 | AF5: 1954 | AG5: 1955 | AH5: 1956 | AI5: 1957 | AJ5: 1958 | AK5: 1959 | AL5: 1960 | AM5: 1961 | AN5: 1962 | AO5: 1963 | AP5: 1964 | AQ5: 1965 | AR5: 1966 | AS5: 1967 | AT5: 1968 | AU5: 1969 | AV5: 1970 | AW5: 1971 | AX5: 1972 | AY5: 1973 | AZ5: 1974 | BA5: 1975 | BB5: 1976 | BC5: 1977 | BD5: 1978 | BE5: 1979 | BF5: 1980 | BG5: 1981 | BH5: 1982 | BI5: 1983 | BJ5: 1984 | BK5: 1985 | BL5: 1986 | BM5: 1987 | BN5: 1988 | BO5: 1989 | BP5: 1990 | BQ5: 1991 | BR5: 1992 | BS5: 1993 | BT5: 1994 | BU5: 1995 | BV5: 1996 | BW5: 1997 | BX5: 1998 | BY5: 1999 | BZ5: 2000 | CA5: 2001 | CB5: 2002 | CC5: 2003 | CD5: 2004 | CE5: 2005 | CF5: 2006 | CG5: 2007 | CH5: 2008 | CI5: 2009 | CJ5: 2010 | CK5: 2011 | CL5: 2012 | CM5: 2013 | CN5: 2014 | CO5: 2015 | CP5: 2016 | CQ5: 2017 | CR5: 2018 | CS5: 2019 | CT5: 2020 | CU5: 2021 | CV5: 2022 | CW5: 2023 | CX5: 2024
A7: ES00 | B7: Equipment, structures, and intellectual property products | C7: =Datasets!B322 -> 0.0355 | D7: =Datasets!C322 -> 0.0352 | E7: =Datasets!D322 -> 0.0347 | F7: =Datasets!E322 -> 0.0346 | G7: =Datasets!F322 -> 0.0343 | H7: =Datasets!G322 -> 0.0335 | I7: =Datasets!H322 -> 0.0328 | J7: =Datasets!I322 -> 0.0321 | ... CX7: =Datasets!CW322 -> 0.0658
A8: EQ00 | B8: Equipment | C8: =Datasets!B323 -> 0.1555 | D8: =Datasets!C323 -> 0.148 | E8: =Datasets!D323 -> 0.1393 | F8: =Datasets!E323 -> 0.1335 | G8: =Datasets!F323 -> 0.1302 | H8: =Datasets!G323 -> 0.1285 | I8: =Datasets!H323 -> 0.1268 | J8: =Datasets!I323 -> 0.125 | ... CX8: =Datasets!CW323 -> 0.1609
A9: EP00 | B9: Information | C9: =Datasets!B324 -> 0.2729 | D9: =Datasets!C324 -> 0.2729 | E9: =Datasets!D324 -> 0.2729 | F9: =Datasets!E324 -> 0.2729 | G9: =Datasets!F324 -> 0.2729 | H9: =Datasets!G324 -> 0.2729 | I9: =Datasets!H324 -> 0.2729 | J9: =Datasets!I324 -> 0.2729 | ... CX9: =Datasets!CW324 -> 0.1898
A10: EP11 | B10: Computers | C10: =Datasets!B325 -> 0 | D10: =Datasets!C325 -> 0 | E10: =Datasets!D325 -> 0 | F10: =Datasets!E325 -> 0 | G10: =Datasets!F325 -> 0 | H10: =Datasets!G325 -> 0 | I10: =Datasets!H325 -> 0 | J10: =Datasets!I325 -> 0 | ... CX10: =Datasets!CW325 -> 0.333
A11: EI00 | B11: Industrial | C11: =Datasets!B326 -> 0.1065 | D11: =Datasets!C326 -> 0.1065 | E11: =Datasets!D326 -> 0.1064 | F11: =Datasets!E326 -> 0.1066 | G11: =Datasets!F326 -> 0.1067 | H11: =Datasets!G326 -> 0.1066 | I11: =Datasets!H326 -> 0.1065 | J11: =Datasets!I326 -> 0.1064 | ... CX11: =Datasets!CW326 -> 0.1045
A12: ET00 | B12: Transportation | C12: =Datasets!B327 -> 0.2387 | D12: =Datasets!C327 -> 0.2522 | E12: =Datasets!D327 -> 0.2527 | F12: =Datasets!E327 -> 0.2596 | G12: =Datasets!F327 -> 0.2659 | H12: =Datasets!G327 -> 0.2693 | I12: =Datasets!H327 -> 0.269 | J12: =Datasets!I327 -> 0.2621 | ... CX12: =Datasets!CW327 -> 0.1848
A13: EO00 | B13: Other equipment | C13: =Datasets!B328 -> 0.1276 | D13: =Datasets!C328 -> 0.1279 | E13: =Datasets!D328 -> 0.1279 | F13: =Datasets!E328 -> 0.1277 | G13: =Datasets!F328 -> 0.1277 | H13: =Datasets!G328 -> 0.1275 | I13: =Datasets!H328 -> 0.1272 | J13: =Datasets!I328 -> 0.127 | ... CX13: =Datasets!CW328 -> 0.139
A14: ST00 | B14: Structures | C14: =Datasets!B329 -> 0.0246 | D14: =Datasets!C329 -> 0.0246 | E14: =Datasets!D329 -> 0.0247 | F14: =Datasets!E329 -> 0.0247 | G14: =Datasets!F329 -> 0.0247 | H14: =Datasets!G329 -> 0.0248 | I14: =Datasets!H329 -> 0.0248 | J14: =Datasets!I329 -> 0.0248 | ... CX14: =Datasets!CW329 -> 0.0261
A15: SCHC | B15: Commercial and healthcare | C15: =Datasets!B330 -> 0.0246 | D15: =Datasets!C330 -> 0.0246 | E15: =Datasets!D330 -> 0.0247 | F15: =Datasets!E330 -> 0.0247 | G15: =Datasets!F330 -> 0.0247 | H15: =Datasets!G330 -> 0.0248 | I15: =Datasets!H330 -> 0.0248 | J15: =Datasets!I330 -> 0.0248 | ... CX15: =Datasets!CW330 -> 0.026
A16: IP00 | B16: Intellectual property products | C16: =Datasets!B331 -> 0.16 | D16: =Datasets!C331 -> 0.16 | E16: =Datasets!D331 -> 0.16 | F16: =Datasets!E331 -> 0.16 | G16: =Datasets!F331 -> 0.16 | H16: =Datasets!G331 -> 0.16 | I16: =Datasets!H331 -> 0.16 | J16: =Datasets!I331 -> 0.16 | ... CX16: =Datasets!CW331 -> 0.2594

Sheet 4450
A1: 4450 - Food and Beverage Stores
A2: Implied Depreciation Rates for Private Nonresidential Fixed Assets
A3: Updated September 26, 2025
A5: Asset Codes | B5: NIPA Asset Types | C5: 1925 | D5: 1926 | E5: 1927 | F5: 1928 | G5: 1929 | H5: 1930 | I5: 1931 | J5: 1932 | K5: 1933 | L5: 1934 | M5: 1935 | N5: 1936 | O5: 1937 | P5: 1938 | Q5: 1939 | R5: 1940 | S5: 1941 | T5: 1942 | U5: 1943 | V5: 1944 | W5: 1945 | X5: 1946 | Y5: 1947 | Z5: 1948 | AA5: 1949 | AB5: 1950 | AC5: 1951 | AD5: 1952 | AE5: 1953 | AF5: 1954 | AG5: 1955 | AH5: 1956 | AI5: 1957 | AJ5: 1958 | AK5: 1959 | AL5: 1960 | AM5: 1961 | AN5: 1962 | AO5: 1963 | AP5: 1964 | AQ5: 1965 | AR5: 1966 | AS5: 1967 | AT5: 1968 | AU5: 1969 | AV5: 1970 | AW5: 1971 | AX5: 1972 | AY5: 1973 | AZ5: 1974 | BA5: 1975 | BB5: 1976 | BC5: 1977 | BD5: 1978 | BE5: 1979 | BF5: 1980 | BG5: 1981 | BH5: 1982 | BI5: 1983 | BJ5: 1984 | BK5: 1985 | BL5: 1986 | BM5: 1987 | BN5: 1988 | BO5: 1989 | BP5: 1990 | BQ5: 1991 | BR5: 1992 | BS5: 1993 | BT5: 1994 | BU5: 1995 | BV5: 1996 | BW5: 1997 | BX5: 1998 | BY5: 1999 | BZ5: 2000 | CA5: 2001 | CB5: 2002 | CC5: 2003 | CD5: 2004 | CE5: 2005 | CF5: 2006 | CG5: 2007 | CH5: 2008 | CI5: 2009 | CJ5: 2010 | CK5: 2011 | CL5: 2012 | CM5: 2013 | CN5: 2014 | CO5: 2015 | CP5: 2016 | CQ5: 2017 | CR5: 2018 | CS5: 2019 | CT5: 2020 | CU5: 2021 | CV5: 2022 | CW5: 2023 | CX5: 2024
A7: ES00 | B7: Equipment, structures, and intellectual property products | C7: =Datasets!B332 -> 0.0369 | D7: =Datasets!C332 -> 0.037 | E7: =Datasets!D332 -> 0.0367 | F7: =Datasets!E332 -> 0.0366 | G7: =Datasets!F332 -> 0.0365 | H7: =Datasets!G332 -> 0.0361 | I7: =Datasets!H332 -> 0.0355 | J7: =Datasets!I332 -> 0.0349 | ... CX7: =Datasets!CW332 -> 0.0717
A8: EQ00 | B8: Equipment | C8: =Datasets!B333 -> 0.1475 | D8: =Datasets!C333 -> 0.1462 | E8: =Datasets!D333 -> 0.1422 | F8: =Datasets!E333 -> 0.1398 | G8: =Datasets!F333 -> 0.1385 | H8: =Datasets!G333 -> 0.138 | I8: =Datasets!H333 -> 0.1371 | J8: =Datasets!I333 -> 0.1356 | ... CX8: =Datasets!CW333 -> 0.1326
A9: EP00 | B9: Information | C9: =Datasets!B334 -> 0.2728 | D9: =Datasets!C334 -> 0.2728 | E9: =Datasets!D334 -> 0.2727 | F9: =Datasets!E334 -> 0.2727 | G9: =Datasets!F334 -> 0.2727 | H9: =Datasets!G334 -> 0.2727 | I9: =Datasets!H334 -> 0.2727 | J9: =Datasets!I334 -> 0.2726 | ... CX9: =Datasets!CW334 -> 0.2521
A10: EP11 | B10: Computers | C10: =Datasets!B335 -> 0 | D10: =Datasets!C335 -> 0 | E10: =Datasets!D335 -> 0 | F10: =Datasets!E335 -> 0 | G10: =Datasets!F335 -> 0 | H10: =Datasets!G335 -> 0 | I10: =Datasets!H335 -> 0 | J10: =Datasets!I335 -> 0 | ... CX10: =Datasets!CW335 -> 0.3351
A11: EI00 | B11: Industrial | C11: =Datasets!B336 -> 0.0991 | D11: =Datasets!C336 -> 0.0995 | E11: =Datasets!D336 -> 0.0998 | F11: =Datasets!E336 -> 0.1002 | G11: =Datasets!F336 -> 0.1003 | H11: =Datasets!G336 -> 0.1002 | I11: =Datasets!H336 -> 0.1 | J11: =Datasets!I336 -> 0.0999 | ... CX11: =Datasets!CW336 -> 0.1058
A12: ET00 | B12: Transportation | C12: =Datasets!B337 -> 0.2387 | D12: =Datasets!C337 -> 0.2522 | E12: =Datasets!D337 -> 0.2527 | F12: =Datasets!E337 -> 0.2596 | G12: =Datasets!F337 -> 0.2659 | H12: =Datasets!G337 -> 0.2693 | I12: =Datasets!H337 -> 0.269 | J12: =Datasets!I337 -> 0.2621 | ... CX12: =Datasets!CW337 -> 0.1858
A13: EO00 | B13: Other equipment | C13: =Datasets!B338 -> 0.1299 | D13: =Datasets!C338 -> 0.1303 | E13: =Datasets!D338 -> 0.1302 | F13: =Datasets!E338 -> 0.1299 | G13: =Datasets!F338 -> 0.1299 | H13: =Datasets!G338 -> 0.1297 | I13: =Datasets!H338 -> 0.1293 | J13: =Datasets!I338 -> 0.1291 | ... CX13: =Datasets!CW338 -> 0.1421
A14: ST00 | B14: Structures | C14: =Datasets!B339 -> 0.0256 | D14: =Datasets!C339 -> 0.0256 | E14: =Datasets!D339 -> 0.0257 | F14: =Datasets!E339 -> 0.0257 | G14: =Datasets!F339 -> 0.0257 | H14: =Datasets!G339 -> 0.0257 | I14: =Datasets!H339 -> 0.0257 | J14: =Datasets!I339 -> 0.0257 | ... CX14: =Datasets!CW339 -> 0.0263
A15: SCHC | B15: Commercial and healthcare | C15: =Datasets!B340 -> 0.0256 | D15: =Datasets!C340 -> 0.0256 | E15: =Datasets!D340 -> 0.0257 | F15: =Datasets!E340 -> 0.0257 | G15: =Datasets!F340 -> 0.0257 | H15: =Datasets!G340 -> 0.0257 | I15: =Datasets!H340 -> 0.0257 | J15: =Datasets!I340 -> 0.0257 | ... CX15: =Datasets!CW340 -> 0.0263
A16: IP00 | B16: Intellectual property products | C16: =Datasets!B341 -> 0.16 | D16: =Datasets!C341 -> 0.16 | E16: =Datasets!D341 -> 0.16 | F16: =Datasets!E341 -> 0.16 | G16: =Datasets!F341 -> 0.16 | H16: =Datasets!G341 -> 0.16 | I16: =Datasets!H341 -> 0.16 | J16: =Datasets!I341 -> 0.16 | ... CX16: =Datasets!CW341 -> 0.2802

Sheet 4520
A1: 4520 - General Merchandise Stores
A2: Implied Depreciation Rates for Private Nonresidential Fixed Assets
A3: Updated September 26, 2025
A5: Asset Codes | B5: NIPA Asset Types | C5: 1925 | D5: 1926 | E5: 1927 | F5: 1928 | G5: 1929 | H5: 1930 | I5: 1931 | J5: 1932 | K5: 1933 | L5: 1934 | M5: 1935 | N5: 1936 | O5: 1937 | P5: 1938 | Q5: 1939 | R5: 1940 | S5: 1941 | T5: 1942 | U5: 1943 | V5: 1944 | W5: 1945 | X5: 1946 | Y5: 1947 | Z5: 1948 | AA5: 1949 | AB5: 1950 | AC5: 1951 | AD5: 1952 | AE5: 1953 | AF5: 1954 | AG5: 1955 | AH5: 1956 | AI5: 1957 | AJ5: 1958 | AK5: 1959 | AL5: 1960 | AM5: 1961 | AN5: 1962 | AO5: 1963 | AP5: 1964 | AQ5: 1965 | AR5: 1966 | AS5: 1967 | AT5: 1968 | AU5: 1969 | AV5: 1970 | AW5: 1971 | AX5: 1972 | AY5: 1973 | AZ5: 1974 | BA5: 1975 | BB5: 1976 | BC5: 1977 | BD5: 1978 | BE5: 1979 | BF5: 1980 | BG5: 1981 | BH5: 1982 | BI5: 1983 | BJ5: 1984 | BK5: 1985 | BL5: 1986 | BM5: 1987 | BN5: 1988 | BO5: 1989 | BP5: 1990 | BQ5: 1991 | BR5: 1992 | BS5: 1993 | BT5: 1994 | BU5: 1995 | BV5: 1996 | BW5: 1997 | BX5: 1998 | BY5: 1999 | BZ5: 2000 | CA5: 2001 | CB5: 2002 | CC5: 2003 | CD5: 2004 | CE5: 2005 | CF5: 2006 | CG5: 2007 | CH5: 2008 | CI5: 2009 | CJ5: 2010 | CK5: 2011 | CL5: 2012 | CM5: 2013 | CN5: 2014 | CO5: 2015 | CP5: 2016 | CQ5: 2017 | CR5: 2018 | CS5: 2019 | CT5: 2020 | CU5: 2021 | CV5: 2022 | CW5: 2023 | CX5: 2024
A7: ES00 | B7: Equipment, structures, and intellectual property products | C7: =Datasets!B342 -> 0.0322 | D7: =Datasets!C342 -> 0.0328 | E7: =Datasets!D342 -> 0.033 | F7: =Datasets!E342 -> 0.0334 | G7: =Datasets!F342 -> 0.0336 | H7: =Datasets!G342 -> 0.0334 | I7: =Datasets!H342 -> 0.0329 | J7: =Datasets!I342 -> 0.0324 | ... CX7: =Datasets!CW342 -> 0.0898
A8: EQ00 | B8: Equipment | C8: =Datasets!B343 -> 0.1348 | D8: =Datasets!C343 -> 0.1372 | E8: =Datasets!D343 -> 0.1362 | F8: =Datasets!E343 -> 0.1358 | G8: =Datasets!F343 -> 0.136 | H8: =Datasets!G343 -> 0.1363 | I8: =Datasets!H343 -> 0.1361 | J8: =Datasets!I343 -> 0.1352 | ... CX8: =Datasets!CW343 -> 0.147
A9: EP00 | B9: Information | C9: =Datasets!B344 -> 0.2727 | D9: =Datasets!C344 -> 0.2727 | E9: =Datasets!D344 -> 0.2727 | F9: =Datasets!E344 -> 0.2727 | G9: =Datasets!F344 -> 0.2727 | H9: =Datasets!G344 -> 0.2726 | I9: =Datasets!H344 -> 0.2726 | J9: =Datasets!I344 -> 0.2725 | ... CX9: =Datasets!CW344 -> 0.1947
A10: EP11 | B10: Computers | C10: =Datasets!B345 -> 0 | D10: =Datasets!C345 -> 0 | E10: =Datasets!D345 -> 0 | F10: =Datasets!E345 -> 0 | G10: =Datasets!F345 -> 0 | H10: =Datasets!G345 -> 0 | I10: =Datasets!H345 -> 0 | J10: =Datasets!I345 -> 0 | ... CX10: =Datasets!CW345 -> 0.3328
A11: EI00 | B11: Industrial | C11: =Datasets!B346 -> 0.0989 | D11: =Datasets!C346 -> 0.0993 | E11: =Datasets!D346 -> 0.0995 | F11: =Datasets!E346 -> 0.0998 | G11: =Datasets!F346 -> 0.1 | H11: =Datasets!G346 -> 0.0999 | I11: =Datasets!H346 -> 0.0997 | J11: =Datasets!I346 -> 0.0996 | ... CX11: =Datasets!CW346 -> 0.1053
A12: ET00 | B12: Transportation | C12: =Datasets!B347 -> 0.2387 | D12: =Datasets!C347 -> 0.2522 | E12: =Datasets!D347 -> 0.2527 | F12: =Datasets!E347 -> 0.2596 | G12: =Datasets!F347 -> 0.2659 | H12: =Datasets!G347 -> 0.2693 | I12: =Datasets!H347 -> 0.269 | J12: =Datasets!I347 -> 0.2621 | ... CX12: =Datasets!CW347 -> 0.1282
A13: EO00 | B13: Other equipment | C13: =Datasets!B348 -> 0.1237 | D13: =Datasets!C348 -> 0.124 | E13: =Datasets!D348 -> 0.1241 | F13: =Datasets!E348 -> 0.1241 | G13: =Datasets!F348 -> 0.1241 | H13: =Datasets!G348 -> 0.124 | I13: =Datasets!H348 -> 0.1238 | J13: =Datasets!I348 -> 0.1236 | ... CX13: =Datasets!CW348 -> 0.1336
A14: ST00 | B14: Structures | C14: =Datasets!B349 -> 0.0238 | D14: =Datasets!C349 -> 0.0238 | E14: =Datasets!D349 -> 0.0239 | F14: =Datasets!E349 -> 0.0239 | G14: =Datasets!F349 -> 0.024 | H14: =Datasets!G349 -> 0.024 | I14: =Datasets!H349 -> 0.024 | J14: =Datasets!I349 -> 0.0241 | ... CX14: =Datasets!CW349 -> 0.0258
A15: SCHC | B15: Commercial and healthcare | C15: =Datasets!B350 -> 0.0238 | D15: =Datasets!C350 -> 0.0238 | E15: =Datasets!D350 -> 0.0239 | F15: =Datasets!E350 -> 0.0239 | G15: =Datasets!F350 -> 0.024 | H15: =Datasets!G350 -> 0.024 | I15: =Datasets!H350 -> 0.024 | J15: =Datasets!I350 -> 0.0241 | ... CX15: =Datasets!CW350 -> 0.0258
A16: IP00 | B16: Intellectual property products | C16: =Datasets!B351 -> 0.16 | D16: =Datasets!C351 -> 0.16 | E16: =Datasets!D351 -> 0.16 | F16: =Datasets!E351 -> 0.16 | G16: =Datasets!F351 -> 0.16 | H16: =Datasets!G351 -> 0.16 | I16: =Datasets!H351 -> 0.16 | J16: =Datasets!I351 -> 0.16 | ... CX16: =Datasets!CW351 -> 0.3727

Sheet 442R
A1: 442R - Other Retail
A2: Implied Depreciation Rates for Private Nonresidential Fixed Assets
A3: Updated September 26, 2025
A5: Asset Codes | B5: NIPA Asset Types | C5: 1925 | D5: 1926 | E5: 1927 | F5: 1928 | G5: 1929 | H5: 1930 | I5: 1931 | J5: 1932 | K5: 1933 | L5: 1934 | M5: 1935 | N5: 1936 | O5: 1937 | P5: 1938 | Q5: 1939 | R5: 1940 | S5: 1941 | T5: 1942 | U5: 1943 | V5: 1944 | W5: 1945 | X5: 1946 | Y5: 1947 | Z5: 1948 | AA5: 1949 | AB5: 1950 | AC5: 1951 | AD5: 1952 | AE5: 1953 | AF5: 1954 | AG5: 1955 | AH5: 1956 | AI5: 1957 | AJ5: 1958 | AK5: 1959 | AL5: 1960 | AM5: 1961 | AN5: 1962 | AO5: 1963 | AP5: 1964 | AQ5: 1965 | AR5: 1966 | AS5: 1967 | AT5: 1968 | AU5: 1969 | AV5: 1970 | AW5: 1971 | AX5: 1972 | AY5: 1973 | AZ5: 1974 | BA5: 1975 | BB5: 1976 | BC5: 1977 | BD5: 1978 | BE5: 1979 | BF5: 1980 | BG5: 1981 | BH5: 1982 | BI5: 1983 | BJ5: 1984 | BK5: 1985 | BL5: 1986 | BM5: 1987 | BN5: 1988 | BO5: 1989 | BP5: 1990 | BQ5: 1991 | BR5: 1992 | BS5: 1993 | BT5: 1994 | BU5: 1995 | BV5: 1996 | BW5: 1997 | BX5: 1998 | BY5: 1999 | BZ5: 2000 | CA5: 2001 | CB5: 2002 | CC5: 2003 | CD5: 2004 | CE5: 2005 | CF5: 2006 | CG5: 2007 | CH5: 2008 | CI5: 2009 | CJ5: 2010 | CK5: 2011 | CL5: 2012 | CM5: 2013 | CN5: 2014 | CO5: 2015 | CP5: 2016 | CQ5: 2017 | CR5: 2018 | CS5: 2019 | CT5: 2020 | CU5: 2021 | CV5: 2022 | CW5: 2023 | CX5: 2024
A7: ES00 | B7: Equipment, structures, and intellectual property products | C7: =Datasets!B352 -> 0.0358 | D7: =Datasets!C352 -> 0.036 | E7: =Datasets!D352 -> 0.0359 | F7: =Datasets!E352 -> 0.036 | G7: =Datasets!F352 -> 0.0359 | H7: =Datasets!G352 -> 0.0355 | I7: =Datasets!H352 -> 0.0349 | J7: =Datasets!I352 -> 0.0342 | ... CX7: =Datasets!CW352 -> 0.0943
A8: EQ00 | B8: Equipment | C8: =Datasets!B353 -> 0.1468 | D8: =Datasets!C353 -> 0.1445 | E8: =Datasets!D353 -> 0.1404 | F8: =Datasets!E353 -> 0.1378 | G8: =Datasets!F353 -> 0.1366 | H8: =Datasets!G353 -> 0.136 | I8: =Datasets!H353 -> 0.1351 | J8: =Datasets!I353 -> 0.1337 | ... CX8: =Datasets!CW353 -> 0.1434
A9: EP00 | B9: Information | C9: =Datasets!B354 -> 0.2728 | D9: =Datasets!C354 -> 0.2728 | E9: =Datasets!D354 -> 0.2728 | F9: =Datasets!E354 -> 0.2728 | G9: =Datasets!F354 -> 0.2728 | H9: =Datasets!G354 -> 0.2728 | I9: =Datasets!H354 -> 0.2728 | J9: =Datasets!I354 -> 0.2728 | ... CX9: =Datasets!CW354 -> 0.1631
A10: EP11 | B10: Computers | C10: =Datasets!B355 -> 0 | D10: =Datasets!C355 -> 0 | E10: =Datasets!D355 -> 0 | F10: =Datasets!E355 -> 0 | G10: =Datasets!F355 -> 0 | H10: =Datasets!G355 -> 0 | I10: =Datasets!H355 -> 0 | J10: =Datasets!I355 -> 0 | ... CX10: =Datasets!CW355 -> 0.3339
A11: EI00 | B11: Industrial | C11: =Datasets!B356 -> 0.0994 | D11: =Datasets!C356 -> 0.0998 | E11: =Datasets!D356 -> 0.1002 | F11: =Datasets!E356 -> 0.1005 | G11: =Datasets!F356 -> 0.1007 | H11: =Datasets!G356 -> 0.1005 | I11: =Datasets!H356 -> 0.1004 | J11: =Datasets!I356 -> 0.1002 | ... CX11: =Datasets!CW356 -> 0.1049
A12: ET00 | B12: Transportation | C12: =Datasets!B357 -> 0.2387 | D12: =Datasets!C357 -> 0.2522 | E12: =Datasets!D357 -> 0.2527 | F12: =Datasets!E357 -> 0.2596 | G12: =Datasets!F357 -> 0.2659 | H12: =Datasets!G357 -> 0.2693 | I12: =Datasets!H357 -> 0.269 | J12: =Datasets!I357 -> 0.2621 | ... CX12: =Datasets!CW357 -> 0.1869
A13: EO00 | B13: Other equipment | C13: =Datasets!B358 -> 0.1324 | D13: =Datasets!C358 -> 0.133 | E13: =Datasets!D358 -> 0.1329 | F13: =Datasets!E358 -> 0.1327 | G13: =Datasets!F358 -> 0.1326 | H13: =Datasets!G358 -> 0.1324 | I13: =Datasets!H358 -> 0.1321 | J13: =Datasets!I358 -> 0.1319 | ... CX13: =Datasets!CW358 -> 0.1347
A14: ST00 | B14: Structures | C14: =Datasets!B359 -> 0.0251 | D14: =Datasets!C359 -> 0.0251 | E14: =Datasets!D359 -> 0.0252 | F14: =Datasets!E359 -> 0.0252 | G14: =Datasets!F359 -> 0.0252 | H14: =Datasets!G359 -> 0.0252 | I14: =Datasets!H359 -> 0.0252 | J14: =Datasets!I359 -> 0.0252 | ... CX14: =Datasets!CW359 -> 0.0264
A15: SCHC | B15: Commercial and healthcare | C15: =Datasets!B360 -> 0.0251 | D15: =Datasets!C360 -> 0.0251 | E15: =Datasets!D360 -> 0.0252 | F15: =Datasets!E360 -> 0.0252 | G15: =Datasets!F360 -> 0.0252 | H15: =Datasets!G360 -> 0.0252 | I15: =Datasets!H360 -> 0.0252 | J15: =Datasets!I360 -> 0.0252 | ... CX15: =Datasets!CW360 -> 0.026
A16: IP00 | B16: Intellectual property products | C16: =Datasets!B361 -> 0.16 | D16: =Datasets!C361 -> 0.16 | E16: =Datasets!D361 -> 0.16 | F16: =Datasets!E361 -> 0.16 | G16: =Datasets!F361 -> 0.16 | H16: =Datasets!G361 -> 0.16 | I16: =Datasets!H361 -> 0.16 | J16: =Datasets!I361 -> 0.16 | ... CX16: =Datasets!CW361 -> 0.3237

Sheet 4810
A1: 4810 - Air Transportation
A2: Implied Depreciation Rates for Private Nonresidential Fixed Assets
A3: Updated September 26, 2025
A5: Asset Codes | B5: NIPA Asset Types | C5: 1925 | D5: 1926 | E5: 1927 | F5: 1928 | G5: 1929 | H5: 1930 | I5: 1931 | J5: 1932 | K5: 1933 | L5: 1934 | M5: 1935 | N5: 1936 | O5: 1937 | P5: 1938 | Q5: 1939 | R5: 1940 | S5: 1941 | T5: 1942 | U5: 1943 | V5: 1944 | W5: 1945 | X5: 1946 | Y5: 1947 | Z5: 1948 | AA5: 1949 | AB5: 1950 | AC5: 1951 | AD5: 1952 | AE5: 1953 | AF5: 1954 | AG5: 1955 | AH5: 1956 | AI5: 1957 | AJ5: 1958 | AK5: 1959 | AL5: 1960 | AM5: 1961 | AN5: 1962 | AO5: 1963 | AP5: 1964 | AQ5: 1965 | AR5: 1966 | AS5: 1967 | AT5: 1968 | AU5: 1969 | AV5: 1970 | AW5: 1971 | AX5: 1972 | AY5: 1973 | AZ5: 1974 | BA5: 1975 | BB5: 1976 | BC5: 1977 | BD5: 1978 | BE5: 1979 | BF5: 1980 | BG5: 1981 | BH5: 1982 | BI5: 1983 | BJ5: 1984 | BK5: 1985 | BL5: 1986 | BM5: 1987 | BN5: 1988 | BO5: 1989 | BP5: 1990 | BQ5: 1991 | BR5: 1992 | BS5: 1993 | BT5: 1994 | BU5: 1995 | BV5: 1996 | BW5: 1997 | BX5: 1998 | BY5: 1999 | BZ5: 2000 | CA5: 2001 | CB5: 2002 | CC5: 2003 | CD5: 2004 | CE5: 2005 | CF5: 2006 | CG5: 2007 | CH5: 2008 | CI5: 2009 | CJ5: 2010 | CK5: 2011 | CL5: 2012 | CM5: 2013 | CN5: 2014 | CO5: 2015 | CP5: 2016 | CQ5: 2017 | CR5: 2018 | CS5: 2019 | CT5: 2020 | CU5: 2021 | CV5: 2022 | CW5: 2023 | CX5: 2024
A7: ES00 | B7: Equipment, structures, and intellectual property products | C7: =Datasets!B362 -> 0.1515 | D7: =Datasets!C362 -> 0.1555 | E7: =Datasets!D362 -> 0.143 | F7: =Datasets!E362 -> 0.1306 | G7: =Datasets!F362 -> 0.1104 | H7: =Datasets!G362 -> 0.096 | I7: =Datasets!H362 -> 0.0879 | J7: =Datasets!I362 -> 0.0823 | ... CX7: =Datasets!CW362 -> 0.065
A8: EQ00 | B8: Equipment | C8: =Datasets!B363 -> 0.1742 | D8: =Datasets!C363 -> 0.1736 | E8: =Datasets!D363 -> 0.1554 | F8: =Datasets!E363 -> 0.1378 | G8: =Datasets!F363 -> 0.1263 | H8: =Datasets!G363 -> 0.1219 | I8: =Datasets!H363 -> 0.1205 | J8: =Datasets!I363 -> 0.1198 | ... CX8: =Datasets!CW363 -> 0.0723
A9: EP00 | B9: Information | C9: =Datasets!B364 -> 0 | D9: =Datasets!C364 -> 0 | E9: =Datasets!D364 -> 0 | F9: =Datasets!E364 -> 0 | G9: =Datasets!F364 -> 0 | H9: =Datasets!G364 -> 0 | I9: =Datasets!H364 -> 0 | J9: =Datasets!I364 -> 0 | ... CX9: =Datasets!CW364 -> 0.2045
A10: EP11 | B10: Computers | C10: =Datasets!B365 -> 0 | D10: =Datasets!C365 -> 0 | E10: =Datasets!D365 -> 0 | F10: =Datasets!E365 -> 0 | G10: =Datasets!F365 -> 0 | H10: =Datasets!G365 -> 0 | I10: =Datasets!H365 -> 0 | J10: =Datasets!I365 -> 0 | ... CX10: =Datasets!CW365 -> 0.3215
A11: EI00 | B11: Industrial | C11: =Datasets!B366 -> 0 | D11: =Datasets!C366 -> 0 | E11: =Datasets!D366 -> 0 | F11: =Datasets!E366 -> 0 | G11: =Datasets!F366 -> 0 | H11: =Datasets!G366 -> 0 | I11: =Datasets!H366 -> 0 | J11: =Datasets!I366 -> 0 | ... CX11: =Datasets!CW366 -> 0.0885
A12: ET00 | B12: Transportation | C12: =Datasets!B367 -> 0.1819 | D12: =Datasets!C367 -> 0.1813 | E12: =Datasets!D367 -> 0.1608 | F12: =Datasets!E367 -> 0.1399 | G12: =Datasets!F367 -> 0.1269 | H12: =Datasets!G367 -> 0.1222 | I12: =Datasets!H367 -> 0.1207 | J12: =Datasets!I367 -> 0.1199 | ... CX12: =Datasets!CW367 -> 0.0667
A13: EO00 | B13: Other equipment | C13: =Datasets!B368 -> 0.1179 | D13: =Datasets!C368 -> 0.1179 | E13: =Datasets!D368 -> 0.1179 | F13: =Datasets!E368 -> 0.1179 | G13: =Datasets!F368 -> 0.1179 | H13: =Datasets!G368 -> 0.1179 | I13: =Datasets!H368 -> 0.1179 | J13: =Datasets!I368 -> 0.1179 | ... CX13: =Datasets!CW368 -> 0.1468
A14: ST00 | B14: Structures | C14: =Datasets!B369 -> 0.0236 | D14: =Datasets!C369 -> 0.0236 | E14: =Datasets!D369 -> 0.0236 | F14: =Datasets!E369 -> 0.0236 | G14: =Datasets!F369 -> 0.0237 | H14: =Datasets!G369 -> 0.0237 | I14: =Datasets!H369 -> 0.0237 | J14: =Datasets!I369 -> 0.0237 | ... CX14: =Datasets!CW369 -> 0.024
A15: SCHC | B15: Commercial and healthcare | C15: =Datasets!B370 -> 0 | D15: =Datasets!C370 -> 0 | E15: =Datasets!D370 -> 0 | F15: =Datasets!E370 -> 0 | G15: =Datasets!F370 -> 0 | H15: =Datasets!G370 -> 0 | I15: =Datasets!H370 -> 0 | J15: =Datasets!I370 -> 0 | ... CX15: =Datasets!CW370 -> 0.0238
A16: IP00 | B16: Intellectual property products | C16: =Datasets!B371 -> 0.16 | D16: =Datasets!C371 -> 0.16 | E16: =Datasets!D371 -> 0.16 | F16: =Datasets!E371 -> 0.16 | G16: =Datasets!F371 -> 0.16 | H16: =Datasets!G371 -> 0.16 | I16: =Datasets!H371 -> 0.16 | J16: =Datasets!I371 -> 0.16 | ... CX16: =Datasets!CW371 -> 0.3686

Sheet 4820
A1: 4820 - Rail Transportation
A2: Implied Depreciation Rates for Private Nonresidential Fixed Assets
A3: Updated September 26, 2025
A5: Asset Codes | B5: NIPA Asset Types | C5: 1925 | D5: 1926 | E5: 1927 | F5: 1928 | G5: 1929 | H5: 1930 | I5: 1931 | J5: 1932 | K5: 1933 | L5: 1934 | M5: 1935 | N5: 1936 | O5: 1937 | P5: 1938 | Q5: 1939 | R5: 1940 | S5: 1941 | T5: 1942 | U5: 1943 | V5: 1944 | W5: 1945 | X5: 1946 | Y5: 1947 | Z5: 1948 | AA5: 1949 | AB5: 1950 | AC5: 1951 | AD5: 1952 | AE5: 1953 | AF5: 1954 | AG5: 1955 | AH5: 1956 | AI5: 1957 | AJ5: 1958 | AK5: 1959 | AL5: 1960 | AM5: 1961 | AN5: 1962 | AO5: 1963 | AP5: 1964 | AQ5: 1965 | AR5: 1966 | AS5: 1967 | AT5: 1968 | AU5: 1969 | AV5: 1970 | AW5: 1971 | AX5: 1972 | AY5: 1973 | AZ5: 1974 | BA5: 1975 | BB5: 1976 | BC5: 1977 | BD5: 1978 | BE5: 1979 | BF5: 1980 | BG5: 1981 | BH5: 1982 | BI5: 1983 | BJ5: 1984 | BK5: 1985 | BL5: 1986 | BM5: 1987 | BN5: 1988 | BO5: 1989 | BP5: 1990 | BQ5: 1991 | BR5: 1992 | BS5: 1993 | BT5: 1994 | BU5: 1995 | BV5: 1996 | BW5: 1997 | BX5: 1998 | BY5: 1999 | BZ5: 2000 | CA5: 2001 | CB5: 2002 | CC5: 2003 | CD5: 2004 | CE5: 2005 | CF5: 2006 | CG5: 2007 | CH5: 2008 | CI5: 2009 | CJ5: 2010 | CK5: 2011 | CL5: 2012 | CM5: 2013 | CN5: 2014 | CO5: 2015 | CP5: 2016 | CQ5: 2017 | CR5: 2018 | CS5: 2019 | CT5: 2020 | CU5: 2021 | CV5: 2022 | CW5: 2023 | CX5: 2024
A7: ES00 | B7: Equipment, structures, and intellectual property products | C7: =Datasets!B372 -> 0.0283 | D7: =Datasets!C372 -> 0.0282 | E7: =Datasets!D372 -> 0.028 | F7: =Datasets!E372 -> 0.0278 | G7: =Datasets!F372 -> 0.0276 | H7: =Datasets!G372 -> 0.0274 | I7: =Datasets!H372 -> 0.0272 | J7: =Datasets!I372 -> 0.027 | ... CX7: =Datasets!CW372 -> 0.0314
A8: EQ00 | B8: Equipment | C8: =Datasets!B373 -> 0.0592 | D8: =Datasets!C373 -> 0.0592 | E8: =Datasets!D373 -> 0.0592 | F8: =Datasets!E373 -> 0.0591 | G8: =Datasets!F373 -> 0.0591 | H8: =Datasets!G373 -> 0.0591 | I8: =Datasets!H373 -> 0.0591 | J8: =Datasets!I373 -> 0.0591 | ... CX8: =Datasets!CW373 -> 0.0646
A9: EP00 | B9: Information | C9: =Datasets!B374 -> 0 | D9: =Datasets!C374 -> 0 | E9: =Datasets!D374 -> 0.11 | F9: =Datasets!E374 -> 0.11 | G9: =Datasets!F374 -> 0.11 | H9: =Datasets!G374 -> 0.11 | I9: =Datasets!H374 -> 0.11 | J9: =Datasets!I374 -> 0.11 | ... CX9: =Datasets!CW374 -> 0.1558
A10: EP11 | B10: Computers | C10: =Datasets!B375 -> 0 | D10: =Datasets!C375 -> 0 | E10: =Datasets!D375 -> 0 | F10: =Datasets!E375 -> 0 | G10: =Datasets!F375 -> 0 | H10: =Datasets!G375 -> 0 | I10: =Datasets!H375 -> 0 | J10: =Datasets!I375 -> 0 | ... CX10: =Datasets!CW375 -> 0.329
A11: EI00 | B11: Industrial | C11: =Datasets!B376 -> 0.05 | D11: =Datasets!C376 -> 0.05 | E11: =Datasets!D376 -> 0.05 | F11: =Datasets!E376 -> 0.05 | G11: =Datasets!F376 -> 0.05 | H11: =Datasets!G376 -> 0.05 | I11: =Datasets!H376 -> 0.05 | J11: =Datasets!I376 -> 0.05 | ... CX11: =Datasets!CW376 -> 0.0773
A12: ET00 | B12: Transportation | C12: =Datasets!B377 -> 0.0592 | D12: =Datasets!C377 -> 0.0592 | E12: =Datasets!D377 -> 0.0592 | F12: =Datasets!E377 -> 0.0591 | G12: =Datasets!F377 -> 0.0591 | H12: =Datasets!G377 -> 0.0591 | I12: =Datasets!H377 -> 0.0591 | J12: =Datasets!I377 -> 0.0591 | ... CX12: =Datasets!CW377 -> 0.0604
A13: EO00 | B13: Other equipment | C13: =Datasets!B378 -> 0.1179 | D13: =Datasets!C378 -> 0.1179 | E13: =Datasets!D378 -> 0.1179 | F13: =Datasets!E378 -> 0.1179 | G13: =Datasets!F378 -> 0.1179 | H13: =Datasets!G378 -> 0.1179 | I13: =Datasets!H378 -> 0.1179 | J13: =Datasets!I378 -> 0.1179 | ... CX13: =Datasets!CW378 -> 0.1463
A14: ST00 | B14: Structures | C14: =Datasets!B379 -> 0.0201 | D14: =Datasets!C379 -> 0.0201 | E14: =Datasets!D379 -> 0.0201 | F14: =Datasets!E379 -> 0.0201 | G14: =Datasets!F379 -> 0.0202 | H14: =Datasets!G379 -> 0.0202 | I14: =Datasets!H379 -> 0.0202 | J14: =Datasets!I379 -> 0.0202 | ... CX14: =Datasets!CW379 -> 0.0227
A15: SCHC | B15: Commercial and healthcare | C15: =Datasets!B380 -> 0 | D15: =Datasets!C380 -> 0 | E15: =Datasets!D380 -> 0 | F15: =Datasets!E380 -> 0 | G15: =Datasets!F380 -> 0 | H15: =Datasets!G380 -> 0 | I15: =Datasets!H380 -> 0 | J15: =Datasets!I380 -> 0 | ... CX15: =Datasets!CW380 -> 0.0248
A16: IP00 | B16: Intellectual property products | C16: =Datasets!B381 -> 0.16 | D16: =Datasets!C381 -> 0.16 | E16: =Datasets!D381 -> 0.16 | F16: =Datasets!E381 -> 0.16 | G16: =Datasets!F381 -> 0.16 | H16: =Datasets!G381 -> 0.16 | I16: =Datasets!H381 -> 0.16 | J16: =Datasets!I381 -> 0.16 | ... CX16: =Datasets!CW381 -> 0.3486

Sheet 4830
A1: 4830 - Water Transportation
A2: Implied Depreciation Rates for Private Nonresidential Fixed Assets
A3: Updated September 26, 2025
A5: Asset Codes | B5: NIPA Asset Types | C5: 1925 | D5: 1926 | E5: 1927 | F5: 1928 | G5: 1929 | H5: 1930 | I5: 1931 | J5: 1932 | K5: 1933 | L5: 1934 | M5: 1935 | N5: 1936 | O5: 1937 | P5: 1938 | Q5: 1939 | R5: 1940 | S5: 1941 | T5: 1942 | U5: 1943 | V5: 1944 | W5: 1945 | X5: 1946 | Y5: 1947 | Z5: 1948 | AA5: 1949 | AB5: 1950 | AC5: 1951 | AD5: 1952 | AE5: 1953 | AF5: 1954 | AG5: 1955 | AH5: 1956 | AI5: 1957 | AJ5: 1958 | AK5: 1959 | AL5: 1960 | AM5: 1961 | AN5: 1962 | AO5: 1963 | AP5: 1964 | AQ5: 1965 | AR5: 1966 | AS5: 1967 | AT5: 1968 | AU5: 1969 | AV5: 1970 | AW5: 1971 | AX5: 1972 | AY5: 1973 | AZ5: 1974 | BA5: 1975 | BB5: 1976 | BC5: 1977 | BD5: 1978 | BE5: 1979 | BF5: 1980 | BG5: 1981 | BH5: 1982 | BI5: 1983 | BJ5: 1984 | BK5: 1985 | BL5: 1986 | BM5: 1987 | BN5: 1988 | BO5: 1989 | BP5: 1990 | BQ5: 1991 | BR5: 1992 | BS5: 1993 | BT5: 1994 | BU5: 1995 | BV5: 1996 | BW5: 1997 | BX5: 1998 | BY5: 1999 | BZ5: 2000 | CA5: 2001 | CB5: 2002 | CC5: 2003 | CD5: 2004 | CE5: 2005 | CF5: 2006 | CG5: 2007 | CH5: 2008 | CI5: 2009 | CJ5: 2010 | CK5: 2011 | CL5: 2012 | CM5: 2013 | CN5: 2014 | CO5: 2015 | CP5: 2016 | CQ5: 2017 | CR5: 2018 | CS5: 2019 | CT5: 2020 | CU5: 2021 | CV5: 2022 | CW5: 2023 | CX5: 2024
A7: ES00 | B7: Equipment, structures, and intellectual property products | C7: =Datasets!B382 -> 0.0633 | D7: =Datasets!C382 -> 0.0645 | E7: =Datasets!D382 -> 0.0648 | F7: =Datasets!E382 -> 0.0654 | G7: =Datasets!F382 -> 0.0659 | H7: =Datasets!G382 -> 0.066 | I7: =Datasets!H382 -> 0.0658 | J7: =Datasets!I382 -> 0.0657 | ... CX7: =Datasets!CW382 -> 0.0998
A8: EQ00 | B8: Equipment | C8: =Datasets!B383 -> 0.0633 | D8: =Datasets!C383 -> 0.0645 | E8: =Datasets!D383 -> 0.0648 | F8: =Datasets!E383 -> 0.0654 | G8: =Datasets!F383 -> 0.0659 | H8: =Datasets!G383 -> 0.066 | I8: =Datasets!H383 -> 0.0658 | J8: =Datasets!I383 -> 0.0657 | ... CX8: =Datasets!CW383 -> 0.0661
A9: EP00 | B9: Information | C9: =Datasets!B384 -> 0 | D9: =Datasets!C384 -> 0 | E9: =Datasets!D384 -> 0 | F9: =Datasets!E384 -> 0 | G9: =Datasets!F384 -> 0 | H9: =Datasets!G384 -> 0 | I9: =Datasets!H384 -> 0 | J9: =Datasets!I384 -> 0 | ... CX9: =Datasets!CW384 -> 0.1611
A10: EP11 | B10: Computers | C10: =Datasets!B385 -> 0 | D10: =Datasets!C385 -> 0 | E10: =Datasets!D385 -> 0 | F10: =Datasets!E385 -> 0 | G10: =Datasets!F385 -> 0 | H10: =Datasets!G385 -> 0 | I10: =Datasets!H385 -> 0 | J10: =Datasets!I385 -> 0 | ... CX10: =Datasets!CW385 -> 0.319
A11: EI00 | B11: Industrial | C11: =Datasets!B386 -> 0 | D11: =Datasets!C386 -> 0 | E11: =Datasets!D386 -> 0 | F11: =Datasets!E386 -> 0 | G11: =Datasets!F386 -> 0 | H11: =Datasets!G386 -> 0 | I11: =Datasets!H386 -> 0 | J11: =Datasets!I386 -> 0 | ... CX11: =Datasets!CW386 -> 0.0981
A12: ET00 | B12: Transportation | C12: =Datasets!B387 -> 0.0623 | D12: =Datasets!C387 -> 0.0633 | E12: =Datasets!D387 -> 0.0635 | F12: =Datasets!E387 -> 0.0638 | G12: =Datasets!F387 -> 0.064 | H12: =Datasets!G387 -> 0.0642 | I12: =Datasets!H387 -> 0.0642 | J12: =Datasets!I387 -> 0.0641 | ... CX12: =Datasets!CW387 -> 0.0626
A13: EO00 | B13: Other equipment | C13: =Datasets!B388 -> 0.1179 | D13: =Datasets!C388 -> 0.1179 | E13: =Datasets!D388 -> 0.1179 | F13: =Datasets!E388 -> 0.1179 | G13: =Datasets!F388 -> 0.1179 | H13: =Datasets!G388 -> 0.1179 | I13: =Datasets!H388 -> 0.1179 | J13: =Datasets!I388 -> 0.1179 | ... CX13: =Datasets!CW388 -> 0.1449
A14: ST00 | B14: Structures | C14: =Datasets!B389 -> 0 | D14: =Datasets!C389 -> 0 | E14: =Datasets!D389 -> 0 | F14: =Datasets!E389 -> 0 | G14: =Datasets!F389 -> 0 | H14: =Datasets!G389 -> 0 | I14: =Datasets!H389 -> 0 | J14: =Datasets!I389 -> 0 | ... CX14: =Datasets!CW389 -> 0.0248
A15: SCHC | B15: Commercial and healthcare | C15: =Datasets!B390 -> 0 | D15: =Datasets!C390 -> 0 | E15: =Datasets!D390 -> 0 | F15: =Datasets!E390 -> 0 | G15: =Datasets!F390 -> 0 | H15: =Datasets!G390 -> 0 | I15: =Datasets!H390 -> 0 | J15: =Datasets!I390 -> 0 | ... CX15: =Datasets!CW390 -> 0.0244
A16: IP00 | B16: Intellectual property products | C16: =Datasets!B391 -> 0.16 | D16: =Datasets!C391 -> 0.16 | E16: =Datasets!D391 -> 0.16 | F16: =Datasets!E391 -> 0.16 | G16: =Datasets!F391 -> 0.16 | H16: =Datasets!G391 -> 0.16 | I16: =Datasets!H391 -> 0.16 | J16: =Datasets!I391 -> 0.16 | ... CX16: =Datasets!CW391 -> 0.4199

Sheet 4840
A1: 4840 - Truck Transportation
A2: Implied Depreciation Rates for Private Nonresidential Fixed Assets
A3: Updated September 26, 2025
A5: Asset Codes | B5: NIPA Asset Types | C5: 1925 | D5: 1926 | E5: 1927 | F5: 1928 | G5: 1929 | H5: 1930 | I5: 1931 | J5: 1932 | K5: 1933 | L5: 1934 | M5: 1935 | N5: 1936 | O5: 1937 | P5: 1938 | Q5: 1939 | R5: 1940 | S5: 1941 | T5: 1942 | U5: 1943 | V5: 1944 | W5: 1945 | X5: 1946 | Y5: 1947 | Z5: 1948 | AA5: 1949 | AB5: 1950 | AC5: 1951 | AD5: 1952 | AE5: 1953 | AF5: 1954 | AG5: 1955 | AH5: 1956 | AI5: 1957 | AJ5: 1958 | AK5: 1959 | AL5: 1960 | AM5: 1961 | AN5: 1962 | AO5: 1963 | AP5: 1964 | AQ5: 1965 | AR5: 1966 | AS5: 1967 | AT5: 1968 | AU5: 1969 | AV5: 1970 | AW5: 1971 | AX5: 1972 | AY5: 1973 | AZ5: 1974 | BA5: 1975 | BB5: 1976 | BC5: 1977 | BD5: 1978 | BE5: 1979 | BF5: 1980 | BG5: 1981 | BH5: 1982 | BI5: 1983 | BJ5: 1984 | BK5: 1985 | BL5: 1986 | BM5: 1987 | BN5: 1988 | BO5: 1989 | BP5: 1990 | BQ5: 1991 | BR5: 1992 | BS5: 1993 | BT5: 1994 | BU5: 1995 | BV5: 1996 | BW5: 1997 | BX5: 1998 | BY5: 1999 | BZ5: 2000 | CA5: 2001 | CB5: 2002 | CC5: 2003 | CD5: 2004 | CE5: 2005 | CF5: 2006 | CG5: 2007 | CH5: 2008 | CI5: 2009 | CJ5: 2010 | CK5: 2011 | CL5: 2012 | CM5: 2013 | CN5: 2014 | CO5: 2015 | CP5: 2016 | CQ5: 2017 | CR5: 2018 | CS5: 2019 | CT5: 2020 | CU5: 2021 | CV5: 2022 | CW5: 2023 | CX5: 2024
A7: ES00 | B7: Equipment, structures, and intellectual property products | C7: =Datasets!B392 -> 0.1621 | D7: =Datasets!C392 -> 0.1624 | E7: =Datasets!D392 -> 0.1616 | F7: =Datasets!E392 -> 0.1606 | G7: =Datasets!F392 -> 0.1593 | H7: =Datasets!G392 -> 0.1577 | I7: =Datasets!H392 -> 0.1562 | J7: =Datasets!I392 -> 0.1545 | ... CX7: =Datasets!CW392 -> 0.1505
A8: EQ00 | B8: Equipment | C8: =Datasets!B393 -> 0.169 | D8: =Datasets!C393 -> 0.1694 | E8: =Datasets!D393 -> 0.1689 | F8: =Datasets!E393 -> 0.1683 | G8: =Datasets!F393 -> 0.167 | H8: =Datasets!G393 -> 0.1656 | I8: =Datasets!H393 -> 0.1644 | J8: =Datasets!I393 -> 0.1632 | ... CX8: =Datasets!CW393 -> 0.1677
A9: EP00 | B9: Information | C9: =Datasets!B394 -> 0 | D9: =Datasets!C394 -> 0 | E9: =Datasets!D394 -> 0 | F9: =Datasets!E394 -> 0 | G9: =Datasets!F394 -> 0 | H9: =Datasets!G394 -> 0 | I9: =Datasets!H394 -> 0 | J9: =Datasets!I394 -> 0 | ... CX9: =Datasets!CW394 -> 0.1647
A10: EP11 | B10: Computers | C10: =Datasets!B395 -> 0 | D10: =Datasets!C395 -> 0 | E10: =Datasets!D395 -> 0 | F10: =Datasets!E395 -> 0 | G10: =Datasets!F395 -> 0 | H10: =Datasets!G395 -> 0 | I10: =Datasets!H395 -> 0 | J10: =Datasets!I395 -> 0 | ... CX10: =Datasets!CW395 -> 0.3226
A11: EI00 | B11: Industrial | C11: =Datasets!B396 -> 0.1072 | D11: =Datasets!C396 -> 0.1072 | E11: =Datasets!D396 -> 0.1072 | F11: =Datasets!E396 -> 0.1072 | G11: =Datasets!F396 -> 0.1072 | H11: =Datasets!G396 -> 0.1072 | I11: =Datasets!H396 -> 0.1072 | J11: =Datasets!I396 -> 0.1072 | ... CX11: =Datasets!CW396 -> 0.1063
A12: ET00 | B12: Transportation | C12: =Datasets!B397 -> 0.1737 | D12: =Datasets!C397 -> 0.1746 | E12: =Datasets!D397 -> 0.1747 | F12: =Datasets!E397 -> 0.1751 | G12: =Datasets!F397 -> 0.1753 | H12: =Datasets!G397 -> 0.1754 | I12: =Datasets!H397 -> 0.1755 | J12: =Datasets!I397 -> 0.1754 | ... CX12: =Datasets!CW397 -> 0.1731
A13: EO00 | B13: Other equipment | C13: =Datasets!B398 -> 0.1642 | D13: =Datasets!C398 -> 0.1644 | E13: =Datasets!D398 -> 0.1636 | F13: =Datasets!E398 -> 0.1623 | G13: =Datasets!F398 -> 0.1566 | H13: =Datasets!G398 -> 0.1485 | I13: =Datasets!H398 -> 0.1442 | J13: =Datasets!I398 -> 0.1421 | ... CX13: =Datasets!CW398 -> 0.149
A14: ST00 | B14: Structures | C14: =Datasets!B399 -> 0.0231 | D14: =Datasets!C399 -> 0.0232 | E14: =Datasets!D399 -> 0.0232 | F14: =Datasets!E399 -> 0.0233 | G14: =Datasets!F399 -> 0.0233 | H14: =Datasets!G399 -> 0.0234 | I14: =Datasets!H399 -> 0.0234 | J14: =Datasets!I399 -> 0.0235 | ... CX14: =Datasets!CW399 -> 0.027
A15: SCHC | B15: Commercial and healthcare | C15: =Datasets!B400 -> 0.0231 | D15: =Datasets!C400 -> 0.0232 | E15: =Datasets!D400 -> 0.0232 | F15: =Datasets!E400 -> 0.0233 | G15: =Datasets!F400 -> 0.0233 | H15: =Datasets!G400 -> 0.0234 | I15: =Datasets!H400 -> 0.0234 | J15: =Datasets!I400 -> 0.0235 | ... CX15: =Datasets!CW400 -> 0.0243
A16: IP00 | B16: Intellectual property products | C16: =Datasets!B401 -> 0.16 | D16: =Datasets!C401 -> 0.16 | E16: =Datasets!D401 -> 0.16 | F16: =Datasets!E401 -> 0.16 | G16: =Datasets!F401 -> 0.16 | H16: =Datasets!G401 -> 0.16 | I16: =Datasets!H401 -> 0.16 | J16: =Datasets!I401 -> 0.16 | ... CX16: =Datasets!CW401 -> 0.3809

Sheet 4850
A1: 4850 - Transit and Ground Passenger Transportation
A2: Implied Depreciation Rates for Private Nonresidential Fixed Assets
A3: Updated September 26, 2025
A5: Asset Codes | B5: NIPA Asset Types | C5: 1925 | D5: 1926 | E5: 1927 | F5: 1928 | G5: 1929 | H5: 1930 | I5: 1931 | J5: 1932 | K5: 1933 | L5: 1934 | M5: 1935 | N5: 1936 | O5: 1937 | P5: 1938 | Q5: 1939 | R5: 1940 | S5: 1941 | T5: 1942 | U5: 1943 | V5: 1944 | W5: 1945 | X5: 1946 | Y5: 1947 | Z5: 1948 | AA5: 1949 | AB5: 1950 | AC5: 1951 | AD5: 1952 | AE5: 1953 | AF5: 1954 | AG5: 1955 | AH5: 1956 | AI5: 1957 | AJ5: 1958 | AK5: 1959 | AL5: 1960 | AM5: 1961 | AN5: 1962 | AO5: 1963 | AP5: 1964 | AQ5: 1965 | AR5: 1966 | AS5: 1967 | AT5: 1968 | AU5: 1969 | AV5: 1970 | AW5: 1971 | AX5: 1972 | AY5: 1973 | AZ5: 1974 | BA5: 1975 | BB5: 1976 | BC5: 1977 | BD5: 1978 | BE5: 1979 | BF5: 1980 | BG5: 1981 | BH5: 1982 | BI5: 1983 | BJ5: 1984 | BK5: 1985 | BL5: 1986 | BM5: 1987 | BN5: 1988 | BO5: 1989 | BP5: 1990 | BQ5: 1991 | BR5: 1992 | BS5: 1993 | BT5: 1994 | BU5: 1995 | BV5: 1996 | BW5: 1997 | BX5: 1998 | BY5: 1999 | BZ5: 2000 | CA5: 2001 | CB5: 2002 | CC5: 2003 | CD5: 2004 | CE5: 2005 | CF5: 2006 | CG5: 2007 | CH5: 2008 | CI5: 2009 | CJ5: 2010 | CK5: 2011 | CL5: 2012 | CM5: 2013 | CN5: 2014 | CO5: 2015 | CP5: 2016 | CQ5: 2017 | CR5: 2018 | CS5: 2019 | CT5: 2020 | CU5: 2021 | CV5: 2022 | CW5: 2023 | CX5: 2024
A7: ES00 | B7: Equipment, structures, and intellectual property products | C7: =Datasets!B402 -> 0.0261 | D7: =Datasets!C402 -> 0.0267 | E7: =Datasets!D402 -> 0.0269 | F7: =Datasets!E402 -> 0.0269 | G7: =Datasets!F402 -> 0.0269 | H7: =Datasets!G402 -> 0.0269 | I7: =Datasets!H402 -> 0.027 | J7: =Datasets!I402 -> 0.027 | ... CX7: =Datasets!CW402 -> 0.0996
A8: EQ00 | B8: Equipment | C8: =Datasets!B403 -> 0.112 | D8: =Datasets!C403 -> 0.1122 | E8: =Datasets!D403 -> 0.1109 | F8: =Datasets!E403 -> 0.1102 | G8: =Datasets!F403 -> 0.1094 | H8: =Datasets!G403 -> 0.1085 | I8: =Datasets!H403 -> 0.108 | J8: =Datasets!I403 -> 0.1075 | ... CX8: =Datasets!CW403 -> 0.1491
A9: EP00 | B9: Information | C9: =Datasets!B404 -> 0 | D9: =Datasets!C404 -> 0 | E9: =Datasets!D404 -> 0.11 | F9: =Datasets!E404 -> 0.11 | G9: =Datasets!F404 -> 0.11 | H9: =Datasets!G404 -> 0.11 | I9: =Datasets!H404 -> 0.11 | J9: =Datasets!I404 -> 0.11 | ... CX9: =Datasets!CW404 -> 0.1466
A10: EP11 | B10: Computers | C10: =Datasets!B405 -> 0 | D10: =Datasets!C405 -> 0 | E10: =Datasets!D405 -> 0 | F10: =Datasets!E405 -> 0 | G10: =Datasets!F405 -> 0 | H10: =Datasets!G405 -> 0 | I10: =Datasets!H405 -> 0 | J10: =Datasets!I405 -> 0 | ... CX10: =Datasets!CW405 -> 0.3375
A11: EI00 | B11: Industrial | C11: =Datasets!B406 -> 0.1072 | D11: =Datasets!C406 -> 0.1072 | E11: =Datasets!D406 -> 0.1072 | F11: =Datasets!E406 -> 0.1072 | G11: =Datasets!F406 -> 0.1072 | H11: =Datasets!G406 -> 0.1072 | I11: =Datasets!H406 -> 0.1072 | J11: =Datasets!I406 -> 0.1072 | ... CX11: =Datasets!CW406 -> 0.0702
A12: ET00 | B12: Transportation | C12: =Datasets!B407 -> 0.1402 | D12: =Datasets!C407 -> 0.1472 | E12: =Datasets!D407 -> 0.1375 | F12: =Datasets!E407 -> 0.1292 | G12: =Datasets!F407 -> 0.1214 | H12: =Datasets!G407 -> 0.115 | I12: =Datasets!H407 -> 0.1123 | J12: =Datasets!I407 -> 0.1092 | ... CX12: =Datasets!CW407 -> 0.1508
A13: EO00 | B13: Other equipment | C13: =Datasets!B408 -> 0.1834 | D13: =Datasets!C408 -> 0.1834 | E13: =Datasets!D408 -> 0.1834 | F13: =Datasets!E408 -> 0.1834 | G13: =Datasets!F408 -> 0.1834 | H13: =Datasets!G408 -> 0.1834 | I13: =Datasets!H408 -> 0.1834 | J13: =Datasets!I408 -> 0.1834 | ... CX13: =Datasets!CW408 -> 0.147
A14: ST00 | B14: Structures | C14: =Datasets!B409 -> 0.0237 | D14: =Datasets!C409 -> 0.0237 | E14: =Datasets!D409 -> 0.0237 | F14: =Datasets!E409 -> 0.0237 | G14: =Datasets!F409 -> 0.0237 | H14: =Datasets!G409 -> 0.0237 | I14: =Datasets!H409 -> 0.0237 | J14: =Datasets!I409 -> 0.0237 | ... CX14: =Datasets!CW409 -> 0.0246
A15: SCHC | B15: Commercial and healthcare | C15: =Datasets!B410 -> 0 | D15: =Datasets!C410 -> 0 | E15: =Datasets!D410 -> 0 | F15: =Datasets!E410 -> 0 | G15: =Datasets!F410 -> 0 | H15: =Datasets!G410 -> 0 | I15: =Datasets!H410 -> 0 | J15: =Datasets!I410 -> 0 | ... CX15: =Datasets!CW410 -> 0.0255
A16: IP00 | B16: Intellectual property products | C16: =Datasets!B411 -> 0.16 | D16: =Datasets!C411 -> 0.16 | E16: =Datasets!D411 -> 0.16 | F16: =Datasets!E411 -> 0.16 | G16: =Datasets!F411 -> 0.16 | H16: =Datasets!G411 -> 0.16 | I16: =Datasets!H411 -> 0.16 | J16: =Datasets!I411 -> 0.16 | ... CX16: =Datasets!CW411 -> 0.3792

Sheet 4860
A1: 4860 - Pipeline Transportation
A2: Implied Depreciation Rates for Private Nonresidential Fixed Assets
A3: Updated September 26, 2025
A5: Asset Codes | B5: NIPA Asset Types | C5: 1925 | D5: 1926 | E5: 1927 | F5: 1928 | G5: 1929 | H5: 1930 | I5: 1931 | J5: 1932 | K5: 1933 | L5: 1934 | M5: 1935 | N5: 1936 | O5: 1937 | P5: 1938 | Q5: 1939 | R5: 1940 | S5: 1941 | T5: 1942 | U5: 1943 | V5: 1944 | W5: 1945 | X5: 1946 | Y5: 1947 | Z5: 1948 | AA5: 1949 | AB5: 1950 | AC5: 1951 | AD5: 1952 | AE5: 1953 | AF5: 1954 | AG5: 1955 | AH5: 1956 | AI5: 1957 | AJ5: 1958 | AK5: 1959 | AL5: 1960 | AM5: 1961 | AN5: 1962 | AO5: 1963 | AP5: 1964 | AQ5: 1965 | AR5: 1966 | AS5: 1967 | AT5: 1968 | AU5: 1969 | AV5: 1970 | AW5: 1971 | AX5: 1972 | AY5: 1973 | AZ5: 1974 | BA5: 1975 | BB5: 1976 | BC5: 1977 | BD5: 1978 | BE5: 1979 | BF5: 1980 | BG5: 1981 | BH5: 1982 | BI5: 1983 | BJ5: 1984 | BK5: 1985 | BL5: 1986 | BM5: 1987 | BN5: 1988 | BO5: 1989 | BP5: 1990 | BQ5: 1991 | BR5: 1992 | BS5: 1993 | BT5: 1994 | BU5: 1995 | BV5: 1996 | BW5: 1997 | BX5: 1998 | BY5: 1999 | BZ5: 2000 | CA5: 2001 | CB5: 2002 | CC5: 2003 | CD5: 2004 | CE5: 2005 | CF5: 2006 | CG5: 2007 | CH5: 2008 | CI5: 2009 | CJ5: 2010 | CK5: 2011 | CL5: 2012 | CM5: 2013 | CN5: 2014 | CO5: 2015 | CP5: 2016 | CQ5: 2017 | CR5: 2018 | CS5: 2019 | CT5: 2020 | CU5: 2021 | CV5: 2022 | CW5: 2023 | CX5: 2024
A7: ES00 | B7: Equipment, structures, and intellectual property products | C7: =Datasets!B412 -> 0.0244 | D7: =Datasets!C412 -> 0.0246 | E7: =Datasets!D412 -> 0.0248 | F7: =Datasets!E412 -> 0.0249 | G7: =Datasets!F412 -> 0.025 | H7: =Datasets!G412 -> 0.0251 | I7: =Datasets!H412 -> 0.025 | J7: =Datasets!I412 -> 0.025 | ... CX7: =Datasets!CW412 -> 0.0421
A8: EQ00 | B8: Equipment | C8: =Datasets!B413 -> 0.1207 | D8: =Datasets!C413 -> 0.1269 | E8: =Datasets!D413 -> 0.1262 | F8: =Datasets!E413 -> 0.1262 | G8: =Datasets!F413 -> 0.1262 | H8: =Datasets!G413 -> 0.1263 | I8: =Datasets!H413 -> 0.1261 | J8: =Datasets!I413 -> 0.1251 | ... CX8: =Datasets!CW413 -> 0.1366
A9: EP00 | B9: Information | C9: =Datasets!B414 -> 0.135 | D9: =Datasets!C414 -> 0.135 | E9: =Datasets!D414 -> 0.135 | F9: =Datasets!E414 -> 0.135 | G9: =Datasets!F414 -> 0.135 | H9: =Datasets!G414 -> 0.135 | I9: =Datasets!H414 -> 0.135 | J9: =Datasets!I414 -> 0.135 | ... CX9: =Datasets!CW414 -> 0.1265
A10: EP11 | B10: Computers | C10: =Datasets!B415 -> 0 | D10: =Datasets!C415 -> 0 | E10: =Datasets!D415 -> 0 | F10: =Datasets!E415 -> 0 | G10: =Datasets!F415 -> 0 | H10: =Datasets!G415 -> 0 | I10: =Datasets!H415 -> 0 | J10: =Datasets!I415 -> 0 | ... CX10: =Datasets!CW415 -> 0.336
A11: EI00 | B11: Industrial | C11: =Datasets!B416 -> 0.1009 | D11: =Datasets!C416 -> 0.1013 | E11: =Datasets!D416 -> 0.1017 | F11: =Datasets!E416 -> 0.102 | G11: =Datasets!F416 -> 0.1021 | H11: =Datasets!G416 -> 0.1019 | I11: =Datasets!H416 -> 0.1018 | J11: =Datasets!I416 -> 0.1016 | ... CX11: =Datasets!CW416 -> 0.1057
A12: ET00 | B12: Transportation | C12: =Datasets!B417 -> 0.2387 | D12: =Datasets!C417 -> 0.2522 | E12: =Datasets!D417 -> 0.2527 | F12: =Datasets!E417 -> 0.2596 | G12: =Datasets!F417 -> 0.2659 | H12: =Datasets!G417 -> 0.2693 | I12: =Datasets!H417 -> 0.269 | J12: =Datasets!I417 -> 0.2621 | ... CX12: =Datasets!CW417 -> 0.1196
A13: EO00 | B13: Other equipment | C13: =Datasets!B418 -> 0.1179 | D13: =Datasets!C418 -> 0.1179 | E13: =Datasets!D418 -> 0.1179 | F13: =Datasets!E418 -> 0.1179 | G13: =Datasets!F418 -> 0.1179 | H13: =Datasets!G418 -> 0.1179 | I13: =Datasets!H418 -> 0.1179 | J13: =Datasets!I418 -> 0.1179 | ... CX13: =Datasets!CW418 -> 0.15
A14: ST00 | B14: Structures | C14: =Datasets!B419 -> 0.0237 | D14: =Datasets!C419 -> 0.0237 | E14: =Datasets!D419 -> 0.0237 | F14: =Datasets!E419 -> 0.0237 | G14: =Datasets!F419 -> 0.0237 | H14: =Datasets!G419 -> 0.0237 | I14: =Datasets!H419 -> 0.0237 | J14: =Datasets!I419 -> 0.0237 | ... CX14: =Datasets!CW419 -> 0.0252
A15: SCHC | B15: Commercial and healthcare | C15: =Datasets!B420 -> 0.0247 | D15: =Datasets!C420 -> 0.0247 | E15: =Datasets!D420 -> 0.0247 | F15: =Datasets!E420 -> 0.0247 | G15: =Datasets!F420 -> 0.0247 | H15: =Datasets!G420 -> 0.0247 | I15: =Datasets!H420 -> 0.0247 | J15: =Datasets!I420 -> 0.0247 | ... CX15: =Datasets!CW420 -> 0.0256
A16: IP00 | B16: Intellectual property products | C16: =Datasets!B421 -> 0.16 | D16: =Datasets!C421 -> 0.16 | E16: =Datasets!D421 -> 0.16 | F16: =Datasets!E421 -> 0.16 | G16: =Datasets!F421 -> 0.16 | H16: =Datasets!G421 -> 0.16 | I16: =Datasets!H421 -> 0.16 | J16: =Datasets!I421 -> 0.16 | ... CX16: =Datasets!CW421 -> 0.2769

Sheet 487S
A1: 487S - Other Transportation and Support Activities
A2: Implied Depreciation Rates for Private Nonresidential Fixed Assets
A3: Updated September 26, 2025
A5: Asset Codes | B5: NIPA Asset Types | C5: 1925 | D5: 1926 | E5: 1927 | F5: 1928 | G5: 1929 | H5: 1930 | I5: 1931 | J5: 1932 | K5: 1933 | L5: 1934 | M5: 1935 | N5: 1936 | O5: 1937 | P5: 1938 | Q5: 1939 | R5: 1940 | S5: 1941 | T5: 1942 | U5: 1943 | V5: 1944 | W5: 1945 | X5: 1946 | Y5: 1947 | Z5: 1948 | AA5: 1949 | AB5: 1950 | AC5: 1951 | AD5: 1952 | AE5: 1953 | AF5: 1954 | AG5: 1955 | AH5: 1956 | AI5: 1957 | AJ5: 1958 | AK5: 1959 | AL5: 1960 | AM5: 1961 | AN5: 1962 | AO5: 1963 | AP5: 1964 | AQ5: 1965 | AR5: 1966 | AS5: 1967 | AT5: 1968 | AU5: 1969 | AV5: 1970 | AW5: 1971 | AX5: 1972 | AY5: 1973 | AZ5: 1974 | BA5: 1975 | BB5: 1976 | BC5: 1977 | BD5: 1978 | BE5: 1979 | BF5: 1980 | BG5: 1981 | BH5: 1982 | BI5: 1983 | BJ5: 1984 | BK5: 1985 | BL5: 1986 | BM5: 1987 | BN5: 1988 | BO5: 1989 | BP5: 1990 | BQ5: 1991 | BR5: 1992 | BS5: 1993 | BT5: 1994 | BU5: 1995 | BV5: 1996 | BW5: 1997 | BX5: 1998 | BY5: 1999 | BZ5: 2000 | CA5: 2001 | CB5: 2002 | CC5: 2003 | CD5: 2004 | CE5: 2005 | CF5: 2006 | CG5: 2007 | CH5: 2008 | CI5: 2009 | CJ5: 2010 | CK5: 2011 | CL5: 2012 | CM5: 2013 | CN5: 2014 | CO5: 2015 | CP5: 2016 | CQ5: 2017 | CR5: 2018 | CS5: 2019 | CT5: 2020 | CU5: 2021 | CV5: 2022 | CW5: 2023 | CX5: 2024
A7: ES00 | B7: Equipment, structures, and intellectual property products | C7: =Datasets!B422 -> 0.0355 | D7: =Datasets!C422 -> 0.0365 | E7: =Datasets!D422 -> 0.0369 | F7: =Datasets!E422 -> 0.0372 | G7: =Datasets!F422 -> 0.0376 | H7: =Datasets!G422 -> 0.038 | I7: =Datasets!H422 -> 0.0378 | J7: =Datasets!I422 -> 0.0372 | ... CX7: =Datasets!CW422 -> 0.0936
A8: EQ00 | B8: Equipment | C8: =Datasets!B423 -> 0.0769 | D8: =Datasets!C423 -> 0.0758 | E8: =Datasets!D423 -> 0.0743 | F8: =Datasets!E423 -> 0.0734 | G8: =Datasets!F423 -> 0.0731 | H8: =Datasets!G423 -> 0.0727 | I8: =Datasets!H423 -> 0.0723 | J8: =Datasets!I423 -> 0.0717 | ... CX8: =Datasets!CW423 -> 0.1266
A9: EP00 | B9: Information | C9: =Datasets!B424 -> 0 | D9: =Datasets!C424 -> 0 | E9: =Datasets!D424 -> 0.11 | F9: =Datasets!E424 -> 0.11 | G9: =Datasets!F424 -> 0.11 | H9: =Datasets!G424 -> 0.11 | I9: =Datasets!H424 -> 0.11 | J9: =Datasets!I424 -> 0.11 | ... CX9: =Datasets!CW424 -> 0.1761
A10: EP11 | B10: Computers | C10: =Datasets!B425 -> 0 | D10: =Datasets!C425 -> 0 | E10: =Datasets!D425 -> 0 | F10: =Datasets!E425 -> 0 | G10: =Datasets!F425 -> 0 | H10: =Datasets!G425 -> 0 | I10: =Datasets!H425 -> 0 | J10: =Datasets!I425 -> 0 | ... CX10: =Datasets!CW425 -> 0.3224
A11: EI00 | B11: Industrial | C11: =Datasets!B426 -> 0.1072 | D11: =Datasets!C426 -> 0.1072 | E11: =Datasets!D426 -> 0.1072 | F11: =Datasets!E426 -> 0.1072 | G11: =Datasets!F426 -> 0.1072 | H11: =Datasets!G426 -> 0.1072 | I11: =Datasets!H426 -> 0.1072 | J11: =Datasets!I426 -> 0.1072 | ... CX11: =Datasets!CW426 -> 0.1052
A12: ET00 | B12: Transportation | C12: =Datasets!B427 -> 0.0763 | D12: =Datasets!C427 -> 0.0751 | E12: =Datasets!D427 -> 0.0735 | F12: =Datasets!E427 -> 0.0726 | G12: =Datasets!F427 -> 0.0722 | H12: =Datasets!G427 -> 0.0718 | I12: =Datasets!H427 -> 0.0713 | J12: =Datasets!I427 -> 0.0706 | ... CX12: =Datasets!CW427 -> 0.1184
A13: EO00 | B13: Other equipment | C13: =Datasets!B428 -> 0.1298 | D13: =Datasets!C428 -> 0.1276 | E13: =Datasets!D428 -> 0.1269 | F13: =Datasets!E428 -> 0.1256 | G13: =Datasets!F428 -> 0.1251 | H13: =Datasets!G428 -> 0.1251 | I13: =Datasets!H428 -> 0.125 | J13: =Datasets!I428 -> 0.1249 | ... CX13: =Datasets!CW428 -> 0.146
